Workbook
Name Segment_POOLER: #N/A
Name Segment_POS: #N/A
Name Segment_SEASON: #N/A

Sheet PTS
AD1: SEASON | AE1: LEADER | AF1: DAYS LED | AG1: STATUS
C2: 2024 | D2: FOW | E2: DEF | F2: GOA | G2: TEAM | H2: PTS | I2: PTS/G | K2: LEAD CHANGE 2024 | L2: DATE | M2: PTS | N2: DL | P2: Gap To Leader | Q2: 2024 | R2: 2023 | S2: 2022 | T2: 2021 | U2: 2020 | V2: 2019 | W2: 2018 | X2: 2017 | Y2: AVG | AD2: 2020 | AE2: DESROSIERS | AF2: 152 | AG2: CHAMP | AJ2: Étiquettes de lignes | AK2: DAYS LED | AL2: SEASONS LED | AM2: Most Recent
A3: 1 | C3: MIOUSSE | D3: =VLOOKUP($C3,'24'!AA:AE,2,FALSE) -> 644 | E3: =VLOOKUP($C3,'24'!AA:AE,3,FALSE) -> 193 | F3: =VLOOKUP($C3,'24'!AA:AE,4,FALSE) -> 88 | G3: =VLOOKUP($C3,'24'!AA:AE,5,FALSE) -> 111 | H3: =SUM(D3:G3) -> 1036 | I3: 1.037 | K3: BLIER | L3: 45210 | M3: 7 | N3: 1 | P3: Winner | Q3: =MAX(H3:H14) -> 1036 | R3: =MAX(H20:H31) -> 1045 | S3: 1011 | T3: 646 | U3: 886 | V3: 999 | W3: 996 | X3: 895 | AD3: 2023 | AE3: DESROSIERS | AF3: 149 | AG3: CHAMP | AI3: 1 | AJ3: DESROSIERS | AK3: 386 | AL3: 4 | AM3: 2023
A4: =A3+1 -> 2 | C4: CHABOT | D4: =VLOOKUP($C4,'24'!AA:AE,2,FALSE) -> 640 | E4: =VLOOKUP($C4,'24'!AA:AE,3,FALSE) -> 182 | F4: =VLOOKUP($C4,'24'!AA:AE,4,FALSE) -> 83 | G4: =VLOOKUP($C4,'24'!AA:AE,5,FALSE) -> 98 | H4: =SUM(D4:G4) -> 1003 | I4: 0.986 | K4: MIOUSSE | L4: 45211 | M4: 17 | N4: 1 | P4: BEAUCHEMIN | Q4: 0.90540541 | R4: =VLOOKUP(P4,$C$19:$I$31,6,FALSE)/$R$3 -> 0.93205742 | S4: 0.96043521 | T4: 0.88544892 | U4: 0.7765237 | V4: 0.96896897 | W4: 1 | X4: 0.94189944 | Y4: =AVERAGE(Q4:X4) -> 0.92134238 | AD4: 2018 | AE4: BEAUCHEMIN | AF4: 142 | AG4: CHAMP | AI4: 2 | AJ4: BLIER | AK4: 154 | AL4: 5 | AM4: 2024
A5: =A4+1 -> 3 | C5: DIEGO | D5: =VLOOKUP($C5,'24'!AA:AE,2,FALSE) -> 640 | E5: =VLOOKUP($C5,'24'!AA:AE,3,FALSE) -> 180 | F5: =VLOOKUP($C5,'24'!AA:AE,4,FALSE) -> 68 | G5: =VLOOKUP($C5,'24'!AA:AE,5,FALSE) -> 104 | H5: =SUM(D5:G5) -> 992 | I5: 1.034 | K5: PICARD | L5: 45212 | M5: 20 | N5: 1 | P5: PICARD | Q5: 0.88610039 | R5: =VLOOKUP(P5,$C$19:$I$31,6,FALSE)/$R$3 -> 0.89665072 | S5: 1 | T5: 0.90712074 | U5: 0.87810384 | V5: 0.86486486 | W5: 0.8624498 | X5: 1 | Y5: =AVERAGE(Q5:X5) -> 0.91191129 | AD5: 2022 | AE5: PICARD | AF5: 102 | AG5: CHAMP | AI5: 3 | AJ5: BEAUCHEMIN | AK5: 150 | AL5: 3 | AM5: 2024
A6: =A5+1 -> 4 | C6: BLIER | D6: =VLOOKUP($C6,'24'!AA:AE,2,FALSE) -> 636 | E6: =VLOOKUP($C6,'24'!AA:AE,3,FALSE) -> 142 | F6: =VLOOKUP($C6,'24'!AA:AE,4,FALSE) -> 60 | G6: =VLOOKUP($C6,'24'!AA:AE,5,FALSE) -> 113 | H6: =SUM(D6:G6) -> 951 | I6: 0.987 | K6: BLIER | L6: 45213 | M6: 24 | N6: 2 | P6: CHABOT | Q6: 0.96814672 | R6: =VLOOKUP(P6,$C$19:$I$31,6,FALSE)/$R$3 -> 0.96650718 | S6: 0.9950544 | T6: 0.81888545 | U6: 0.82167043 | V6: 0.89089089 | W6: 0.90763052 | X6: 0.9027933 | Y6: =AVERAGE(Q6:X6) -> 0.90894736 | AD6: 2024 | AE6: MIOUSSE | AF6: =$N$32 -> 99 | AG6: CHAMP | AI6: 4 | AJ6: PICARD | AK6: 104 | AL6: 3 | AM6: 2024
A7: =A6+1 -> 5 | C7: BEAUCHEMIN | D7: =VLOOKUP($C7,'24'!AA:AE,2,FALSE) -> 599 | E7: =VLOOKUP($C7,'24'!AA:AE,3,FALSE) -> 167 | F7: =VLOOKUP($C7,'24'!AA:AE,4,FALSE) -> 91 | G7: =VLOOKUP($C7,'24'!AA:AE,5,FALSE) -> 81 | H7: =SUM(D7:G7) -> 938 | I7: 0.956 | K7: MIOUSSE | L7: 45214 | M7: 17 | N7: 5 | P7: DESROSIERS | Q7: 0.67760618 | R7: =VLOOKUP(P7,$C$19:$I$31,6,FALSE)/$R$3 -> 1 | S7: 0.76953511 | T7: 1 | U7: 1 | V7: 1 | W7: 0.90361446 | X7: 0.89832402 | Y7: =AVERAGE(Q7:X7) -> 0.90613497 | AD7: 2021 | AE7: BLIER | AF7: 87 | AI7: 5 | AJ7: MIOUSSE | AK7: 103 | AL7: 4 | AM7: 2024
A8: =A7+1 -> 6 | C8: CONSTANTIN | D8: =VLOOKUP($C8,'24'!AA:AE,2,FALSE) -> 562 | E8: =VLOOKUP($C8,'24'!AA:AE,3,FALSE) -> 175 | F8: =VLOOKUP($C8,'24'!AA:AE,4,FALSE) -> 98 | G8: =VLOOKUP($C8,'24'!AA:AE,5,FALSE) -> 98 | H8: =SUM(D8:G8) -> 933 | I8: 0.916 | K8: MOROTTI | L8: 45218 | M8: 51 | N8: 2 | P8: CON/FOR | Q8: 0.90057915 | R8: 0.85263158 | S8: 0.91196835 | T8: 0.82817337 | U8: 0.82844244 | V8: 0.95595596 | W8: 0.95983936 | X8: 0.97653631 | Y8: =AVERAGE(Q8:X8) -> 0.90176581 | AD8: 2019 | AE8: FORCIER | AF8: 77 | AI8: 6 | AJ8: CHABOT | AK8: 87 | AL8: 4 | AM8: 2023
A9: =A8+1 -> 7 | C9: MOROTTI | D9: =VLOOKUP($C9,'24'!AA:AE,2,FALSE) -> 605 | E9: =VLOOKUP($C9,'24'!AA:AE,3,FALSE) -> 147 | F9: =VLOOKUP($C9,'24'!AA:AE,4,FALSE) -> 65 | G9: =VLOOKUP($C9,'24'!AA:AE,5,FALSE) -> 107 | H9: =SUM(D9:G9) -> 924 | I9: 0.959 | K9: DIEGO | L9: 45220 | M9: 62 | N9: 1 | P9: BLIER | Q9: 0.91795367 | R9: =VLOOKUP(P9,$C$19:$I$31,6,FALSE)/$R$3 -> 0.95598086 | S9: 0.88625124 | T9: 0.9752322 | U9: 0.84424379 | V9: 0.86986987 | W9: 0.7811245 | X9: DNP | Y9: =AVERAGE(Q9:X9) -> 0.89009373 | AD9: 2022 | AE9: CHABOT | AF9: 66 | AI9: 7 | AJ9: FORCIER | AK9: 77 | AL9: 1 | AM9: 2019
A10: =A9+1 -> 8 | C10: PICARD | D10: =VLOOKUP($C10,'24'!AA:AE,2,FALSE) -> 576 | E10: =VLOOKUP($C10,'24'!AA:AE,3,FALSE) -> 152 | F10: =VLOOKUP($C10,'24'!AA:AE,4,FALSE) -> 88 | G10: =VLOOKUP($C10,'24'!AA:AE,5,FALSE) -> 102 | H10: =SUM(D10:G10) -> 918 | I10: 0.952 | K10: BEAUCHEMIN | L10: 45221 | M10: 77 | N10: 1 | P10: MIOUSSE | Q10: 1 | R10: =VLOOKUP(P10,$C$19:$I$31,6,FALSE)/$R$3 -> 0.88229665 | S10: 0.884273 | T10: 0.88544892 | U10: 0.81602709 | V10: 0.79479479 | W10: 0.84437751 | X10: 0.83687151 | Y10: =AVERAGE(Q10:X10) -> 0.86801118 | AD10: 2019 | AE10: DESROSIERS | AF10: 56 | AG10: CHAMP | AI10: 8 | AJ10: DIEGO | AK10: 66 | AL10: 3 | AM10: 2024
A11: =A10+1 -> 9 | C11: LESSARD | D11: =VLOOKUP($C11,'24'!AA:AE,2,FALSE) -> 555 | E11: =VLOOKUP($C11,'24'!AA:AE,3,FALSE) -> 143 | F11: =VLOOKUP($C11,'24'!AA:AE,4,FALSE) -> 72 | G11: =VLOOKUP($C11,'24'!AA:AE,5,FALSE) -> 109 | H11: =SUM(D11:G11) -> 879 | I11: 0.902 | K11: LESSARD | L11: 45222 | M11: 79 | N11: 2 | P11: MOROTTI | Q11: 0.89189189 | R11: =VLOOKUP(P11,$C$19:$I$31,6,FALSE)/$R$3 -> 0.80574163 | S11: 0.86547972 | T11: 0.93188854 | U11: 0.82167043 | V11: 0.82382382 | W11: 0.8373494 | X11: 0.8972067 | Y11: =AVERAGE(Q11:X11) -> 0.85938152 | AD11: 2019 | AE11: HENAULT | AF11: 54 | AI11: 9 | AJ11: HENAULT | AK11: 54 | AL11: 1 | AM11: 2019
A12: =A11+1 -> 10 | C12: HENAULT | D12: =VLOOKUP($C12,'24'!AA:AE,2,FALSE) -> 486 | E12: =VLOOKUP($C12,'24'!AA:AE,3,FALSE) -> 150 | F12: =VLOOKUP($C12,'24'!AA:AE,4,FALSE) -> 83 | G12: =VLOOKUP($C12,'24'!AA:AE,5,FALSE) -> 110 | H12: =SUM(D12:G12) -> 829 | I12: 0.88 | K12: DIEGO | L12: 45224 | M12: 94 | N12: 3 | P12: LESSARD | Q12: 0.8484556 | R12: =VLOOKUP(P12,$C$19:$I$31,6,FALSE)/$R$3 -> 0.8076555 | S12: 0.88031652 | T12: 0.95665635 | U12: 0.74943567 | V12: 0.75975976 | W12: 0.81726908 | X12: 0.92067039 | Y12: =AVERAGE(Q12:X12) -> 0.84252736 | AD12: 2024 | AE12: DIEGO | AF12: 41 | AI12: 10 | AJ12: CONSTANTIN | AK12: 31 | AL12: 2 | AM12: 2024
A13: =A12+1 -> 11 | C13: ROBB | D13: =VLOOKUP($C13,'24'!AA:AE,2,FALSE) -> 587 | E13: =VLOOKUP($C13,'24'!AA:AE,3,FALSE) -> 109 | F13: =VLOOKUP($C13,'24'!AA:AE,4,FALSE) -> 22 | G13: =VLOOKUP($C13,'24'!AA:AE,5,FALSE) -> 47 | H13: =SUM(D13:G13) -> 765 | I13: 0.787 | K13: BEAUCHEMIN | L13: 45226 | M13: 103 | N13: 3 | P13: DIEGO | Q13: 0.95752896 | R13: =VLOOKUP(P13,$C$19:$I$31,6,FALSE)/$R$3 -> 0.93397129 | S13: 0.88526212 | T13: 0.81424149 | U13: 0.7234763 | V13: 0.78078078 | W13: 0.80421687 | X13: 0.81564246 | Y13: =AVERAGE(Q13:X13) -> 0.83939003 | AD13: 2024 | AE13: BLIER | AF13: 35 | AI13: 11 | AJ13: LESSARD | AK13: 19 | AL13: 2 | AM13: 2024
A14: =A13+1 -> 12 | C14: DESROSIERS | D14: =VLOOKUP($C14,'24'!AA:AE,2,FALSE) -> 447 | E14: =VLOOKUP($C14,'24'!AA:AE,3,FALSE) -> 110 | F14: =VLOOKUP($C14,'24'!AA:AE,4,FALSE) -> 93 | G14: =VLOOKUP($C14,'24'!AA:AE,5,FALSE) -> 52 | H14: =SUM(D14:G14) -> 702 | I14: 0.743 | K14: DIEGO | L14: 45228 | M14: 114 | N14: 5 | P14: HENAULT | Q14: 0.80019305 | R14: =VLOOKUP(P14,$C$19:$I$31,6,FALSE)/$R$3 -> 0.77416268 | S14: 0.83481701 | T14: 0.82817337 | U14: 0.80699774 | V14: 0.91191191 | W14: 0.89257028 | X14: 0.77988827 | Y14: =AVERAGE(Q14:X14) -> 0.82858929 | AD14: 2021 | AE14: DESROSIERS | AF14: 29 | AG14: CHAMP | AI14: 12 | AJ14: MOROTTI | AK14: 16 | AL14: 3 | AM14: 2024
K15: BEAUCHEMIN | L15: 45230 | M15: 103 | N15: 6 | P15: ROB/DAV | Q15: 0.73841699 | R15: 0.7722488 | S15: 0.8793274 | T15: 0.79411765 | U15: 0.84988713 | V15: 0.87287287 | W15: DNP | X15: DNP | Y15: =AVERAGE(Q15:X15) -> 0.81781181 | AD15: 2022 | AE15: CONSTANTIN | AF15: 26 | AI15: 13 | AJ15: ROBB | AK15: 7 | AL15: 1 | AM15: 2022
C16: AVG | D16: =AVERAGE(D3:D15) -> 581.41667 | E16: =AVERAGE(E3:E15) -> 154.16667 | F16: =AVERAGE(F3:F15) -> 75.916667 | G16: =AVERAGE(G3:G15) -> 94.333333 | H16: =AVERAGE(H3:H15) -> 905.83333 | I16: =AVERAGE(I3:I15) -> 0.92825 | K16: DIEGO | L16: 45233 | M16: 134 | N16: 7 | P16: AVG | Q16: =AVERAGE(Q4:Q15) -> 0.8743565 | R16: =AVERAGE(R4:R15) -> 0.88165869 | S16: =AVERAGE(S4:S15) -> 0.89606001 | T16: =AVERAGE(T4:T15) -> 0.88544892 | U16: =AVERAGE(U4:U15) -> 0.82637321 | V16: =AVERAGE(V4:V15) -> 0.87454121 | W16: =AVERAGE(W4:W15) -> 0.87367652 | X16: =AVERAGE(X4:X15) -> 0.89698324 | AD16: 2023 | AE16: BLIER | AF16: 24 | AJ16: (vide)
K17: BLIER | L17: 45235 | M17: 144 | N17: 4 | AD17: 2018 | AE17: DIEGO | AF17: 24 | AJ17: Total général | AK17: 1254 | AL17: 36 | AM17: 2024
K18: CONSTANTIN | L18: 45237 | M18: 155 | N18: 3 | P18: Gap To Leader | Q18: 2024 | R18: 2023 | S18: 2022 | T18: 2021 | U18: 2020 | V18: 2019 | W18: 2018 | X18: 2017 | Y18: AVG | AD18: 2021 | AE18: LESSARD | AF18: 17
C19: 2023 | D19: FOW | E19: DEF | F19: GOA | G19: TEAM | H19: PTS | I19: PTS/G | K19: BLIER | L19: 45240 | M19: 173 | N19: 6 | P19: Winner | Q19: 1036 | R19: 1045 | S19: 1011 | T19: 646 | U19: 886 | V19: 999 | W19: 996 | X19: 895 | AD19: 2018 | AE19: CHABOT | AF19: 10
A20: 1 | C20: DESROSIERS | D20: 694 | E20: 178 | F20: 66 | G20: 107 | H20: =SUM(D20:G20) -> 1045 | I20: 1.0429142 | K20: MIOUSSE | L20: 45242 | M20: 186 | N20: 6 | P20: BEAUCHEMIN | Q20: 98 | R20: 71 | S20: =$S$19-VLOOKUP(P20,$C$37:$H$48,6,FALSE) -> 40 | T20: =$T$19-VLOOKUP(P20,$C$54:$H$65,6,FALSE) -> 74 | U20: =$U$19-VLOOKUP(P20,$C$71:$H$82,6,FALSE) -> 198 | V20: =$V$19-VLOOKUP(P20,$C$88:$H$99,6,FALSE) -> 31 | W20: =$W$19-VLOOKUP(P20,$C$105:$H$116,6,FALSE) -> 0 | X20: =$X$19-VLOOKUP(P20,$C$121:$H$132,6,FALSE) -> 52 | Y20: =AVERAGE(Q20:X20) -> 70.5 | AD20: 2018 | AE20: MOROTTI | AF20: 10
A21: =A20+1 -> 2 | C21: CHABOT | D21: 613 | E21: 186 | F21: 102 | G21: 109 | H21: =SUM(D21:G21) -> 1010 | I21: 0.99311701 | K21: CONSTANTIN | L21: 45243 | M21: 155 | N21: 5 | P21: CHABOT | Q21: 33 | R21: 35 | S21: =$S$19-VLOOKUP(P21,$C$37:$H$48,6,FALSE) -> 5 | T21: =$T$19-VLOOKUP(P21,$C$54:$H$65,6,FALSE) -> 117 | U21: =$U$19-VLOOKUP(P21,$C$71:$H$82,6,FALSE) -> 158 | V21: =$V$19-VLOOKUP(P21,$C$88:$H$99,6,FALSE) -> 109 | W21: =$W$19-VLOOKUP(P21,$C$105:$H$116,6,FALSE) -> 92 | X21: =$X$19-VLOOKUP(P21,$C$121:$H$132,6,FALSE) -> 87 | Y21: =AVERAGE(Q21:X21) -> 79.5 | AD21: 2023 | AE21: CHABOT | AF21: 8
A22: =A21+1 -> 3 | C22: BLIER | D22: 661 | E22: 181 | F22: 44 | G22: 113 | H22: =SUM(D22:G22) -> 999 | I22: 1.0384615 | K22: BLIER | L22: 45245 | M22: 202 | N22: 29 | P22: PICARD | Q22: 118 | R22: 108 | S22: =$S$19-VLOOKUP(P22,$C$37:$H$48,6,FALSE) -> 0 | T22: =$T$19-VLOOKUP(P22,$C$54:$H$65,6,FALSE) -> 60 | U22: =$U$19-VLOOKUP(P22,$C$71:$H$82,6,FALSE) -> 108 | V22: =$V$19-VLOOKUP(P22,$C$88:$H$99,6,FALSE) -> 135 | W22: =$W$19-VLOOKUP(P22,$C$105:$H$116,6,FALSE) -> 137 | X22: =$X$19-VLOOKUP(P22,$C$121:$H$132,6,FALSE) -> 0 | Y22: =AVERAGE(Q22:X22) -> 83.25 | AD22: 2022 | AE22: ROBB | AF22: 7
A23: =A22+1 -> 4 | C23: DIEGO | D23: 648 | E23: 146 | F23: 89 | G23: 93 | H23: =SUM(D23:G23) -> 976 | I23: 0.98486377 | K23: DIEGO | L23: 45268 | M23: 322 | N23: 21 | P23: CON/FOR | Q23: 103 | R23: 154 | S23: 89 | T23: 83 | U23: 152 | V23: 44 | W23: 40 | X23: 21 | Y23: =AVERAGE(Q23:X23) -> 85.75 | AD23: 2020 | AE23: BLIER | AF23: 7
A24: =A23+1 -> 5 | C24: BEAUCHEMIN | D24: 613 | E24: 192 | F24: 88 | G24: 81 | H24: =SUM(D24:G24) -> 974 | I24: 0.96819085 | K24: BLIER | L24: 45282 | M24: 398 | N24: 35 | P24: DESROSIERS | Q24: 334 | R24: 0 | S24: =$S$19-VLOOKUP(P24,$C$37:$H$48,6,FALSE) -> 233 | T24: =$T$19-VLOOKUP(P24,$C$54:$H$65,6,FALSE) -> 0 | U24: =$U$19-VLOOKUP(P24,$C$71:$H$82,6,FALSE) -> 0 | V24: =$V$19-VLOOKUP(P24,$C$88:$H$99,6,FALSE) -> 0 | W24: =$W$19-VLOOKUP(P24,$C$105:$H$116,6,FALSE) -> 96 | X24: =$X$19-VLOOKUP(P24,$C$121:$H$132,6,FALSE) -> 91 | Y24: =AVERAGE(Q24:X24) -> 94.25 | AD24: 2024 | AE24: BEAUCHEMIN | AF24: 6
A25: =A24+1 -> 6 | C25: PICARD | D25: 610 | E25: 133 | F25: 103 | G25: 91 | H25: =SUM(D25:G25) -> 937 | I25: 0.93141153 | K25: DIEGO | L25: 45288 | M25: 420 | N25: 22 | P25: BLIER | Q25: 85 | R25: 46 | S25: =$S$19-VLOOKUP(P25,$C$37:$H$48,6,FALSE) -> 115 | T25: =$T$19-VLOOKUP(P25,$C$54:$H$65,6,FALSE) -> 16 | U25: =$U$19-VLOOKUP(P25,$C$71:$H$82,6,FALSE) -> 138 | V25: =$V$19-VLOOKUP(P25,$C$88:$H$99,6,FALSE) -> 130 | W25: =$W$19-VLOOKUP(P25,$C$105:$H$116,6,FALSE) -> 218 | X25: DNP | Y25: =AVERAGE(Q25:X25) -> 106.85714 | AD25: 2024 | AE25: CONSTANTIN | AF25: 5
A26: =A25+1 -> 7 | C26: MIOUSSE | D26: 572 | E26: 150 | F26: 97 | G26: 103 | H26: =SUM(D26:G26) -> 922 | I26: 0.94370522 | K26: MIOUSSE | L26: 45289 | M26: 427 | N26: 9 | P26: MIOUSSE | Q26: 0 | R26: 123 | S26: =$S$19-VLOOKUP(P26,$C$37:$H$48,6,FALSE) -> 117 | T26: =$T$19-VLOOKUP(P26,$C$54:$H$65,6,FALSE) -> 74 | U26: =$U$19-VLOOKUP(P26,$C$71:$H$82,6,FALSE) -> 163 | V26: =$V$19-VLOOKUP(P26,$C$88:$H$99,6,FALSE) -> 205 | W26: =$W$19-VLOOKUP(P26,$C$105:$H$116,6,FALSE) -> 155 | X26: =$X$19-VLOOKUP(P26,$C$121:$H$132,6,FALSE) -> 146 | Y26: =AVERAGE(Q26:X26) -> 122.875 | AD26: 2023 | AE26: MOROTTI | AF26: 4
A27: =A26+1 -> 8 | C27: CONSTANTIN | D27: 579 | E27: 149 | F27: 54 | G27: 109 | H27: =SUM(D27:G27) -> 891 | I27: 0.888335 | K27: DIEGO | L27: 45292 | M27: 450 | N27: 27 | P27: MOROTTI | Q27: 112 | R27: 203 | S27: =$S$19-VLOOKUP(P27,$C$37:$H$48,6,FALSE) -> 136 | T27: =$T$19-VLOOKUP(P27,$C$54:$H$65,6,FALSE) -> 44 | U27: =$U$19-VLOOKUP(P27,$C$71:$H$82,6,FALSE) -> 158 | V27: =$V$19-VLOOKUP(P27,$C$88:$H$99,6,FALSE) -> 176 | W27: =$W$19-VLOOKUP(P27,$C$105:$H$116,6,FALSE) -> 162 | X27: =$X$19-VLOOKUP(P27,$C$121:$H$132,6,FALSE) -> 92 | Y27: =AVERAGE(Q27:X27) -> 135.375 | AD27: 2021 | AE27: CHABOT | AF27: 3
A28: =A27+1 -> 9 | C28: LESSARD | D28: 523 | E28: 151 | F28: 75 | G28: 95 | H28: =SUM(D28:G28) -> 844 | I28: 0.87190083 | K28: MIOUSSE | L28: 45297 | M28: 478 | N28: 63 | P28: DIEGO | Q28: 44 | R28: 69 | S28: =$S$19-VLOOKUP(P28,$C$37:$H$48,6,FALSE) -> 116 | T28: =$T$19-VLOOKUP(P28,$C$54:$H$65,6,FALSE) -> 120 | U28: =$U$19-VLOOKUP(P28,$C$71:$H$82,6,FALSE) -> 245 | V28: =$V$19-VLOOKUP(P28,$C$88:$H$99,6,FALSE) -> 219 | W28: =$W$19-VLOOKUP(P28,$C$105:$H$116,6,FALSE) -> 195 | X28: =$X$19-VLOOKUP(P28,$C$121:$H$132,6,FALSE) -> 165 | Y28: =AVERAGE(Q28:X28) -> 146.625 | AD28: 2023 | AE28: BEAUCHEMIN | AF28: 2
A29: =A28+1 -> 10 | C29: MOROTTI | D29: 551 | E29: 100 | F29: 93 | G29: 98 | H29: =SUM(D29:G29) -> 842 | I29: 0.85136502 | K29: DIEGO | L29: 45351 | M29: 736 | N29: 28 | P29: LESSARD | Q29: 157 | R29: 201 | S29: =$S$19-VLOOKUP(P29,$C$37:$H$48,6,FALSE) -> 121 | T29: =$T$19-VLOOKUP(P29,$C$54:$H$65,6,FALSE) -> 28 | U29: =$U$19-VLOOKUP(P29,$C$71:$H$82,6,FALSE) -> 222 | V29: =$V$19-VLOOKUP(P29,$C$88:$H$99,6,FALSE) -> 240 | W29: =$W$19-VLOOKUP(P29,$C$105:$H$116,6,FALSE) -> 182 | X29: =$X$19-VLOOKUP(P29,$C$121:$H$132,6,FALSE) -> 71 | Y29: =AVERAGE(Q29:X29) -> 152.75 | AD29: 2021 | AE29: MIOUSSE | AF29: 2
A30: =A29+1 -> 11 | C30: HENAULT | D30: 450 | E30: 160 | F30: 88 | G30: 111 | H30: =SUM(D30:G30) -> 809 | I30: 0.86709539 | K30: MIOUSSE | L30: 45352 | M30: 744 | N30: 65 | P30: HENAULT | Q30: 207 | R30: 236 | S30: =$S$19-VLOOKUP(P30,$C$37:$H$48,6,FALSE) -> 167 | T30: =$T$19-VLOOKUP(P30,$C$54:$H$65,6,FALSE) -> 111 | U30: =$U$19-VLOOKUP(P30,$C$71:$H$82,6,FALSE) -> 171 | V30: =$V$19-VLOOKUP(P30,$C$88:$H$99,6,FALSE) -> 88 | W30: =$W$19-VLOOKUP(P30,$C$105:$H$116,6,FALSE) -> 107 | X30: =$X$19-VLOOKUP(P30,$C$121:$H$132,6,FALSE) -> 197 | Y30: =AVERAGE(Q30:X30) -> 160.5 | AD30: 2024 | AE30: MOROTTI | AF30: 2
A31: =A30+1 -> 12 | C31: ROBB | D31: 478 | E31: 164 | F31: 73 | G31: 92 | H31: =SUM(D31:G31) -> 807 | I31: 0.81928934 | K31: DIEGO | L31: 45354 | M31: 751 | N31: 41 | P31: ROB/DAV | Q31: 271 | R31: 238 | S31: 122 | T31: 133 | U31: 133 | V31: 127 | W31: DNP | X31: DNP | Y31: =AVERAGE(Q31:X31) -> 170.66667 | AD31: 2024 | AE31: LESSARD | AF31: 2
K32: MIOUSSE | L32: 45367 | M32: 810 | N32: 99 | P32: AVG | Q32: =AVERAGE(Q20:Q31) -> 130.16667 | R32: =AVERAGE(R20:R31) -> 123.66667 | S32: =AVERAGE(S20:S31) -> 105.08333 | T32: =AVERAGE(T20:T31) -> 71.666667 | U32: =AVERAGE(U20:U31) -> 153.83333 | V32: =AVERAGE(V20:V31) -> 125.33333 | W32: =AVERAGE(W20:W31) -> 125.81818 | X32: =AVERAGE(X20:X31) -> 92.2 | AD32: 2018 | AE32: MIOUSSE | AF32: 1
C33: AVG | D33: =AVERAGE(D20:D32) -> 582.66667 | E33: =AVERAGE(E20:E32) -> 157.5 | F33: =AVERAGE(F20:F32) -> 81 | G33: =AVERAGE(G20:G32) -> 100.16667 | H33: =AVERAGE(H20:H32) -> 921.33333 | I33: =AVERAGE(I20:I32) -> 0.93338747 | AD33: 2023 | AE33: PICARD | AF33: 1
AD34: 2021 | AE34: DIEGO | AF34: 1
K35: LEAD CHANGE 2023 | L35: DATE | M35: PTS | N35: DL | AD35: 2019 | AE35: BLIER | AF35: 1
C36: 2022 | D36: FOW | E36: DEF | F36: GOA | G36: TEAM | H36: PTS | I36: PTS/G | K36: PICARD | L36: 44842 | M36: 2 | N36: 1 | AD36: 2023 | AE36: MIOUSSE | AF36: 1
A37: 1 | C37: PICARD | D37: 626 | E37: 179 | F37: 93 | G37: 113 | H37: 1011 | I37: 1.06 | K37: MOROTTI | L37: 44843 | M37: 3 | N37: 4 | AD37: 2024 | AE37: PICARD | AF37: 1
A38: =A37+1 -> 2 | C38: CHABOT | D38: 632 | E38: 159 | F38: 93 | G38: 122 | H38: 1006 | I38: 1.03 | K38: DESROSIERS | L38: 44847 | M38: 16 | N38: 10
A39: =A38+1 -> 3 | C39: BEAUCHEMIN | D39: 617 | E39: 169 | F39: 96 | G39: 89 | H39: 971 | I39: 0.997 | K39: CHABOT | L39: 44857 | M39: 80 | N39: 1
A40: =A39+1 -> 4 | C40: CONSTANTIN | D40: 557 | E40: 171 | F40: 90 | G40: 104 | H40: 922 | I40: 0.98 | K40: DESROSIERS | L40: 44858 | M40: 81 | N40: 11
A41: =A40+1 -> 5 | C41: BLIER | D41: 551 | E41: 114 | F41: 116 | G41: 115 | H41: 896 | I41: 0.928 | K41: CHABOT | L41: 44859 | M41: 80 | N41: 2
A42: =A41+1 -> 6 | C42: DIEGO | D42: 550 | E42: 191 | F42: 38 | G42: 116 | H42: 895 | I42: 0.955 | K42: DESROSIERS | L42: 44860 | M42: 81 | N42: 14
A43: =A42+1 -> 7 | C43: MIOUSSE | D43: 617 | E43: 107 | F43: 60 | G43: 110 | H43: 894 | I43: 0.982 | K43: MIOUSSE | L43: 44863 | M43: 109 | N43: 1
A44: =A43+1 -> 8 | C44: LESSARD | D44: 550 | E44: 168 | F44: 53 | G44: 119 | H44: 890 | I44: 0.939 | K44: DESROSIERS | L44: 44864 | M44: 121 | N44: 39
A45: =A44+1 -> 9 | C45: ROBB | D45: 549 | E45: 155 | F45: 91 | G45: 94 | H45: 889 | I45: 0.931 | K45: BLIER | L45: 44889 | M45: 259 | N45: 2
A46: =A45+1 -> 10 | C46: MOROTTI | D46: 503 | E46: 175 | F46: 90 | G46: 107 | H46: 875 | I46: 0.921 | K46: DESROSIERS | L46: 44891 | M46: 268 | N46: 40
A47: =A46+1 -> 11 | C47: HENAULT | D47: 558 | E47: 137 | F47: 49 | G47: 100 | H47: 844 | I47: 0.888 | K47: BLIER | L47: 44892 | M47: 280 | N47: 4
A48: =A47+1 -> 12 | C48: DESROSIERS | D48: 505 | E48: 110 | F48: 79 | G48: 84 | H48: 778 | I48: 0.87 | K48: DESROSIERS | L48: 44894 | M48: 283 | N48: 41
K49: BEAUCHEMIN | L49: 44895 | M49: 293 | N49: 2
C50: AVG | D50: =AVERAGE(D37:D49) -> 567.91667 | E50: =AVERAGE(E37:E49) -> 152.91667 | F50: =AVERAGE(F37:F49) -> 79 | G50: =AVERAGE(G37:G49) -> 106.08333 | H50: =AVERAGE(H37:H49) -> 905.91667 | I50: =AVERAGE(I37:I49) -> 0.95675 | K50: CHABOT | L50: 44897 | M50: 307 | N50: 4
K51: DESROSIERS | L51: 44899 | M51: 321 | N51: 44
K52: CHABOT | L52: 44902 | M52: 338 | N52: 5
C53: 2021 | D53: FOW | E53: DEF | F53: GOA | G53: TEAM | H53: PTS | I53: PTS/G | K53: BLIER | L53: 44903 | M53: 342 | N53: 5
A54: 1 | C54: DESROSIERS | D54: 438 | E54: 86 | F54: 40 | G54: 82 | H54: =SUM(D54:G54) -> 646 | I54: 0.96 | K54: CHABOT | L54: 44904 | M54: 355 | N54: 6
A55: =A54+1 -> 2 | C55: BLIER | D55: 366 | E55: 115 | F55: 72 | G55: 77 | H55: =SUM(D55:G55) -> 630 | I55: 0.935 | K55: BLIER | L55: 44905 | M55: 363 | N55: 9
A56: =A55+1 -> 3 | C56: LESSARD | D56: 368 | E56: 126 | F56: 42 | G56: 82 | H56: =SUM(D56:G56) -> 618 | I56: 0.909 | K56: DESROSIERS | L56: 44909 | M56: 381 | N56: 48
A57: =A56+1 -> 4 | C57: MOROTTI | D57: 358 | E57: 108 | F57: 63 | G57: 73 | H57: =SUM(D57:G57) -> 602 | I57: 0.881 | K57: CHABOT | L57: 44913 | M57: 409 | N57: 7
A58: =A57+1 -> 5 | C58: PICARD | D58: 367 | E58: 115 | F58: 44 | G58: 60 | H58: =SUM(D58:G58) -> 586 | I58: 0.875 | K58: DESROSIERS | L58: 44914 | M58: 416 | N58: 53
A59: =A58+1 -> 6 | C59: MIOUSSE | D59: 393 | E59: 67 | F59: 35 | G59: 77 | H59: =SUM(D59:G59) -> 572 | I59: 0.883 | K59: BLIER | L59: 44919 | M59: 447 | N59: 24
A60: =A59+1 -> 7 | C60: BEAUCHEMIN | D60: 321 | E60: 107 | F60: 86 | G60: 58 | H60: =SUM(D60:G60) -> 572 | I60: 0.851 | K60: DESROSIERS | L60: 44934 | M60: 518 | N60: 83
A61: =A60+1 -> 8 | C61: CONSTANTIN | D61: 387 | E61: 70 | F61: 46 | G61: 60 | H61: =SUM(D61:G61) -> 563 | I61: 0.857 | K61: CHABOT | L61: 44964 | M61: 663 | N61: 8
A62: =A61+1 -> 9 | C62: HENAULT | D62: 288 | E62: 86 | F62: 86 | G62: 75 | H62: =SUM(D62:G62) -> 535 | I62: 0.809 | K62: DESROSIERS | L62: 44965 | M62: 669 | N62: 149
A63: =A62+1 -> 10 | C63: CHABOT | D63: 352 | E63: 86 | F63: 36 | G63: 55 | H63: =SUM(D63:G63) -> 529 | I63: 0.824
A64: =A63+1 -> 11 | C64: DIEGO | D64: 304 | E64: 105 | F64: 67 | G64: 50 | H64: =SUM(D64:G64) -> 526 | I64: 0.769 | K64: LEAD CHANGE 2022 | L64: DATE | M64: PTS | N64: DL
A65: =A64+1 -> 12 | C65: ROBB | D65: 322 | E65: 73 | F65: 55 | G65: 63 | H65: =SUM(D65:G65) -> 513 | I65: 0.786 | K65: CONSTANTIN | L65: 44482 | M65: 8 | N65: 6
K66: CHABOT | L66: 44488 | M66: 43 | N66: 41
C67: AVG | D67: =AVERAGE(D54:D66) -> 355.33333 | E67: =AVERAGE(E54:E66) -> 95.333333 | F67: =AVERAGE(F54:F66) -> 56 | G67: =AVERAGE(G54:G66) -> 67.666667 | H67: =AVERAGE(H54:H66) -> 574.33333 | I67: =AVERAGE(I54:I66) -> 0.86158333 | K67: PICARD | L67: 44529 | M67: 262 | N67: 18
K68: CONSTANTIN | L68: 44547 | M68: 342 | N68: 25
K69: CHABOT | L69: 44566 | M69: 394 | N69: 43
C70: 2020 | D70: FOW | E70: DEF | F70: GOA | G70: TEAM | H70: PTS | I70: PTS/G | K70: CONSTANTIN | L70: 44568 | M70: 403 | N70: 26
A71: 1 | C71: DESROSIERS | D71: 608 | E71: 97 | F71: 89 | G71: 92 | H71: =SUM(D71:G71) -> 886 | I71: 1.014 | K71: CHABOT | L71: 44569 | M71: 406 | N71: 44
A72: =A71+1 -> 2 | C72: PICARD | D72: 442 | E72: 168 | F72: 74 | G72: 94 | H72: =SUM(D72:G72) -> 778 | I72: 0.925 | K72: ROBB | L72: 44570 | M72: 415 | N72: 7
A73: =A72+1 -> 3 | C73: ROBB | D73: 456 | E73: 115 | F73: 90 | G73: 92 | H73: =SUM(D73:G73) -> 753 | I73: 0.897 | K73: CHABOT | L73: 44577 | M73: 445 | N73: =L73-L72+N71 -> 51
A74: =A73+1 -> 4 | C74: BLIER | D74: 452 | E74: 136 | F74: 74 | G74: 86 | H74: =SUM(D74:G74) -> 748 | I74: 0.944 | K74: PICARD | L74: 44587 | M74: 492 | N74: =L75-L74+N67 -> 19
A75: =A74+1 -> 5 | C75: FORCIER | D75: 449 | E75: 151 | F75: 55 | G75: 79 | H75: =SUM(D75:G75) -> 734 | I75: 0.864 | K75: CHABOT | L75: 44588 | M75: 500 | N75: =L75-L73+N73 -> 62
A76: =A75+1 -> 6 | C76: MOROTTI | D76: 469 | E76: 115 | F76: 44 | G76: 100 | H76: =SUM(D76:G76) -> 728 | I76: 0.874 | K76: PICARD | L76: 44595 | M76: 529 | N76: 91
A77: =A76+1 -> 7 | C77: CHABOT | D77: 464 | E77: 111 | F77: 63 | G77: 90 | H77: =SUM(D77:G77) -> 728 | I77: 0.865 | K77: CHABOT | L77: 44667 | M77: 935 | N77: 63
A78: =A77+1 -> 8 | C78: MIOUSSE | D78: 465 | E78: 103 | F78: 77 | G78: 78 | H78: =SUM(D78:G78) -> 723 | I78: 0.882 | K78: PICARD | L78: 44668 | M78: 938 | N78: 94
A79: =A78+1 -> 9 | C79: HENAULT | D79: 464 | E79: 91 | F79: 78 | G79: 82 | H79: =SUM(D79:G79) -> 715 | I79: 0.845 | K79: CHABOT | L79: 44671 | M79: 950 | N79: 66
A80: =A79+1 -> 10 | C80: BEAUCHEMIN | D80: 407 | E80: 128 | F80: 72 | G80: 81 | H80: =SUM(D80:G80) -> 688 | I80: 0.816 | K80: PICARD | L80: 44674 | M80: 964 | N80: 102
A81: =A80+1 -> 11 | C81: LESSARD | D81: 436 | E81: 107 | F81: 58 | G81: 63 | H81: =SUM(D81:G81) -> 664 | I81: 0.784
A82: =A81+1 -> 12 | C82: DIEGO | D82: 398 | E82: 121 | F82: 54 | G82: 68 | H82: =SUM(D82:G82) -> 641 | I82: 0.751 | K82: LEAD CHANGE 2021 | L82: DATE | M82: PTS | N82: DL
K83: DIEGO | L83: 44210 | M83: 10 | N83: 1
C84: AVG | D84: =AVERAGE(D72:D82) -> 445.63636 | E84: =AVERAGE(E72:E82) -> 122.36364 | F84: =AVERAGE(F72:F83) -> 67.181818 | G84: =AVERAGE(G72:G82) -> 83 | H84: =AVERAGE(H72:H82) -> 718.18182 | I84: =AVERAGE(I72:I82) -> 0.85881818 | K84: LESSARD | L84: 44211 | M84: 25 | N84: 5
K85: CHABOT | L85: 44216 | M85: 51 | N85: 1
K86: LESSARD | L86: 44217 | M86: 54 | N86: 6
C87: 2019 | D87: FOW | E87: DEF | F87: GOA | G87: TEAM | H87: PTS | I87: PTS/G | K87: MIOUSSE | L87: 44218 | M87: 58 | N87: 2
A88: 1 | C88: DESROSIERS | D88: 687 | E88: 137 | F88: 75 | G88: 100 | H88: =SUM(D88:G88) -> 999 | I88: 1.041 | K88: DESROSIERS | L88: 44220 | M88: 68 | N88: 1
A89: =A88+1 -> 2 | C89: BEAUCHEMIN | D89: 641 | E89: 121 | F89: 106 | G89: 100 | H89: =SUM(D89:G89) -> 968 | I89: 0.97 | K89: CHABOT | L89: 44221 | M89: 71 | N89: 3
A90: =A89+1 -> 3 | C90: FORCIER | D90: 608 | E90: 158 | F90: 90 | G90: 99 | H90: =SUM(D90:G90) -> 955 | I90: 0.936 | K90: LESSARD | L90: 44223 | M90: 85 | N90: 8
A91: =A90+1 -> 4 | C91: HENAULT | D91: 565 | E91: 172 | F91: 76 | G91: 98 | H91: =SUM(D91:G91) -> 911 | I91: 0.902 | K91: DESROSIERS | L91: 44225 | M91: 94 | N91: 13
A92: =A91+1 -> 5 | C92: CHABOT | D92: 558 | E92: 149 | F92: 84 | G92: 99 | H92: =SUM(D92:G92) -> 890 | I92: 0.876 | K92: LESSARD | L92: 44237 | M92: 157 | N92: 17
A93: =A92+1 -> 6 | C93: DAVID | D93: 541 | E93: 143 | F93: 88 | G93: 100 | H93: =SUM(D93:G93) -> 872 | I93: 0.853 | K93: BLIER | L93: 44246 | M93: 191 | N93: 87
A94: =A93+1 -> 7 | C94: BLIER | D94: 537 | E94: 136 | F94: 103 | G94: 93 | H94: =SUM(D94:G94) -> 869 | I94: 0.869 | K94: DESROSIERS | L94: 44320 | M94: 594 | N94: 29
A95: =A94+1 -> 8 | C95: PICARD | D95: 530 | E95: 123 | F95: 83 | G95: 128 | H95: =SUM(D95:G95) -> 864 | I95: 0.899
A96: =A95+1 -> 9 | C96: MOROTTI | D96: 503 | E96: 153 | F96: 63 | G96: 104 | H96: =SUM(D96:G96) -> 823 | I96: 0.866 | K96: LEAD CHANGE 2020 | L96: DATE | M96: PTS | N96: LD
A97: =A96+1 -> 10 | C97: MIOUSSE | D97: 549 | E97: 108 | F97: 66 | G97: 71 | H97: =SUM(D97:G97) -> 794 | I97: 0.791 | K97: DESROSIERS | L97: 43741 | M97: 7 | N97: 1
A98: =A97+1 -> 11 | C98: DIEGO | D98: 519 | E98: 128 | F98: 49 | G98: 84 | H98: =SUM(D98:G98) -> 780 | I98: 0.832 | K98: BLIER | L98: 43377 | M98: 19 | N98: 5
A99: =A98+1 -> 12 | C99: LESSARD | D99: 399 | E99: 151 | F99: 102 | G99: 107 | H99: =SUM(D99:G99) -> 759 | I99: 0.769 | K99: DESROSIERS | L99: 43748 | M99: 52 | N99: 14
K100: BLIER | L100: 43761 | M100: 135 | N100: 7
...

Sheet W2W
A2: 2024 | B2: 1 | C2: PTS | D2: 2 | E2: PTS | F2: 3 | G2: PTS | H2: 4 | I2: PTS | J2: 5 | K2: PTS | L2: 6 | M2: PTS | N2: 7 | O2: PTS | P2: 8 | Q2: PTS | R2: 9 | S2: PTS | T2: 10 | U2: PTS | V2: 11 | W2: PTS | X2: 12 | Y2: PTS
A3: 1 | B3: MIOUSSE | C3: 43 | D3: LESSARD | E3: 39 | F3: MOROTTI | G3: 39 | H3: CHABOT | I3: 39 | J3: BLIER | K3: 38 | L3: DIEGO | M3: 37 | N3: PICARD | O3: 37 | P3: CONSTANTIN | Q3: 32 | R3: BEAUCHEMIN | S3: 30 | T3: ROBB | U3: 29 | V3: HENAULT | W3: 28 | X3: DESROSIERS | Y3: 23
A4: 2 | B4: LESSARD (40) | C4: 79 | D4: BEAUCHEMIN (49) | E4: 79 | F4: DIEGO (40) | G4: 77 | H4: MOROTTI (34) | I4: 73 | J4: BLIER (34) | K4: 72 | L4: PICARD (33) | M4: 70 | N4: CHABOT (28) | O4: 67 | P4: CONSTANTIN (34) | Q4: 66 | R4: MIOUSSE (18) | S4: 61 | T4: HENAULT (26) | U4: 54 | V4: ROBB (21) | W4: 50 | X4: DESROSIERS (25) | Y4: 48
A5: 3 | B5: BEAUCHEMIN (46) | C5: 125 | D5: DIEGO (46) | E5: 123 | F5: LESSARD (41) | G5: 120 | H5: CHABOT (52) | I5: 119 | J5: CONSTANTIN (45) | K5: 111 | L5: BLIER (39) | M5: 111 | N5: PICARD (41) | O5: 111 | P5: MIOUSSE (46) | Q5: 107 | R5: MOROTTI (31) | S5: 104 | T5: HENAULT (40) | U5: 94 | V5: DESROSIERS (36) | W5: 84 | X5: ROBB (27) | Y5: 77
A6: 4 | B6: CONSTANTIN (44) | C6: 155 | D6: MIOUSSE (47) | E6: 154 | F6: BLIER (40) | G6: 151 | H6: BEAUCHEMIN (24) | I6: 149 | J6: DIEGO (25) | K6: 148 | L6: CHABOT (26) | M6: 145 | N6: PICARD (34) | O6: 145 | P6: LESSARD (20) | Q6: 140 | R6: MOROTTI (30) | S6: 134 | T6: HENAULT (32) | U6: 126 | V6: DESROSIERS (21) | W6: 105 | X6: ROBB (28) | Y6: 105
A7: 5 | B7: CONSTANTIN (38) | C7: 193 | D7: MIOUSSE (36) | E7: 190 | F7: BLIER (38) | G7: 189 | H7: BEAUCHEMIN (38) | I7: 187 | J7: DIEGO (37) | K7: 185 | L7: LESSARD (44) | M7: 184 | N7: PICARD (34) | O7: 179 | P7: CHABOT (33) | Q7: 178 | R7: MOROTTI (29) | S7: 163 | T7: HENAULT (32) | U7: 158 | V7: ROBB (37) | W7: 142 | X7: DESROSIERS (33) | Y7: 138
A8: 6 | B8: BLIER (52) | C8: 241 | D8: DIEGO (44) | E8: 229 | F8: CONSTANTIN (35) | G8: 228 | H8: BEAUCHEMIN (39) | I8: 226 | J8: MIOUSSE (36) | K8: 226 | L8: LESSARD (33) | M8: 217 | N8: PICARD (38) | O8: 217 | P8: CHABOT (28) | Q8: 206 | R8: MOROTTI (41) | S8: 204 | T8: HENAULT (37) | U8: 195 | V8: ROBB (30) | W8: 172 | X8: DESROSIERS (18) | Y8: 156
A9: 7 | B9: BLIER (29) | C9: 270 | D9: CONSTANTIN (33) | E9: 261 | F9: BEAUCHEMIN (32) | G9: 258 | H9: MIOUSSE (31) | I9: 257 | J9: DIEGO (27) | K9: 256 | L9: LESSARD (32) | M9: 249 | N9: PICARD (31) | O9: 248 | P9: CHABOT (34) | Q9: 240 | R9: MOROTTI (30) | S9: 234 | T9: HENAULT (33) | U9: 228 | V9: ROBB (25) | W9: 197 | X9: DESROSIERS (21) | Y9: 177
A10: 8 | B10: BLIER (37) | C10: 307 | D10: DIEGO (43) | E10: 299 | F10: CONSTANTIN (30) | G10: 291 | H10: MIOUSSE (33) | I10: 290 | J10: LESSARD (40) | K10: 289 | L10: BEAUCHEMIN (30) | M10: 288 | N10: PICARD (34) | O10: 282 | P10: CHABOT (40) | Q10: 280 | R10: MOROTTI (33) | S10: 267 | T10: HENAULT (36) | U10: 264 | V10: ROBB (34) | W10: 231 | X10: DESROSIERS (26) | Y10: 203
A11: 9 | B11: DIEGO (44) | C11: 343 | D11: BLIER (30) | E11: 337 | F11: CONSTANTIN (42) | G11: 333 | H11: BEAUCHEMIN (37) | I11: 325 | J11: PICARD (40) | K11: 322 | L11: LESSARD (28) | M11: 317 | N11: MIOUSSE (25) | O11: 315 | P11: CHABOT (33) | Q11: 313 | R11: MOROTTI (35) | S11: 302 | T11: HENAULT (32) | U11: 296 | V11: ROBB (42) | W11: 273 | X11: DESROSIERS (27) | Y11: 230
A12: 10 | B12: DIEGO (37) | C12: 380 | D12: BLIER (41) | E12: 378 | F12: PICARD (47) | G12: 369 | H12: CONSTANTIN (28) | I12: 361 | J12: MIOUSSE (44) | K12: 359 | L12: BEAUCHEMIN (31) | M12: 356 | N12: CHABOT (37) | O12: 350 | P12: LESSARD (29) | Q12: 346 | R12: MOROTTI (27) | S12: 329 | T12: HENAULT (33) | U12: 329 | V12: ROBB (31) | W12: 304 | X12: DESROSIERS (20) | Y12: 250
A13: 11 | B13: BLIER (33) | C13: 411 | D13: DIEGO (30) | E13: 410 | F13: PICARD (33) | G13: 402 | H13: MIOUSSE (36) | I13: 395 | J13: CONSTANTIN (31) | K13: 392 | L13: CHABOT (37) | M13: 387 | N13: BEAUCHEMIN (30) | O13: 386 | P13: LESSARD (28) | Q13: 374 | R13: HENAULT (30) | S13: 359 | T13: MOROTTI (23) | U13: 352 | V13: ROBB (23) | W13: 327 | X13: DESROSIERS (33) | Y13: 283
A14: 12 | B14: DIEGO (41) | C14: 451 | D14: MIOUSSE (53) | E14: 448 | F14: BLIER (25) | G14: 436 | H14: CONSTANTIN (36) | I14: 428 | J14: PICARD (20) | K14: 422 | L14: BEAUCHEMIN (35) | M14: 421 | N14: LESSARD (46) | O14: 420 | P14: CHABOT (22) | Q14: 409 | R14: HENAULT (34) | S14: 393 | T14: MOROTTI (23) | U14: 375 | V14: ROBB (25) | W14: 352 | X14: DESROSIERS (25) | Y14: 308
... A28: 26 | B28: MIOUSE (42) | C28: 1027 | D28: CHABOT (57) | E28: 993 | F28: DIEGO (32) | G28: 986 | H28: BLIER (29) | I28: 939 | J28: CONSTANTIN (34) | K28: 928 | L28: BEAUCHEMIN (35) | M28: 927 | N28: MOROTTI (33) | O28: 913 | P28: PICARD (39) | Q28: 910 | R28: LESSARD (39) | S28: 868 | T28: HENAULT (31) | U28: 819 | V28: ROBB (25) | W28: 756 | X28: DESROSIERS (31) | Y28: 695
A29: END | B29: MIOUSE | C29: 1027 | D29: CHABOT | E29: 1003 | F29: DIEGO | G29: 993 | H29: BLIER | I29: 951 | J29: BEAUCHEMIN | K29: 938 | L29: CONSTANTIN | M29: 933 | N29: MOROTTI | O29: 924 | P29: PICARD | Q29: 878 | R29: LESSARD | S29: 787 | T29: HENAULT | U29: 929 | V29: ROBB | W29: 765 | X29: DESROSIERS | Y29: 702

Sheet W2WC
BC1: Season | BD1: Week | BE1: DATE | BF1: POOLER | BG1: PTS
B2: WEEK 2 WEEK CUP 2023 | AH2: SCORING | AK2: W2W CUP Stats | AL2: Wins | AM2: Pod | AN2: Last | AO2: Champ | AR2: Most Points in a week | AV2: Last Win | AW2: POOLER | AX2: Weeks | AY2: Days | BC2: 2022 | BD2: 1 | BE2: 44488 | BF2: CHABOT | BG2: 43
B3: POOLER/WEEK | C3: 1 | D3: 2 | E3: 3 | F3: 4 | G3: 5 | H3: 6 | I3: 7 | J3: 8 | K3: 9 | L3: 10 | M3: 11 | N3: 12 | O3: 13 | P3: 14 | Q3: 15 | R3: 16 | S3: 17 | T3: 18 | U3: 19 | V3: 20 | W3: 21 | X3: 22 | Y3: 23 | Z3: 24 | AA3: 25 | AB3: 26 | AC3: TOTAL | AD3: AVG | AE3: W | AF3: PD | AH3: PLACE | AI3: POINTS | AK3: DESROSIERS | AL3: =SUMIF(B:B,AK3,AE:AE) -> 29 | AM3: =SUMIF(B:B,AK3,AF:AF) -> 62 | AN3: 17 | AO3: 3 | AQ3: 1 | AR3: MIOUSSE | AS3: 66 | AT3: 2024 | AV3: 44265 | AW3: HENAULT | AX3: 86 | AY3: =TODAY()-AV3 -> 1140 | BC3: 2022 | BD3: 2 | BE3: 44495 | BF3: PICARD | BG3: 45 | BI3: Étiquettes de lignes | BJ3: Nombre de POOLER | BK3: Min de Season | BL3: Max de PTS
A4: 1 | B4: MIOUSSE | C4: 1 | D4: 12 | E4: 4 | F4: 1 | G4: 7 | H4: 7 | I4: 6 | J4: 8 | K4: 12 | L4: 2 | M4: 2 | N4: 1 | O4: 2 | P4: 3 | Q4: 3 | R4: 4 | S4: 1 | T4: 5 | U4: 9 | V4: 9 | W4: 7 | X4: 1 | Y4: 1 | Z4: 6 | AA4: 2 | AB4: 2 | AC4: 346 | AD4: =AVERAGE(C4:AB4) -> 4.5384615 | AE4: =COUNTIF(C4:AB4,1) -> 6 | AF4: =COUNTIF(B4:AB4,"<=3") -> 13 | AH4: 1 | AI4: 25 | AK4: BEAUCHEMIN | AL4: =SUMIF(B:B,AK4,AE:AE) -> 23 | AM4: =SUMIF(B:B,AK4,AF:AF) -> 52 | AN4: 9 | AO4: 1 | AQ4: 2 | AR4: BEAUCHEMIN | AS4: 59 | AT4: 2022 | AV4: 44572 | AW4: ROBB | AX4: 65 | AY4: =TODAY()-AV4 -> 833 | BC4: 2022 | BD4: 3 | BE4: 44502 | BF4: ROBB | BG4: 46 | BI4: CHABOT | BJ4: 15 | BK4: 2022 | BL4: 57 | BO4: POOLER/WEEK | BP4: 1 | BQ4: 2 | BR4: 3 | BS4: 4 | BT4: 5 | BU4: 6 | BV4: 7 | BW4: 8 | BX4: 9 | BY4: 10 | BZ4: 11 | CA4: 12 | CB4: 13 | CC4: 14 | CD4: 15 | CE4: 16 | CF4: 17 | CG4: 18 | CH4: 19 | CI4: 20 | CJ4: 21 | CK4: 22 | CL4: 23 | CM4: 24 | CN4: 25 | CO4: 26
A5: 2 | B5: CHABOT | C5: 4 | D5: 8 | E5: 1 | F5: 8 | G5: 9 | H5: 11 | I5: 1 | J5: 3 | K5: 7 | L5: 5 | M5: 1 | N5: 11 | O5: 8 | P5: 5 | Q5: 1 | R5: 2 | S5: 4 | T5: 2 | U5: 7 | V5: 2 | W5: 12 | X5: 2 | Y5: 5 | Z5: 2 | AA5: 1 | AB5: 1 | AC5: 335 | AD5: =AVERAGE(C5:AB5) -> 4.7307692 | AE5: =COUNTIF(C5:AB5,1) -> 6 | AF5: =COUNTIF(B5:AB5,"<=3") -> 12 | AH5: 2 | AI5: 18 | AK5: CHABOT | AL5: =SUMIF(B:B,AK5,AE:AE) -> 22 | AM5: =SUMIF(B:B,AK5,AF:AF) -> 74 | AN5: 15 | AO5: 1 | AQ5: 3 | AR5: BEAUCHEMIN | AS5: 59 | AT5: 2019 | AV5: 44985 | AW5: DESROSIERS | AX5: 32 | AY5: =TODAY()-AV5 -> 420 | BC5: 2022 | BD5: 4 | BE5: 44509 | BF5: DESROSIERS | BG5: 40 | BI5: BEAUCHEMIN | BJ5: 11 | BK5: 2022 | BL5: 59 | BO5: MIOUSSE | BP5: 1 | BQ5: 12 | BR5: 4 | BS5: 1 | BT5: 7 | BU5: 7 | BV5: 6 | BW5: 8 | BX5: 12 | BY5: 2 | BZ5: 2 | CA5: 1 | CB5: 2 | CC5: 3 | CD5: 3 | CE5: 4
A6: 3 | B6: DIEGO | C6: 6 | D6: 3 | E6: 2 | F6: 9 | G6: 5 | H6: 2 | I6: 10 | J6: 1 | K6: 1 | L6: 4 | M6: 7 | N6: 3 | O6: 5 | P6: 6 | Q6: 6 | R6: 6 | S6: 8 | T6: 1 | U6: 2 | V6: 3 | W6: 6 | X6: 5 | Y6: 3 | Z6: 1 | AA6: 8 | AB6: 8 | AC6: 321 | AD6: =AVERAGE(C6:AB6) -> 4.6538462 | AE6: =COUNTIF(C6:AB6,1) -> 4 | AF6: =COUNTIF(B6:AB6,"<=3") -> 11 | AH6: 3 | AI6: 15 | AK6: PICARD | AL6: =SUMIF(B:B,AK6,AE:AE) -> 17 | AM6: =SUMIF(B:B,AK6,AF:AF) -> 47 | AN6: 10 | AQ6: 4 | AR6: DIEGO | AS6: 58 | AT6: 2024 | AV6: 45244 | AW6: LESSARD | AX6: 21 | AY6: =TODAY()-AV6 -> 161 | BC6: 2022 | BD6: 5 | BE6: 44516 | BF6: CHABOT | BG6: 45 | BI6: BLIER | BJ6: 9 | BK6: 2023 | BL6: 50 | BO6: BLIER | BP6: 5 | BQ6: 4 | BR6: 9 | BS6: 3 | BT6: 2 | BU6: 1 | BV6: 9 | BW6: 4 | BX6: 9 | BY6: 3 | BZ6: 3 | CA6: 7 | CB6: 1 | CC6: 2 | CD6: 5 | CE6: 3
A7: 4 | B7: BLIER | C7: 5 | D7: 4 | E7: 9 | F7: 3 | G7: 2 | H7: 1 | I7: 9 | J7: 4 | K7: 9 | L7: 3 | M7: 3 | N7: 7 | O7: 1 | P7: 2 | Q7: 5 | R7: 3 | S7: 3 | T7: 9 | U7: 10 | V7: 12 | W7: 10 | X7: 6 | Y7: 2 | Z7: 9 | AA7: 3 | AB7: 11 | AC7: 264 | AD7: =AVERAGE(C7:AB7) -> 5.5769231 | AE7: =COUNTIF(C7:AB7,1) -> 2 | AF7: =COUNTIF(B7:AB7,"<=3") -> 11 | AH7: 4 | AI7: 12 | AK7: FOR/CON | AL7: =VLOOKUP("CONSTANTIN",AK4:AO20,2,FALSE)+12 -> 17 | AM7: =VLOOKUP("CONSTANTIN",AK4:AO20,3,FALSE)+29 -> 46 | AN7: =VLOOKUP("CONSTANTIN",AK4:AO20,4,FALSE)+3 -> 5 | AQ7: 5 | AR7: MULTIPLE | AS7: 57 | AT7: xxx | AV7: 45279 | AW7: PICARD | AX7: 16 | AY7: =TODAY()-AV7 -> 126 | BC7: 2022 | BD7: 6 | BE7: 44523 | BF7: PICARD | BG7: 52 | BI7: PICARD | BJ7: 9 | BK7: 2022 | BL7: 52 | BO7: DIEGO | BP7: 6 | BQ7: 3 | BR7: 2 | BS7: 9 | BT7: 5 | BU7: 2 | BV7: 10 | BW7: 1 | BX7: 1 | BY7: 4 | BZ7: 7 | CA7: 3 | CB7: 5 | CC7: 6 | CD7: 6 | CE7: 6
A8: 5 | B8: BEAUCHEMIN | C8: 9 | D8: 1 | E8: 3 | F8: 10 | G8: 4 | H8: 4 | I8: 4 | J8: 10 | K8: 5 | L8: 7 | M8: 8 | N8: 5 | O8: 4 | P8: 1 | Q8: 7 | R8: 5 | S8: 6 | T8: 6 | U8: 8 | V8: 1 | W8: 3 | X8: 11 | Y8: 7 | Z8: 11 | AA8: 6 | AB8: 5 | AC8: 247 | AD8: =AVERAGE(C8:AB8) -> 5.8076923 | AE8: =COUNTIF(C8:AB8,1) -> 3 | AF8: =COUNTIF(B8:AB8,"<=3") -> 5 | AH8: 5 | AI8: 10 | AK8: BLIER | AL8: =SUMIF(B:B,AK8,AE:AE) -> 16 | AM8: =SUMIF(B:B,AK8,AF:AF) -> 45 | AN8: 14 | AO8: 1 | AV8: 45300 | AW8: BLIER | AX8: 13 | AY8: =TODAY()-AV8 -> 105 | BC8: 2022 | BD8: 7 | BE8: 44530 | BF8: PICARD | BG8: 40 | BI8: DESROSIERS | BJ8: 9 | BK8: 2022 | BL8: 56 | BO8: CHABOT | BP8: 4 | BQ8: 8 | BR8: 1 | BS8: 8 | BT8: 9 | BU8: 11 | BV8: 1 | BW8: 3 | BX8: 7 | BY8: 5 | BZ8: 1 | CA8: 11 | CB8: 8 | CC8: 5 | CD8: 1 | CE8: 2
A9: 6 | B9: CONSTANTIN | C9: 8 | D9: 6 | E9: 5 | F9: 2 | G9: 3 | H9: 8 | I9: 2 | J9: 11 | K9: 2 | L9: 10 | M9: 6 | N9: 4 | O9: 9 | P9: 8 | Q9: 4 | R9: 8 | S9: 2 | T9: 4 | U9: 4 | V9: 7 | W9: 1 | X9: 10 | Y9: 11 | Z9: 4 | AA9: 4 | AB9: 6 | AC9: 244 | AD9: =AVERAGE(C9:AB9) -> 5.7307692 | AE9: =COUNTIF(C9:AB9,1) -> 1 | AF9: =COUNTIF(B9:AB9,"<=3") -> 6 | AH9: 6 | AI9: 8 | AK9: FORCIER | AL9: =SUMIF(B:B,AK9,AE:AE) -> 12 | AM9: =SUMIF(B:B,AK9,AF:AF) -> 29 | AN9: 3 | AR9: Most Wins in Sea | AV9: 45349 | AW9: MOROTTI | AX9: 7 | AY9: =TODAY()-AV9 -> 56 | BC9: 2022 | BD9: 8 | BE9: 44537 | BF9: CONSTANTIN | BG9: 48 | BI9: MIOUSSE | BJ9: 7 | BK9: 2023 | BL9: 66 | BO9: BEAUCHEMIN | BP9: 9 | BQ9: 1 | BR9: 3 | BS9: 10 | BT9: 4 | BU9: 4 | BV9: 4 | BW9: 10 | BX9: 5 | BY9: 7 | BZ9: 8 | CA9: 5 | CB9: 4 | CC9: 1 | CD9: 7 | CE9: 5
A10: 7 | B10: MOROTTI | C10: 3 | D10: 5 | E10: 11 | F10: 6 | G10: 12 | H10: 3 | I10: 8 | J10: 9 | K10: 6 | L10: 11 | M10: 11 | N10: 10 | O10: 11 | P10: 10 | Q10: 2 | R10: 1 | S10: 9 | T10: 7 | U10: 1 | V10: 5 | W10: 2 | X10: 4 | Y10: 4 | Z10: 3 | AA10: 5 | AB10: 7 | AC10: 223 | AD10: =AVERAGE(C10:AB10) -> 6.3846154 | AE10: =COUNTIF(C10:AB10,1) -> 2 | AF10: =COUNTIF(B10:AB10,"<=3") -> 7 | AH10: 7 | AI10: 6 | AK10: MIOUSSE | AL10: =SUMIF(B:B,AK10,AE:AE) -> 11 | AM10: =SUMIF(B:B,AK10,AF:AF) -> 32 | AN10: 8 | AO10: 1 | AQ10: 1 | AR10: DESROSIERS | AS10: 8 | AT10: 2020 | AV10: 45357 | AW10: BEAUCHEMIN | AX10: 6 | AY10: =TODAY()-AV10 -> 48 | BC10: 2022 | BD10: 9 | BE10: 44544 | BF10: CONSTANTIN | BG10: 37 | BI10: DIEGO | BJ10: 7 | BK10: 2022 | BL10: 58 | BO10: LESSARD | BP10: 2 | BQ10: 2 | BR10: 6 | BS10: 12 | BT10: 1 | BU10: 9 | BV10: 5 | BW10: 2 | BX10: 10 | BY10: 9 | BZ10: 10 | CA10: 2 | CB10: 3 | CC10: 4 | CD10: 9 | CE10: 10
A11: 8 | B11: LESSARD | C11: 2 | D11: 2 | E11: 6 | F11: 12 | G11: 1 | H11: 9 | I11: 5 | J11: 2 | K11: 10 | L11: 9 | M11: 10 | N11: 2 | O11: 3 | P11: 4 | Q11: 9 | R11: 10 | S11: 11 | T11: 12 | U11: 5 | V11: 4 | W11: 4 | X11: 7 | Y11: 8 | Z11: 8 | AA11: 12 | AB11: 4 | AC11: 213 | AD11: =AVERAGE(C11:AB11) -> 6.5769231 | AE11: =COUNTIF(C11:AB11,1) -> 1 | AF11: =COUNTIF(B11:AB11,"<=3") -> 6 | AH11: 8 | AI11: 4 | AK11: DIEGO | AL11: =SUMIF(B:B,AK11,AE:AE) -> 9 | AM11: =SUMIF(B:B,AK11,AF:AF) -> 41 | AN11: 19 | AQ11: 2 | AR11: DESROSIERS | AS11: 7 | AT11: 2023 | AV11: 45363 | AW11: CONSTANTIN | AX11: 5 | AY11: =TODAY()-AV11 -> 42 | BC11: 2022 | BD11: 10 | BE11: 44551 | BF11: CONSTANTIN | BG11: 36 | BI11: CONSTANTIN | BJ11: 5 | BK11: 2022 | BL11: 48 | BO11: CONSTANTIN | BP11: 8 | BQ11: 6 | BR11: 5 | BS11: 2 | BT11: 3 | BU11: 8 | BV11: 2 | BW11: 11 | BX11: 2 | BY11: 10 | BZ11: 6 | CA11: 4 | CB11: 9 | CC11: 8 | CD11: 4 | CE11: 8
A12: 9 | B12: PICARD | C12: 7 | D12: 7 | E12: 7 | F12: 4 | G12: 8 | H12: 5 | I12: 7 | J12: 6 | K12: 4 | L12: 1 | M12: 4 | N12: 12 | O12: 6 | P12: 7 | Q12: 10 | R12: 12 | S12: 5 | T12: 3 | U12: 3 | V12: 6 | W12: 11 | X12: 3 | Y12: 6 | Z12: 10 | AA12: 10 | AB12: 3 | AC12: 210 | AD12: =AVERAGE(C12:AB12) -> 6.4230769 | AE12: =COUNTIF(C12:AB12,1) -> 1 | AF12: =COUNTIF(B12:AB12,"<=3") -> 5 | AH12: 9 | AI12: 2 | AK12: HENAULT | AL12: =SUMIF(B:B,AK12,AE:AE) -> 9 | AM12: =SUMIF(B:B,AK12,AF:AF) -> 29 | AN12: 11 | AQ12: 3 | AR12: CHABOT | AS12: 7 | AT12: 2023 | AV12: 45377 | AW12: MIOUSSE | AX12: 3 | AY12: =TODAY()-AV12 -> 28 | BC12: 2022 | BD12: 11 | BE12: 44565 | BF12: CHABOT | BG12: 43 | BI12: MOROTTI | BJ12: 2 | BK12: 2024 | BL12: 53 | BO12: PICARD | BP12: 7 | BQ12: 7 | BR12: 7 | BS12: 4 | BT12: 8 | BU12: 5 | BV12: 7 | BW12: 6 | BX12: 4 | BY12: 1 | BZ12: 4 | CA12: 12 | CB12: 6 | CC12: 7 | CD12: 10 | CE12: 12
A13: 10 | B13: HENAULT | C13: 11 | D13: 9 | E13: 8 | F13: 5 | G13: 11 | H13: 6 | I13: 3 | J13: 5 | K13: 8 | L13: 6 | M13: 9 | N13: 6 | O13: 10 | P13: 9 | Q13: 11 | R13: 9 | S13: 12 | T13: 8 | U13: 6 | V13: 10 | W13: 8 | X13: 8 | Y13: 9 | Z13: 7 | AA13: 9 | AB13: 9 | AC13: 109 | AD13: =AVERAGE(C13:AB13) -> 8.1538462 | AE13: =COUNTIF(C13:AB13,1) -> 0 | AF13: =COUNTIF(B13:AB13,"<=3") -> 1 | AH13: 10 | AI13: 1 | AK13: MOROTTI | AL13: =SUMIF(B:B,AK13,AE:AE) -> 7 | AM13: =SUMIF(B:B,AK13,AF:AF) -> 30 | AN13: 14 | AQ13: 4 | AR13: PICARD | AS13: 7 | AT13: 2022 | AV13: 45384 | AW13: DIEGO | AX13: 2 | AY13: =TODAY()-AV13 -> 21 | BC13: 2022 | BD13: 12 | BE13: 44572 | BF13: ROBB | BG13: 42 | BI13: ROBB | BJ13: 2 | BK13: 2022 | BL13: 46 | BO13: MOROTTI | BP13: 3 | BQ13: 5 | BR13: 11 | BS13: 6 | BT13: 12 | BU13: 3 | BV13: 8 | BW13: 9 | BX13: 6 | BY13: 11 | BZ13: 11 | CA13: 10 | CB13: 11 | CC13: 10 | CD13: 2 | CE13: 1
A14: 11 | B14: ROBB | C14: 10 | D14: 11 | E14: 12 | F14: 7 | G14: 6 | H14: 10 | I14: 11 | J14: 7 | K14: 3 | L14: 8 | M14: 12 | N14: 8 | O14: 7 | P14: 12 | Q14: 8 | R14: 7 | S14: 10 | T14: 11 | U14: 11 | V14: 8 | W14: 5 | X14: 12 | Y14: 10 | Z14: 12 | AA14: 11 | AB14: 12 | AC14: 77 | AD14: =AVERAGE(C14:AB14) -> 9.2692308 | AE14: =COUNTIF(C14:AB14,1) -> 0 | AF14: =COUNTIF(B14:AB14,"<=3") -> 1 | AK14: DAV/ROB | AL14: =VLOOKUP("ROBB",AK2:AO18,2,FALSE) -> 5 | AM14: =VLOOKUP("robb",AK3:AN18,3,FALSE)+5 -> 23 | AN14: =VLOOKUP("robb",AK3:AN18,4,FALSE)+2 -> 21 | AQ14: 5 | AR14: MULTIPLE | AS14: 6 | AT14: X | AV14: 45398 | AW14: CHABOT | AX14: 0 | AY14: =TODAY()-AV14 -> 7 | BC14: 2022 | BD14: 13 | BE14: 44579 | BF14: CHABOT | BG14: 40 | BI14: LESSARD | BJ14: 1 | BK14: 2024 | BL14: 44 | BO14: HENAULT | BP14: 11 | BQ14: 9 | BR14: 8 | BS14: 5 | BT14: 11 | BU14: 6 | BV14: 3 | BW14: 5 | BX14: 8 | BY14: 6 | BZ14: 9 | CA14: 6 | CB14: 10 | CC14: 9 | CD14: 11 | CE14: 9
A15: 12 | B15: DESROSIERS | C15: 12 | D15: 10 | E15: 10 | F15: 11 | G15: 10 | H15: 12 | I15: 12 | J15: 12 | K15: 11 | L15: 12 | M15: 5 | N15: 9 | O15: 12 | P15: 11 | Q15: 12 | R15: 11 | S15: 7 | T15: 10 | U15: 12 | V15: 11 | W15: 9 | X15: 9 | Y15: 12 | Z15: 5 | AA15: 7 | AB15: 10 | AC15: 43 | AD15: =AVERAGE(C15:AB15) -> 10.153846 | AE15: =COUNTIF(C15:AB15,1) -> 0 | AF15: =COUNTIF(B15:AB15,"<=3") -> 0 | AK15: ROBB | AL15: =SUMIF(B:B,AK15,AE:AE) -> 5 | AM15: =SUMIF(B:B,AK15,AF:AF) -> 18 | AN15: 19 | BC15: 2022 | BD15: 14 | BE15: 44586 | BF15: PICARD | BG15: 49 | BI15: (vide) | BO15: ROBB | BP15: 10 | BQ15: 11 | BR15: 12 | BS15: 7 | BT15: 6 | BU15: 10 | BV15: 11 | BW15: 7 | BX15: 3 | BY15: 8 | BZ15: 12 | CA15: 8 | CB15: 7 | CC15: 12 | CD15: 8 | CE15: 7
AK16: CONSTANTIN | AL16: =SUMIF(B:B,AK16,AE:AE) -> 5 | AM16: =SUMIF(B:B,AK16,AF:AF) -> 17 | AN16: 2 | AR16: Most Podiums in Sea | AW16: Most Weeks Between Ws | BC16: 2022 | BD16: 15 | BE16: 44593 | BF16: DIEGO | BG16: 45 | BI16: Total général | BJ16: 77 | BK16: 2022 | BL16: 66 | BO16: DESROSIERS | BP16: 12 | BQ16: 10 | BR16: 10 | BS16: 11 | BT16: 10 | BU16: 12 | BV16: 12 | BW16: 12 | BX16: 11 | BY16: 12 | BZ16: 5 | CA16: 9 | CB16: 12 | CC16: 11 | CD16: 12 | CE16: 11
AK17: LESSARD | AL17: =SUMIF(B:B,AK17,AE:AE) -> 4 | AM17: =SUMIF(B:B,AK17,AF:AF) -> 26 | AN17: 25 | AQ17: 1 | AR17: DESROSIERS | AS17: 17 | AT17: 2020 | AW17: DIEGO | AX17: 87 | AY17: 18-21 | BC17: 2022 | BD17: 16 | BE17: 44607 | BF17: BEAUCHEMIN | BG17: 59
AK18: DAVID | AL18: =SUMIF(B:B,AK18,AE:AE) -> 0 | AM18: =SUMIF(B:B,AK18,AF:AF) -> 5 | AN18: 2 | AQ18: 2 | AR18: CHABOT | AS18: 15 | AT18: 2023 | AW18: MOROTTI | AX18: 66 | AY18: 21-24 | BC18: 2022 | BD18: 17 | BE18: 44614 | BF18: PICARD | BG18: 52
AQ19: 3 | AR19: CHABOT | AS19: 15 | AT19: 2022 | AW19: LESSARD | AX19: 60 | AY19: 18-21 | BC19: 2022 | BD19: 18 | BE19: 44621 | BF19: BEAUCHEMIN | BG19: 45
AQ20: 4 | AR20: DESROSIERS | AS20: 14 | AT20: 2019 | AW20: MOROTTI | AX20: 55 | AY20: 18-20 | BC20: 2022 | BD20: 19 | BE20: 44628 | BF20: PICARD | BG20: 45
AQ21: 5 | AR21: BEAUCHEMIN | AS21: 14 | AT21: 2018 | AW21: CONSTANTIN | AX21: 50 | AY21: 22-24 | BC21: 2022 | BD21: 20 | BE21: 44635 | BF21: CHABOT | BG21: 45
AW22: PICARD | AX22: 24 | AY22: 18-19 | BC22: 2022 | BD22: 21 | BE22: 44642 | BF22: CONSTANTIN | BG22: 40
B23: WEEK 2 WEEK CUP 2023 | AR23: Most Wins in a Row | AW23: CHABOT | AX23: 19 | AY23: 18-19 | BC23: 2022 | BD23: 22 | BE23: 44649 | BF23: PICARD | BG23: 51
B24: POOLER/WEEK | C24: 1 | D24: 2 | E24: 3 | F24: 4 | G24: 5 | H24: 6 | I24: 7 | J24: 8 | K24: 9 | L24: 10 | M24: 11 | N24: 12 | O24: 13 | P24: 14 | Q24: 15 | R24: 16 | S24: 17 | T24: 18 | U24: 19 | V24: 20 | W24: 21 | X24: 22 | Y24: 23 | Z24: 24 | AA24: 25 | AC24: TOTAL | AD24: AVG | AE24: W | AF24: PD | AQ24: 1 | AR24: BLIER | AS24: 3 | AT24: 2023 | AW24: DESROSIERS | AX24: 11 | AY24: 18-19 | BC24: 2022 | BD24: 23 | BE24: 44656 | BF24: CHABOT | BG24: 47
A25: 1 | B25: DESROSIERS | C25: 1 | D25: 8 | E25: 1 | F25: 6 | G25: 1 | H25: 12 | I25: 7 | J25: 1 | K25: 6 | L25: 1 | M25: 9 | N25: 3 | O25: 1 | P25: 2 | Q25: 5 | R25: 2 | S25: 3 | T25: 6 | U25: 1 | V25: 2 | W25: 4 | X25: 2 | Y25: 6 | Z25: 7 | AA25: 7 | AC25: 355 | AD25: =AVERAGE(C25:AB25) -> 4.16 | AE25: =COUNTIF(C25:AB25,1) -> 7 | AF25: =COUNTIF(B25:AB25,"<=3") -> 13 | AQ25: 2 | AR25: CONSTANTIN | AS25: 3 | AT25: 2022 | AW25: BEAUCHEMIN | AX25: 10 | AY25: 2018 | BC25: 2022 | BD25: 24 | BE25: 44663 | BF25: BEAUCHEMIN | BG25: 51
A26: 2 | B26: BLIER | C26: 2 | D26: 9 | E26: 5 | F26: 1 | G26: 5 | H26: 4 | I26: 5 | J26: 3 | K26: 2 | L26: 5 | M26: 1 | N26: 1 | O26: 10 | P26: 6 | Q26: 11 | R26: 1 | S26: 11 | T26: 4 | U26: 6 | V26: 1 | W26: 1 | X26: 1 | Y26: 4 | Z26: 5 | AA26: 12 | AC26: 331 | AD26: =AVERAGE(C26:AB26) -> 4.64 | AE26: =COUNTIF(C26:AB26,1) -> 7 | AF26: =COUNTIF(B26:AB26,"<=3") -> 10 | AQ26: 3 | AR26: BLIER | AS26: 3 | AT26: 2021 | AW26: CHABOT | AX26: 9 | AY26: 2018 | BC26: 2022 | BD26: 25 | BE26: 44670 | BF26: BEAUCHEMIN | BG26: 59
A27: 3 | B27: CHABOT | C27: 6 | D27: 1 | E27: 3 | F27: 12 | G27: 11 | H27: 1 | I27: 3 | J27: 2 | K27: 4 | L27: 2 | M27: 10 | N27: 2 | O27: 3 | P27: 1 | Q27: 2 | R27: 3 | S27: 9 | T27: 2 | U27: 11 | V27: 3 | W27: 7 | X27: 9 | Y27: 2 | Z27: 6 | AA27: 3 | AC27: 312 | AD27: =AVERAGE(C27:AB27) -> 4.72 | AE27: =COUNTIF(C27:AB27,1) -> 3 | AF27: =COUNTIF(B27:AB27,"<=3") -> 15 | AQ27: 4 | AR27: MULTIPLE | AS27: 2 | AT27: X | AW27: DESROSIERS | AX27: 3 | AY27: 2018 | BC27: 2022 | BD27: 26 | BE27: 44677 | BF27: DESROSIERS | BG27: 48
A28: 4 | B28: DIEGO | C28: 11 | D28: 11 | E28: 6 | F28: 2 | G28: 2 | H28: 6 | I28: 2 | J28: 12 | K28: 1 | L28: 7 | M28: 3 | N28: 4 | O28: 6 | P28: 3 | Q28: 1 | R28: 4 | S28: 6 | T28: 3 | U28: 7 | V28: 11 | W28: 3 | X28: 8 | Y28: 5 | Z28: 2 | AA28: 2 | AC28: 282 | AD28: =AVERAGE(C28:AB28) -> 5.12 | AE28: =COUNTIF(C28:AB28,1) -> 2 | AF28: =COUNTIF(B28:AB28,"<=3") -> 11 | AW28: BEAUCHEMIN | AX28: 1 | AY28: 2018 | BC28: 2023 | BD28: 1 | BE28: 44852 | BF28: DESROSIERS | BG28: 53
A29: 5 | B29: BEAUCHEMIN | C29: 8 | D29: 5 | E29: 2 | F29: 8 | G29: 3 | H29: 7 | I29: 4 | J29: 6 | K29: 5 | L29: 9 | M29: 7 | N29: 5 | O29: 4 | P29: 7 | Q29: 8 | R29: 10 | S29: 1 | T29: 1 | U29: 12 | V29: 4 | W29: 9 | X29: 3 | Y29: 3 | Z29: 1 | AA29: 1 | AC29: 272 | AD29: =AVERAGE(C29:AB29) -> 5.32 | AE29: =COUNTIF(C29:AB29,1) -> 4 | AF29: =COUNTIF(B29:AB29,"<=3") -> 8 | AR29: Most Pod in a Row | BC29: 2023 | BD29: 2 | BE29: 44859 | BF29: CHABOT | BG29: 42
A30: 6 | B30: PICARD | C30: 3 | D30: 12 | E30: 10 | F30: 3 | G30: 6 | H30: 2 | I30: 1 | J30: 5 | K30: 12 | L30: 4 | M30: 2 | N30: 11 | O30: 5 | P30: 9 | Q30: 3 | R30: 9 | S30: 7 | T30: 10 | U30: 8 | V30: 7 | W30: 2 | X30: 6 | Y30: 9 | Z30: 4 | AA30: 6 | AC30: 216 | AD30: =AVERAGE(C30:AB30) -> 6.24 | AE30: =COUNTIF(C30:AB30,1) -> 1 | AF30: =COUNTIF(B30:AB30,"<=3") -> 7 | AQ30: 1 | AR30: CHABOT | AS30: 7 | AT30: 2022 | BC30: 2023 | BD30: 3 | BE30: 44866 | BF30: DESROSIERS | BG30: 43
A31: 7 | B31: MIOUSSE | C31: 4 | D31: 7 | E31: 4 | F31: 9 | G31: 4 | H31: 5 | I31: 10 | J31: 4 | K31: 7 | L31: 10 | M31: 8 | N31: 12 | O31: 2 | P31: 10 | Q31: 6 | R31: 8 | S31: 10 | T31: 5 | U31: 2 | V31: 5 | W31: 8 | X31: 10 | Y31: 1 | Z31: 9 | AA31: 5 | AC31: 190 | AD31: =AVERAGE(C31:AB31) -> 6.6 | AE31: =COUNTIF(C31:AB31,1) -> 1 | AF31: =COUNTIF(B31:AB31,"<=3") -> 3 | AQ31: 2 | AR31: MIOUSSE | AS31: 6 | AT31: 2024 | BC31: 2023 | BD31: 4 | BE31: 44873 | BF31: BLIER | BG31: 50
A32: 8 | B32: CONSTANTIN | C32: 10 | D32: 2 | E32: 7 | F32: 4 | G32: 8 | H32: 9 | I32: 12 | J32: 9 | K32: 10 | L32: 3 | M32: 4 | N32: 6 | O32: 11 | P32: 5 | Q32: 7 | R32: 5 | S32: 8 | T32: 9 | U32: 9 | V32: 8 | W32: 5 | X32: 7 | Y32: 10 | Z32: 8 | AA32: 4 | AC32: 152 | AD32: =AVERAGE(C32:AB32) -> 7.2 | AE32: =COUNTIF(C32:AB32,1) -> 0 | AF32: =COUNTIF(B32:AB32,"<=3") -> 2 | AQ32: 3 | AR32: MULTIPLE | AS32: 5 | AT32: X | BC32: 2023 | BD32: 5 | BE32: 44880 | BF32: DESROSIERS | BG32: 46
A33: 9 | B33: LESSARD | C33: 9 | D33: 4 | E33: 10 | F33: 7 | G33: 9 | H33: 3 | I33: 9 | J33: 11 | K33: 3 | L33: 8 | M33: 5 | N33: 7 | O33: 8 | P33: 12 | Q33: 12 | R33: 12 | S33: 4 | T33: 8 | U33: 3 | V33: 9 | W33: 12 | X33: 4 | Y33: 8 | Z33: 12 | AA33: 8 | AC33: 137 | AD33: =AVERAGE(C33:AB33) -> 7.88 | AE33: =COUNTIF(C33:AB33,1) -> 0 | AF33: =COUNTIF(B33:AB33,"<=3") -> 3 | AQ33: 3 | BC33: 2023 | BD33: 6 | BE33: 44887 | BF33: CHABOT | BG33: 49
A34: 10 | B34: MOROTTI | C34: 7 | D34: 3 | E34: 8 | F34: 5 | G34: 7 | H34: 11 | I34: 11 | J34: 7 | K34: 8 | L34: 6 | M34: 11 | N34: 8 | O34: 12 | P34: 4 | Q34: 9 | R34: 7 | S34: 5 | T34: 7 | U34: 10 | V34: 12 | W34: 6 | X34: 5 | Y34: 11 | Z34: 11 | AA34: 9 | AC34: 120 | AD34: =AVERAGE(C34:AB34) -> 8 | AE34: =COUNTIF(C34:AB34,1) -> 0 | AF34: =COUNTIF(B34:AB34,"<=3") -> 1 | AR34: Best AVG | BC34: 2023 | BD34: 7 | BE34: 44894 | BF34: PICARD | BG34: 46
A35: 11 | B35: HENAULT | C35: 12 | D35: 6 | E35: 11 | F35: 11 | G35: 12 | H35: 8 | I35: 6 | J35: 8 | K35: 9 | L35: 11 | M35: 12 | N35: 9 | O35: 9 | P35: 11 | Q35: 4 | R35: 6 | S35: 12 | T35: 11 | U35: 4 | V35: 10 | W35: 10 | X35: 12 | Y35: 7 | Z35: 3 | AA35: 10 | AC35: 86 | AD35: =AVERAGE(C35:AB35) -> 8.96 | AE35: =COUNTIF(C35:AB35,1) -> 0 | AF35: =COUNTIF(B35:AB35,"<=3") -> 1 | AQ35: 1 | AR35: DESROSIERS | AS35: 3.04 | AT35: 2020 | BC35: 2023 | BD35: 8 | BE35: 44901 | BF35: DESROSIERS | BG35: 49
A36: 12 | B36: ROBB | C36: 5 | D36: 10 | E36: 12 | F36: 10 | G36: 10 | H36: 10 | I36: 8 | J36: 10 | K36: 11 | L36: 12 | M36: 6 | N36: 10 | O36: 7 | P36: 8 | Q36: 10 | R36: 11 | S36: 2 | T36: 12 | U36: 5 | V36: 6 | W36: 11 | X36: 11 | Y36: 12 | Z36: 10 | AA36: 11 | AC36: 76 | AD36: =AVERAGE(C36:AB36) -> 9.2 | AE36: =COUNTIF(C36:AB36,1) -> 0 | AF36: =COUNTIF(B36:AB36,"<=3") -> 1 | AQ36: 2 | AR36: BEAUCHEMIN | AS36: 3.77 | AT36: 2018 | BC36: 2023 | BD36: 9 | BE36: 44908 | BF36: DIEGO | BG36: 46
AQ37: 3 | AR37: DESROSIERS | AS37: 4.16 | AT37: 2023 | BC37: 2023 | BD37: 10 | BE37: 44915 | BF37: DESROSIERS | BG37: 56
AQ38: 4 | AR38: DESROSIERS | AS38: 4.23 | AT38: 2019 | BC38: 2023 | BD38: 11 | BE38: 44922 | BF38: BLIER | BG38: 34
B39: WEEK 2 WEEK CUP 2022 | AQ39: 5 | AR39: CHABOT | AS39: 4.27 | AT39: 2022 | BC39: 2023 | BD39: 12 | BE39: 44929 | BF39: BLIER | BG39: 41
B40: POOLER/WEEK | C40: 1 | D40: 2 | E40: 3 | F40: 4 | G40: 5 | H40: 6 | I40: 7 | J40: 8 | K40: 9 | L40: 10 | M40: 11 | N40: 12 | O40: 13 | P40: 14 | Q40: 15 | R40: 16 | S40: 17 | T40: 18 | U40: 19 | V40: 20 | W40: 21 | X40: 22 | Y40: 23 | Z40: 24 | AA40: 25 | AB40: 26 | AC40: TOTAL | AD40: AVG | AE40: W | AF40: PD | BC40: 2023 | BD40: 13 | BE40: 44936 | BF40: DESROSIERS | BG40: 49
A41: 1 | B41: CHABOT | C41: 1 | D41: 2 | E41: 4 | F41: 3 | G41: 1 | H41: 9 | I41: 6 | J41: 7 | K41: 12 | L41: 10 | M41: 1 | N41: 5 | O41: 1 | P41: 5 | Q41: 3 | R41: 11 | S41: 2 | T41: 3 | U41: 2 | V41: 1 | W41: 3 | X41: 2 | Y41: 1 | Z41: 8 | AA41: 3 | AB41: 5 | AC41: 360 | AD41: =AVERAGE(C41:AB41) -> 4.2692308 | AE41: =COUNTIF(C41:AB41,1) -> 6 | AF41: =COUNTIF(B41:AB41,1)+COUNTIF(B41:AB41,2)+COUNTIF(B41:AB41,3) -> 15 | AR41: Most Last Places in Season | BC41: 2023 | BD41: 14 | BE41: 44943 | BF41: CHABOT | BG41: 50
A42: 2 | B42: PICARD | C42: 6 | D42: 1 | E42: 2 | F42: 9 | G42: 9 | H42: 1 | I42: 1 | J42: 4 | K42: 6 | L42: 6 | M42: 10 | N42: 4 | O42: 11 | P42: 1 | Q42: 8 | R42: 2 | S42: 1 | T42: 12 | U42: 1 | V42: 3 | W42: 8 | X42: 1 | Y42: 6 | Z42: 3 | AA42: 6 | AB42: 4 | AC42: 330 | AD42: =AVERAGE(C42:AB42) -> 4.8461538 | AE42: =COUNTIF(C42:AB42,1) -> 7 | AF42: =COUNTIF(B42:AB42,1)+COUNTIF(B42:AB42,2)+COUNTIF(B42:AB42,3) -> 11 | AQ42: 1 | AR42: DESROSIERS | AS42: 9 | AT42: 2024 | BC42: 2023 | BD42: 15 | BE42: 44950 | BF42: DIEGO | BG42: 48
A43: 3 | B43: BEAUCHEMIN | C43: 10 | D43: 6 | E43: 3 | F43: 5 | G43: 4 | H43: 7 | I43: 7 | J43: 11 | K43: 8 | L43: 7 | M43: 7 | N43: 12 | O43: 2 | P43: 7 | Q43: 7 | R43: 1 | S43: 7 | T43: 1 | U43: 5 | V43: 5 | W43: 5 | X43: 7 | Y43: 3 | Z43: 1 | AA43: 1 | AB43: 2 | AC43: 279 | AD43: =AVERAGE(C43:AB43) -> 5.4230769 | AE43: =COUNTIF(C43:AB43,1) -> 4 | AF43: =COUNTIF(B43:AB43,1)+COUNTIF(B43:AB43,2)+COUNTIF(B43:AB43,3) -> 8 | AQ43: 2 | AR43: DESROSIERS | AS43: 8 | AT43: 2022 | BC43: 2023 | BD43: 16 | BE43: 44957 | BF43: BLIER | BG43: 42
A44: 4 | B44: CONSTANTIN | C44: 4 | D44: 4 | E44: 10 | F44: 6 | G44: 8 | H44: 2 | I44: 2 | J44: 1 | K44: 1 | L44: 1 | M44: 8 | N44: 9 | O44: 10 | P44: 4 | Q44: 6 | R44: 8 | S44: 3 | T44: 6 | U44: 10 | V44: 7 | W44: 1 | X44: 6 | Y44: 7 | Z44: 11 | AA44: 12 | AB44: 7 | AC44: 254 | AD44: =AVERAGE(C44:AB44) -> 5.9230769 | AE44: =COUNTIF(C44:AB44,1) -> 4 | AF44: =COUNTIF(B44:AB44,1)+COUNTIF(B44:AB44,2)+COUNTIF(B44:AB44,3) -> 7 | AQ44: 3 | AR44: BEAUCHEMIN | AS44: 6 | AT44: 2020 | BC44: 2023 | BD44: 17 | BE44: 44971 | BF44: BEAUCHEMIN | BG44: 42
A45: 5 | B45: ROBB | C45: 7 | D45: 12 | E45: 1 | F45: 2 | G45: 3 | H45: 3 | I45: 9 | J45: 5 | K45: 5 | L45: 2 | M45: 4 | N45: 1 | O45: 8 | P45: 9 | Q45: 5 | R45: 9 | S45: 8 | T45: 4 | U45: 6 | V45: 11 | W45: 12 | X45: 3 | Y45: 9 | Z45: 12 | AA45: 10 | AB45: 10 | AC45: 217 | AD45: =AVERAGE(C45:AB45) -> 6.5384615 | AE45: =COUNTIF(C45:AB45,1) -> 2 | AF45: =COUNTIF(B45:AB45,1)+COUNTIF(B45:AB45,2)+COUNTIF(B45:AB45,3) -> 7 | AQ45: 3 | AR45: DIEGO | AS45: 6 | AT45: 2019 | BC45: 2023 | BD45: 18 | BE45: 44978 | BF45: BEAUCHEMIN | BG45: 48
A46: 6 | B46: DIEGO | C46: 12 | D46: 5 | E46: 7 | F46: 11 | G46: 6 | H46: 9 | I46: 8 | J46: 6 | K46: 2 | L46: 3 | M46: 5 | N46: 8 | O46: 3 | P46: 11 | Q46: 1 | R46: 7 | S46: 6 | T46: 2 | U46: 9 | V46: 2 | W46: 2 | X46: 9 | Y46: 12 | Z46: 6 | AA46: 9 | AB46: 8 | AC46: 211 | AD46: =AVERAGE(C46:AB46) -> 6.5 | AE46: =COUNTIF(C46:AB46,1) -> 1 | AF46: =COUNTIF(B46:AB46,1)+COUNTIF(B46:AB46,2)+COUNTIF(B46:AB46,3) -> 7 | AQ46: 5 | AR46: MULTIPLE | AS46: 5 | AT46: X | BC46: 2023 | BD46: 19 | BE46: 44985 | BF46: DESROSIERS | BG46: 55
A47: 7 | B47: BLIER | C47: 2 | D47: 11 | E47: 5 | F47: 8 | G47: 11 | H47: 6 | I47: 4 | J47: 10 | K47: 4 | L47: 5 | M47: 2 | N47: 10 | O47: 12 | P47: 12 | Q47: 4 | R47: 4 | S47: 4 | T47: 5 | U47: 12 | V47: 10 | W47: 10 | X47: 5 | Y47: 4 | Z47: 5 | AA47: 2 | AB47: 3 | AC47: 207 | AD47: =AVERAGE(C47:AB47) -> 6.5384615 | AE47: =COUNTIF(C47:AB47,1) -> 0 | AF47: =COUNTIF(B47:AB47,1)+COUNTIF(B47:AB47,2)+COUNTIF(B47:AB47,3) -> 4 | BC47: 2023 | BD47: 20 | BE47: 44992 | BF47: BLIER | BG47: 45
A48: 8 | B48: MIOUSSE | C48: 8 | D48: 7 | E48: 6 | F48: 7 | G48: 2 | H48: 4 | I48: 3 | J48: 3 | K48: 9 | L48: 4 | M48: 11 | N48: 2 | O48: 6 | P48: 10 | Q48: 10 | R48: 6 | S48: 9 | T48: 9 | U48: 8 | V48: 4 | W48: 7 | X48: 10 | Y48: 11 | Z48: 4 | AA48: 5 | AB48: 9 | AC48: 189 | AD48: =AVERAGE(C48:AB48) -> 6.6923077 | AE48: =COUNTIF(C48:AB48,1) -> 0 | AF48: =COUNTIF(B48:AB48,1)+COUNTIF(B48:AB48,2)+COUNTIF(B48:AB48,3) -> 4 | AR48: Worst AVG | BC48: 2023 | BD48: 21 | BE48: 44999 | BF48: BLIER | BG48: 50
A49: 9 | B49: MOROTTI | C49: 11 | D49: 3 | E49: 8 | F49: 12 | G49: 5 | H49: 11 | I49: 10 | J49: 9 | K49: 7 | L49: 12 | M49: 3 | N49: 7 | O49: 5 | P49: 3 | Q49: 2 | R49: 5 | S49: 5 | T49: 7 | U49: 3 | V49: 6 | W49: 6 | X49: 4 | Y49: 5 | Z49: 9 | AA49: 11 | AB49: 11 | AC49: 183 | AD49: =AVERAGE(C49:AB49) -> 6.9230769 | AE49: =COUNTIF(C49:AB49,1) -> 0 | AF49: =COUNTIF(B49:AB49,1)+COUNTIF(B49:AB49,2)+COUNTIF(B49:AB49,3) -> 5 | AQ49: 1 | AR49: DESROSIERS | AS49: 10.15 | AT49: 2024 | BC49: 2023 | BD49: 22 | BE49: 45006 | BF49: BLIER | BG49: 50
A50: 10 | B50: LESSARD | C50: 3 | D50: 8 | E50: 11 | F50: 4 | G50: 7 | H50: 5 | I50: 5 | J50: 8 | K50: 3 | L50: 9 | M50: 12 | N50: 3 | O50: 4 | P50: 2 | Q50: 9 | R50: 3 | S50: 10 | T50: 11 | U50: 4 | V50: 9 | W50: 9 | X50: 12 | Y50: 8 | Z50: 7 | AA50: 4 | AB50: 12 | AC50: 179 | AD50: =AVERAGE(C50:AB50) -> 7 | AE50: =COUNTIF(C50:AB50,1) -> 0 | AF50: =COUNTIF(B50:AB50,1)+COUNTIF(B50:AB50,2)+COUNTIF(B50:AB50,3) -> 5 | AQ50: 2 | AR50: DESROSIERS | AS50: 9.23 | AT50: 2022 | BC50: 2023 | BD50: 23 | BE50: 45013 | BF50: MIOUSSE | BG50: 45
A51: 11 | B51: HENAULT | C51: 5 | D51: 9 | E51: 9 | F51: 10 | G51: 10 | H51: 10 | I51: 12 | J51: 2 | K51: 10 | L51: 11 | M51: 6 | N51: 6 | O51: 9 | P51: 8 | Q51: 11 | R51: 10 | S51: 11 | T51: 8 | U51: 7 | V51: 8 | W51: 4 | X51: 11 | Y51: 10 | Z51: 2 | AA51: 7 | AB51: 6 | AC51: 118 | AD51: =AVERAGE(C51:AB51) -> 8.1538462 | AE51: =COUNTIF(C51:AB51,1) -> 0 | AF51: =COUNTIF(B51:AB51,1)+COUNTIF(B51:AB51,2)+COUNTIF(B51:AB51,3) -> 2 | AQ51: 3 | AR51: ROBB | AS51: 9.2 | AT51: 2023 | BC51: 2023 | BD51: 24 | BE51: 45020 | BF51: BEAUCHEMIN | BG51: 45
A52: 12 | B52: DESROSIERS | C52: 9 | D52: 10 | E52: 12 | F52: 1 | G52: 12 | H52: 12 | I52: 11 | J52: 12 | K52: 11 | L52: 8 | M52: 9 | N52: 11 | O52: 7 | P52: 6 | Q52: 12 | R52: 12 | S52: 12 | T52: 10 | U52: 11 | V52: 12 | W52: 11 | X52: 8 | Y52: 2 | Z52: 10 | AA52: 8 | AB52: 1 | AC52: 101 | AD52: =AVERAGE(C52:AB52) -> 9.2307692 | AE52: =COUNTIF(C52:AB52,1) -> 2 | AF52: =COUNTIF(B52:AB52,1)+COUNTIF(B52:AB52,2)+COUNTIF(B52:AB52,3) -> 3 | AQ52: 4 | AR52: LESSARD | AS52: 9.04 | AT52: 2019 | BC52: 2023 | BD52: 25 | BE52: 45027 | BF52: BEAUCHEMIN | BG52: 49
AQ53: 5 | AR53: HENAULT | AS53: 8.96 | AT53: 2023 | BC53: 2024 | BD53: 1 | BE53: 45216 | BF53: MIOUSSE | BG53: 43
AQ54: 5 | BC54: 2024 | BD54: 2 | BE54: 45223 | BF54: BEAUCHEMIN | BG54: 49
B55: WEEK 2 WEEK CUP 2021 | BC55: 2024 | BD55: 3 | BE55: 45230 | BF55: CHABOT | BG55: 52
B56: POOLER/WEEK | C56: 1 | D56: 2 | E56: 3 | F56: 4 | G56: 5 | H56: 6 | I56: 7 | J56: 8 | K56: 9 | L56: 10 | M56: 11 | N56: 12 | O56: 13 | P56: 14 | Q56: 15 | R56: 16 | S56: 17 | T56: 18 | U56: 19 | V56: 20 | W56: 21 | X56: 22 | Y56: 23 | Z56: 24 | AA56: 25 | AB56: 26 | AC56: TOTAL | AD56: AVG | AE56: W | AF56: PD | BC56: 2024 | BD56: 4 | BE56: 45237 | BF56: MIOUSSE | BG56: 47
A57: 1 | B57: BLIER | C57: 4 | D57: 8 | E57: 12 | F57: 2 | G57: 1 | H57: 1 | I57: 1 | J57: 3 | K57: 7 | L57: 6 | M57: 2 | N57: 2 | O57: 4 | P57: 7 | Q57: 8 | R57: 4 | S57: 11 | AC57: 208 | AD57: =AVERAGE(C57:AB57) -> 4.8823529 | AE57: 3 | AF57: 7 | BC57: 2024 | BD57: 5 | BE57: 45244 | BF57: LESSARD | BG57: 44
A58: 2 | B58: LESSARD | C58: 2 | D58: 5 | E58: 7 | F58: 1 | G58: 5 | H58: 3 | I58: 9 | J58: 2 | K58: 5 | L58: 7 | M58: 4 | N58: 6 | O58: 8 | P58: 2 | Q58: 3 | R58: 2 | S58: 5 | AC58: 205 | AD58: =AVERAGE(C58:AB58) -> 4.4705882 | AE58: 1 | AF58: 7 | BC58: 2024 | BD58: 6 | BE58: 45251 | BF58: BLIER | BG58: 42
A59: 3 | B59: DESROSIERS | C59: 11 | D59: 2 | E59: 1 | F59: 8 | G59: 6 | H59: 4 | I59: 11 | J59: 7 | K59: 3 | L59: 9 | M59: 8 | N59: 1 | O59: 5 | P59: 3 | Q59: 5 | R59: 1 | S59: 4 | AC59: 191 | AD59: =AVERAGE(C59:AB59) -> 5.2352941 | AE59: 3 | AF59: 6 | BC59: 2024 | BD59: 7 | BE59: 45258 | BF59: CHABOT | BG59: 34
A60: 4 | B60: MOROTTI | C60: 10 | D60: 3 | E60: 8 | F60: 4 | G60: 2 | H60: 11 | I60: 7 | J60: 12 | K60: 10 | L60: 5 | M60: 1 | N60: 3 | O60: 2 | P60: 1 | Q60: 10 | R60: 11 | S60: 1 | AC60: 176 | AD60: =AVERAGE(C60:AB60) -> 5.9411765 | AE60: 3 | AF60: 7 | BC60: 2024 | BD60: 8 | BE60: 45265 | BF60: DIEGO | BG60: 43
A61: 5 | B61: MIOUSSE | C61: 5 | D61: 4 | E61: 11 | F61: 9 | G61: 10 | H61: 6 | I61: 6 | J61: 9 | K61: 1 | L61: 4 | M61: 3 | N61: 5 | O61: 7 | P61: 4 | Q61: 2 | R61: 7 | S61: 12 | AC61: 147 | AD61: =AVERAGE(C61:AB61) -> 6.1764706 | AE61: 1 | AF61: 3 | BC61: 2024 | BD61: 9 | BE61: 45272 | BF61: DIEGO | BG61: 44
A62: 6 | B62: BEAUCHEMIN | C62: 3 | D62: 11 | E62: 2 | F62: 11 | G62: 12 | H62: 9 | I62: 5 | J62: 10 | K62: 2 | L62: 1 | M62: 7 | N62: 4 | O62: 6 | P62: 11 | Q62: 6 | R62: 3 | S62: 7 | AC62: 144 | AD62: =AVERAGE(C62:AB62) -> 6.4705882 | AE62: 1 | AF62: 5 | BC62: 2024 | BD62: 10 | BE62: 45279 | BF62: PICARD | BG62: 47
A63: 7 | B63: PICARD | C63: 12 | D63: 1 | E63: 3 | F63: 7 | G63: 7 | H63: 7 | I63: 10 | J63: 4 | K63: 4 | L63: 10 | M63: 6 | N63: 7 | O63: 1 | P63: 6 | Q63: 11 | R63: 10 | S63: 6 | AC63: 140 | AD63: =AVERAGE(C63:AB63) -> 6.5882353 | AE63: 2 | AF63: 3 | BC63: 2024 | BD63: 11 | BE63: 45286 | BF63: CHABOT | BG63: 37
A64: 8 | B64: CONSTANTIN | C64: 7 | D64: 6 | E64: 4 | F64: 5 | G64: 4 | H64: 8 | I64: 4 | J64: 8 | K64: 6 | L64: 3 | M64: 9 | N64: 11 | O64: 9 | P64: 9 | Q64: 4 | R64: 8 | S64: 2 | AC64: 131 | AD64: =AVERAGE(C64:AB64) -> 6.2941176 | AE64: 0 | AF64: 2 | BC64: 2024 | BD64: 12 | BE64: 45293 | BF64: MIOUSSE | BG64: 53
A65: 9 | B65: CHABOT | C65: 1 | D65: 9 | E65: 9 | F65: 3 | G65: 8 | H65: 2 | I65: 8 | J65: 5 | K65: 9 | L65: 12 | M65: 5 | N65: 12 | O65: 10 | P65: 10 | Q65: 12 | R65: 12 | S65: 3 | AC65: 109 | AD65: =AVERAGE(C65:AB65) -> 7.6470588 | AE65: 1 | AF65: 4 | BC65: 2024 | BD65: 13 | BE65: 45300 | BF65: BLIER | BG65: 50
A66: 10 | B66: HENAULT | C66: 9 | D66: 10 | E66: 5 | F66: 6 | G66: 9 | H66: 10 | I66: 2 | J66: 1 | K66: 11 | L66: 2 | M66: 11 | N66: 10 | O66: 12 | P66: 8 | Q66: 7 | R66: 9 | S66: 10 | AC66: 99 | AD66: =AVERAGE(C66:AB66) -> 7.7647059 | AE66: 1 | AF66: 3 | BC66: 2024 | BD66: 14 | BE66: 45307 | BF66: BEAUCHEMIN | BG66: 42
A67: 11 | B67: DIEGO | C67: 8 | D67: 12 | E67: 10 | F67: 10 | G67: 11 | H67: 5 | I67: 3 | J67: 6 | K67: 12 | L67: 11 | M67: 12 | N67: 9 | O67: 11 | P67: 5 | Q67: 1 | R67: 6 | S67: 9 | AC67: 86 | AD67: =AVERAGE(C67:AB67) -> 8.2941176 | AE67: 1 | AF67: 2 | BC67: 2024 | BD67: 15 | BE67: 45314 | BF67: CHABOT | BG67: 40
A68: 12 | B68: ROBB | C68: 6 | D68: 7 | E68: 6 | F68: 12 | G68: 3 | H68: 12 | I68: 12 | J68: 11 | K68: 9 | L68: 8 | M68: 10 | N68: 8 | O68: 3 | P68: 12 | Q68: 9 | R68: 5 | S68: 8 | AC68: 79 | AD68: =AVERAGE(C68:AB68) -> 8.2941176 | AE68: 0 | AF68: 2 | BC68: 2024 | BD68: 16 | BE68: 45314 | BF68: MOROTTI | BG68: 47
BC69: 2024 | BD69: 17 | BE69: 45335 | BF69: MIOUSSE | BG69: 41
BC70: 2024 | BD70: 18 | BE70: 45342 | BF70: DIEGO | BG70: 58
B71: WEEK 2 WEEK CUP 2020 | BC71: 2024 | BD71: 19 | BE71: 45349 | BF71: MOROTTI | BG71: 53
B72: POOLER/WEEK | C72: 1 | D72: 2 | E72: 3 | F72: 4 | G72: 5 | H72: 6 | I72: 7 | J72: 8 | K72: 9 | L72: 10 | M72: 11 | N72: 12 | O72: 13 | P72: 14 | Q72: 15 | R72: 16 | S72: 17 | T72: 18 | U72: 19 | V72: 20 | W72: 21 | X72: 22 | Y72: 23 | Z72: 24 | AA72: 25 | AB72: 26 | AC72: TOTAL | AD72: AVG | AE72: W | AF72: PD | BC72: 2024 | BD72: 20 | BE72: 45357 | BF72: BEAUCHEMIN | BG72: 43
A73: 1 | B73: DESROSIERS | C73: 1 | D73: 1 | E73: 3 | F73: 1 | G73: 8 | H73: 1 | I73: 1 | J73: 2 | K73: 2 | L73: 2 | M73: 4 | N73: 3 | O73: 7 | P73: 2 | Q73: 5 | R73: 1 | S73: 6 | T73: 1 | U73: 2 | V73: 11 | W73: 2 | X73: 1 | Y73: 3 | AC73: 397 | AD73: =AVERAGE(C73:AB73) -> 3.0434783 | AE73: 8 | AF73: 17 | BC73: 2024 | BD73: 21 | BE73: 45363 | BF73: CONSTANTIN | BG73: 36
A74: 2 | B74: PICARD | C74: 5 | D74: 5 | E74: 8 | F74: 3 | G74: 2 | H74: 3 | I74: 9 | J74: 11 | K74: 7 | L74: 1 | M74: 3 | N74: 1 | O74: 1 | P74: 8 | Q74: 6 | R74: 5 | S74: 1 | T74: 4 | U74: 11 | V74: 8 | W74: 3 | X74: 3 | Y74: 8 | AC74: 267 | AD74: =AVERAGE(C74:AB74) -> 5.0434783 | AE74: 4 | AF74: 10 | BC74: 2024 | BD74: 22 | BE74: 45370 | BF74: MIOUSSE | BG74: 49
A75: 3 | B75: BLIER | C75: 3 | D75: 2 | E75: 1 | F75: 7 | G75: 5 | H75: 12 | I75: 2 | J75: 12 | K75: 8 | L75: 9 | M75: 5 | N75: 5 | O75: 5 | P75: 3 | Q75: 12 | R75: 7 | S75: 4 | T75: 2 | U75: 7 | V75: 2 | W75: 5 | X75: 4 | Y75: 2 | AC75: 243 | AD75: =AVERAGE(C75:AB75) -> 5.3913043 | AE75: 1 | AF75: 8 | BC75: 2024 | BD75: 23 | BE75: 45370 | BF75: MIOUSSE | BG75: 66
A76: 4 | B76: ROBB | C76: 8 | D76: 11 | E76: 9 | F76: 12 | G76: 12 | H76: 6 | I76: 5 | J76: 1 | K76: 11 | L76: 4 | M76: 9 | N76: 4 | O76: 3 | P76: 4 | Q76: 3 | R76: 3 | S76: 10 | T76: 3 | U76: 1 | V76: 7 | W76: 9 | X76: 7 | Y76: 1 | AC76: 212 | AD76: =AVERAGE(C76:AB76) -> 6.2173913 | AE76: 3 | AF76: 7 | BC76: 2024 | BD76: 24 | BE76: 45384 | BF76: DIEGO | BG76: 46
A77: 5 | B77: CHABOT | C77: 4 | D77: 7 | E77: 4 | F77: 2 | G77: 9 | H77: 10 | I77: 3 | J77: 10 | K77: 4 | L77: 7 | M77: 2 | N77: 2 | O77: 12 | P77: 10 | Q77: 1 | R77: 6 | S77: 3 | T77: 5 | U77: 12 | V77: 3 | W77: 10 | X77: 12 | Y77: 6 | AC77: 204 | AD77: =AVERAGE(C77:AB77) -> 6.2608696 | AE77: 1 | AF77: 7 | BC77: 2024 | BD77: 25 | BE77: 45391 | BF77: CHABOT | BG77: 51
A78: 6 | B78: FORCIER | C78: 10 | D78: 3 | E78: 7 | F78: 11 | G78: 10 | H78: 9 | I78: 7 | J78: 6 | K78: 5 | L78: 3 | M78: 1 | N78: 11 | O78: 8 | P78: 1 | Q78: 7 | R78: 2 | S78: 12 | T78: 10 | U78: 3 | V78: 4 | W78: 7 | X78: 8 | Y78: 11 | AC78: 180 | AD78: =AVERAGE(C78:AB78) -> 6.7826087 | AE78: 2 | AF78: 6 | BC78: 2024 | BD78: 26 | BE78: 45398 | BF78: CHABOT | BG78: 57
A79: 7 | B79: MOROTTI | C79: 11 | D79: 8 | E79: 2 | F79: 8 | G79: 4 | H79: 4 | I79: 4 | J79: 4 | K79: 1 | L79: 12 | M79: 7 | N79: 9 | O79: 10 | P79: 6 | Q79: 9 | R79: 4 | S79: 7 | T79: 8 | U79: 6 | V79: 10 | W79: 12 | X79: 2 | Y79: 7 | AC79: 173 | AD79: =AVERAGE(C79:AB79) -> 6.7391304 | AE79: 1 | AF79: 3
A80: 8 | B80: MIOUSSE | C80: 6 | D80: 9 | E80: 6 | F80: 5 | G80: 7 | H80: 11 | I80: 6 | J80: 3 | K80: 3 | L80: 6 | M80: 8 | N80: 7 | O80: 2 | P80: 7 | Q80: 10 | R80: 11 | S80: 11 | T80: 6 | U80: 4 | V80: 1 | W80: 8 | X80: 10 | Y80: 5 | AC80: 165 | AD80: =AVERAGE(C80:AB80) -> 6.6086957 | AE80: 1 | AF80: 4
A81: 9 | B81: HENAULT | C81: 7 | D81: 6 | E81: 10 | F81: 9 | G81: 1 | H81: 7 | I81: 8 | J81: 7 | K81: 9 | L81: 5 | M81: 11 | N81: 10 | O81: 4 | P81: 5 | Q81: 9 | R81: 8 | S81: 2 | T81: 7 | U81: 10 | V81: 5 | W81: 1 | X81: 11 | Y81: 9 | AC81: 161 | AD81: =AVERAGE(C81:AB81) -> 7 | AE81: 2 | AF81: 3
A82: 10 | B82: BEAUCHEMIN | C82: 2 | D82: 12 | E82: 5 | F82: 4 | G82: 11 | H82: 2 | I82: 10 | J82: 5 | K82: 12 | L82: 8 | M82: 12 | N82: 12 | O82: 6 | P82: 12 | Q82: 2 | R82: 9 | S82: 9 | T82: 9 | U82: 5 | V82: 12 | W82: 6 | X82: 5 | Y82: 4 | AC82: 145 | AD82: =AVERAGE(C82:AB82) -> 7.5652174 | AE82: 0 | AF82: 3
A83: 11 | B83: LESSARD | C83: 9 | D83: 4 | E83: 12 | F83: 10 | G83: 6 | H83: 8 | I83: 12 | J83: 8 | K83: 6 | L83: 11 | M83: 10 | N83: 5 | O83: 9 | P83: 9 | Q83: 11 | R83: 10 | S83: 5 | T83: 12 | U83: 9 | V83: 6 | W83: 4 | X83: 9 | Y83: 12 | AC83: 89 | AD83: =AVERAGE(C83:AB83) -> 8.5652174 | AE83: 0 | AF83: 0
A84: 12 | B84: DIEGO | C84: 12 | D84: 10 | E84: 11 | F84: 6 | G84: 3 | H84: 5 | I84: 11 | J84: 9 | K84: 10 | L84: 10 | M84: 6 | N84: 8 | O84: 11 | P84: 11 | Q84: 4 | R84: 12 | S84: 8 | T84: 11 | U84: 8 | V84: 9 | W84: 11 | X84: 6 | Y84: 10 | AC84: 81 | AD84: =AVERAGE(C84:AB84) -> 8.7826087 | AE84: 0 | AF84: 1
B87: WEEK 2 WEEK CUP 2019
B88: POOLER/WEEK | C88: 1 | D88: 2 | E88: 3 | F88: 4 | G88: 5 | H88: 6 | I88: 7 | J88: 8 | K88: 9 | L88: 10 | M88: 11 | N88: 12 | O88: 13 | P88: 14 | Q88: 15 | R88: 16 | S88: 17 | T88: 18 | U88: 19 | V88: 20 | W88: 21 | X88: 22 | Y88: 23 | Z88: 24 | AA88: 25 | AB88: 26 | AC88: TOTAL | AD88: AVG | AE88: W | AF88: PD
A89: 1 | B89: DESROSIERS | C89: 1 | D89: 1 | E89: 7 | F89: 10 | G89: 9 | H89: 2 | I89: 3 | J89: 7 | K89: 4 | L89: 2 | M89: 11 | N89: 2 | O89: 9 | P89: 7 | Q89: 5 | R89: 5 | S89: 3 | T89: 2 | U89: 1 | V89: 2 | W89: 7 | X89: 1 | Y89: 1 | Z89: 4 | AA89: 1 | AB89: 3 | AC89: 358 | AD89: =AVERAGE(C89:AB89) -> 4.2307692 | AE89: 6 | AF89: 14
A90: 2 | B90: FORCIER | C90: 7 | D90: 3 | E90: 1 | F90: 5 | G90: 7 | H90: 6 | I90: 2 | J90: 5 | K90: 5 | L90: 5 | M90: 1 | N90: 1 | O90: 11 | P90: 1 | Q90: 2 | R90: 1 | S90: 2 | T90: 3 | U90: 4 | V90: 10 | W90: 4 | X90: 3 | Y90: 11 | Z90: 5 | AA90: 11 | AB90: 4 | AC90: 331 | AD90: =AVERAGE(C90:AB90) -> 4.6153846 | AE90: 5 | AF90: 11
A91: 3 | B91: BEAUCHEMIN | C91: 9 | D91: 4 | E91: 11 | F91: 1 | G91: 2 | H91: 9 | I91: 5 | J91: 6 | K91: 6 | L91: 9 | M91: 10 | N91: 4 | O91: 2 | P91: 6 | Q91: 1 | R91: 10 | S91: 6 | T91: 1 | U91: 3 | V91: 1 | W91: 5 | X91: 5 | Y91: 10 | Z91: 2 | AA91: 8 | AB91: 1 | AC91: 293 | AD91: =AVERAGE(C91:AB91) -> 5.2692308 | AE91: 5 | AF91: 9
A92: 4 | B92: HENAULT | C92: 5 | D92: 2 | E92: 3 | F92: 2 | G92: 1 | H92: 1 | I92: 9 | J92: 2 | K92: 2 | L92: 8 | M92: 9 | N92: 7 | O92: 7 | P92: 4 | Q92: 8 | R92: 12 | S92: 10 | T92: 10 | U92: 11 | V92: 3 | W92: 3 | X92: 12 | Y92: 6 | Z92: 1 | AA92: 4 | AB92: 5 | AC92: 270 | AD92: =AVERAGE(C92:AB92) -> 5.6538462 | AE92: 3 | AF92: 10
A93: 5 | B93: CHABOT | C93: 2 | D93: 9 | E93: 9 | F93: 9 | G93: 5 | H93: 3 | I93: 1 | J93: 4 | K93: 3 | L93: 10 | M93: 2 | N93: 3 | O93: 10 | P93: 12 | Q93: 3 | R93: 11 | S93: 1 | T93: 8 | U93: 2 | V93: 7 | W93: 1 | X93: 6 | Y93: 12 | Z93: 9 | AA93: 6 | AB93: 12 | AC93: 237 | AD93: =AVERAGE(C93:AB93) -> 6.1538462 | AE93: 3 | AF93: 10
A94: 6 | B94: PICARD | C94: 4 | D94: 5 | E94: 2 | F94: 4 | G94: 3 | H94: 11 | I94: 4 | J94: 10 | K94: 1 | L94: 4 | M94: 6 | N94: 12 | O94: 3 | P94: 8 | Q94: 4 | R94: 8 | S94: 4 | T94: 6 | U94: 12 | V94: 5 | W94: 10 | X94: 7 | Y94: 2 | Z94: 6 | AA94: 5 | AB94: 11 | AC94: 228 | AD94: =AVERAGE(C94:AB94) -> 6.0384615 | AE94: 1 | AF94: 5
A95: 7 | B95: DAVID | C95: 11 | D95: 7 | E95: 4 | F95: 3 | G95: 10 | H95: 7 | I95: 12 | J95: 9 | K95: 8 | L95: 7 | M95: 5 | N95: 10 | O95: 6 | P95: 2 | Q95: 7 | R95: 3 | S95: 8 | T95: 5 | U95: 7 | V95: 12 | W95: 2 | X95: 4 | Y95: 3 | Z95: 8 | AA95: 7 | AB95: 6 | AC95: 203 | AD95: =AVERAGE(C95:AB95) -> 6.6538462 | AE95: 0 | AF95: 5
A96: 8 | B96: BLIER | C96: 12 | D96: 8 | E96: 8 | F96: 6 | G96: 8 | H96: 8 | I96: 10 | J96: 1 | K96: 9 | L96: 1 | M96: 8 | N96: 5 | O96: 1 | P96: 10 | Q96: 9 | R96: 7 | S96: 12 | T96: 7 | U96: 6 | V96: 4 | W96: 9 | X96: 2 | Y96: 4 | Z96: 10 | AA96: 9 | AB96: 9 | AC96: 187 | AD96: =AVERAGE(C96:AB96) -> 7.0384615 | AE96: 3 | AF96: 4
A97: 9 | B97: MOROTTI | C97: 6 | D97: 10 | E97: 6 | F97: 8 | G97: 12 | H97: 5 | I97: 6 | J97: 8 | K97: 11 | L97: 6 | M97: 12 | N97: 8 | O97: 8 | P97: 5 | Q97: 6 | R97: 6 | S97: 5 | T97: 4 | U97: 5 | V97: 6 | W97: 8 | X97: 10 | Y97: 7 | Z97: 11 | AA97: 2 | AB97: 2 | AC97: 172 | AD97: =AVERAGE(C97:AB97) -> 7.0384615 | AE97: 0 | AF97: 2
A98: 10 | B98: MIOUSSE | C98: 10 | D98: 11 | E98: 10 | F98: 11 | G98: 5 | H98: 4 | I98: 7 | J98: 3 | K98: 7 | L98: 3 | M98: 4 | N98: 11 | O98: 12 | P98: 11 | Q98: 10 | R98: 2 | S98: 7 | T98: 12 | U98: 10 | V98: 9 | W98: 11 | X98: 8 | Y98: 5 | Z98: 7 | AA98: 10 | AB98: 10 | AC98: 126 | AD98: =AVERAGE(C98:AB98) -> 8.0769231 | AE98: 0 | AF98: 3
A99: 11 | B99: DIEGO | C99: 3 | D99: 6 | E99: 12 | F99: 12 | G99: 11 | H99: 12 | I99: 11 | J99: 12 | K99: 10 | L99: 11 | M99: 3 | N99: 9 | O99: 5 | P99: 3 | Q99: 12 | R99: 4 | S99: 9 | T99: 9 | U99: 9 | V99: 8 | W99: 12 | X99: 9 | Y99: 9 | Z99: 3 | AA99: 3 | AB99: 7 | AC99: 126 | AD99: =AVERAGE(C99:AB99) -> 8.2307692 | AE99: 0 | AF99: 5
A100: 12 | B100: LESSARD | C100: 8 | D100: 12 | E100: 5 | F100: 7 | G100: 6 | H100: 10 | I100: 8 | J100: 11 | K100: 12 | L100: 12 | M100: 7 | N100: 6 | O100: 4 | P100: 9 | Q100: 11 | R100: 9 | S100: 11 | T100: 11 | U100: 8 | V100: 11 | W100: 6 | X100: 11 | Y100: 8 | Z100: 12 | AA100: 12 | AB100: 8 | AC100: 84 | AD100: =AVERAGE(C100:AB100) -> 9.0384615 | AE100: 0 | AF100: 0
B103: WEEK 2 WEEK CUP 2018
B104: POOLER/WEEK | C104: 1 | D104: 2 | E104: 3 | F104: 4 | G104: 5 | H104: 6 | I104: 7 | J104: 8 | K104: 9 | L104: 10 | M104: 11 | N104: 12 | O104: 13 | P104: 14 | Q104: 15 | R104: 16 | S104: 17 | T104: 18 | U104: 19 | V104: 20 | W104: 21 | X104: 22 | Y104: 23 | Z104: 24 | AA104: 25 | AB104: 26 | AC104: TOTAL | AD104: AVG | AE104: W | AF104: PD
...

Sheet 24
A1: 2023 | B1: DESROSIERS | D1: CHABOT | F1: BLIER | H1: BEAUCHEMIN | J1: PICARD | L1: MIOUSSE | N1: CONSTANTIN | P1: LESSARD | R1: ROBB | T1: MOROTTI | V1: HENAULT | X1: DIEGO | AB1: F | AC1: D | AD1: G | AE1: T
A2: 1 | B2: THOMPSON | C2: 56 | D2: TARASENKO | E2: 55 | F2: TOFFOLI | G2: 55 | H2: PASTRNAK | I2: 110 | J2: MARNER | K2: 85 | L2: TKACHUK M. | M2: 88 | N2: ROBERTSON | O2: 80 | P2: RANTANEN | Q2: 104 | R2: MACKINNON | S2: 140 | T2: DRAISAITL | U2: 106 | V2: BEDARD | W2: 61 | X2: MCDAVID | Y2: 132 | AA2: DESROSIERS | AB2: =SUMPRODUCT(LARGE(C2:C13,{1;2;3;4;5;6;7;8})) -> 447 | AC2: =SUMPRODUCT(LARGE(C14:C18,{1;2;3})) -> 110 | AD2: =LARGE(C19:C20,1) -> 93 | AE2: =C21 -> 52 | AL2: LESSY - Franchise Record | AQ2: Miousse - Sharpool Record
A3: 2 | B3: SUZUKI | C3: 77 | D3: PANARIN | E3: 120 | F3: KUCHEROV | G3: 144 | H3: STUTZLE | I3: 70 | J3: MILLER JT. | K3: 103 | L3: MATTHEWS | M3: 107 | N3: PAVELSKI | O3: 67 | P3: TAVARES | Q3: 65 | R3: HINTZ | S3: 65 | T3: POINT | U3: 90 | V3: GAUDREAU | W3: 60 | X3: HUGHES J. | Y3: 74 | AA3: CHABOT | AB3: =SUMPRODUCT(LARGE(E2:E13,{1;2;3;4;5;6;7;8})) -> 640 | AC3: =SUMPRODUCT(LARGE(E14:E18,{1;2;3})) -> 182 | AD3: =LARGE(E19:E20,1) -> 83 | AE3: =E21 -> 98 | AL3: Most points by a Forward Group | AQ3: Most points in a Season by a Defence Group
A4: 3 | B4: KOVALENKO | C4: 0 | D4: STAMKOS | E4: 81 | F4: PETTERSSON | G4: 89 | H4: HISCHIER | I4: 67 | J4: KAPRIZOV | K4: 96 | L4: GUENTZEL | M4: 77 | N4: BRATT | O4: 83 | P4: NELSON | Q4: 69 | R4: TROCHECK | S4: 77 | T4: TKACHUK B. | U4: 74 | V4: EICHEL | W4: 68 | X4: NYLANDER | Y4: 98 | AA4: BLIER | AB4: =SUMPRODUCT(LARGE(G2:G13,{1;2;3;4;5;6;7;8})) -> 636 | AC4: =SUMPRODUCT(LARGE(G14:G18,{1;2;3})) -> 142 | AD4: =LARGE(G19:G20,1) -> 60 | AE4: =G21 -> 113 | AL4: NEW - 2024 | AN4: OLD - 2022 | AQ4: NEW - 2024 | AS4: BEAUCH - OLD - 2023
A5: 4 | B5: KELLER | C5: 76 | D5: TUCH | E5: 59 | F5: CROSBY | G5: 94 | H5: BARKOV | I5: 80 | J5: SCHEIFELE | K5: 72 | L5: AHO | M5: 89 | N5: HORVAT | O5: 68 | P5: KANE P. | Q5: 47 | R5: BOESER | S5: 73 | T5: MALKIN | U5: 67 | V5: FORSBERG | W5: 94 | X5: CONNOR | Y5: 61 | AA5: BEAUCHEMIN | AB5: =SUMPRODUCT(LARGE(I2:I13,{1;2;3;4;5;6;7;8})) -> 599 | AC5: =SUMPRODUCT(LARGE(I14:I18,{1;2;3})) -> 167 | AD5: =LARGE(I19:I20,1) -> 91 | AE5: =I21 -> 81 | AL5: RANTANEN | AM5: 103 | AN5: PERRON | AO5: 57 | AQ5: HUGHES Q. | AR5: 92 | AS5: WERENSKI | AT5: 8
A6: 5 | B6: COZENS | C6: 47 | D6: KYROU | E6: 67 | F6: OVECHKIN | G6: 65 | H6: LARKIN | I6: 69 | J6: ZEGRAS | K6: 15 | L6: KEMPE | M6: 75 | N6: HUBERDEAU | O6: 52 | P6: SVECHNIKOV | Q6: 52 | R6: BUNTING | S6: 55 | T6: ZUCCARELLO | U6: 63 | V6: JOHNSON K. | W6: 16 | X6: GIROUX | Y6: 64 | AA6: PICARD | AB6: =SUMPRODUCT(LARGE(K2:K13,{1;2;3;4;5;6;7;8})) -> 576 | AC6: =SUMPRODUCT(LARGE(K14:K18,{1;2;3})) -> 152 | AD6: =LARGE(K19:K20,1) -> 88 | AE6: =K21 -> 102 | AG6: BEDARD | AH6: 69.5 | AL6: TAVARES | AM6: 64 | AN6: O'REILLY | AO6: 58 | AQ6: RIELLY | AR6: 58 | AS6: SEIDER | AT6: 42
A7: 6 | B7: MACCELLI | C7: 57 | D7: NECAS | E7: 53 | F7: VERHAEGHE | G7: 72 | H7: FIALA | I7: 73 | J7: LINDHOLM E. | K7: 44 | L7: BENIERS | M7: 37 | N7: WHEELER | O7: 21 | P7: KUZNETSOV | Q7: 24 | R7: KAKKO | S7: 19 | T7: DUBOIS | U7: 40 | V7: LUNDELL | W7: 35 | X7: MARCHAND | Y7: 67 | AA7: MIOUSSE | AB7: =SUMPRODUCT(LARGE(M2:M13,{1;2;3;4;5;6;7;8})) -> 644 | AC7: =SUMPRODUCT(LARGE(M14:M18,{1;2;3})) -> 193 | AD7: =LARGE(M19:M20,1) -> 88 | AE7: =M21 -> 111 | AG7: matchs | AH7: 66 | AL7: NELSON | AM7: 69 | AN7: TAVARES | AO7: 76 | AQ7: KLINGBERG | AR7: 5 | AS7: DOBSON | AT7: 49
A8: 7 | B8: COOLEY | C8: 44 | D8: THOMAS | E8: 86 | F8: BUCHNEVICH | G8: 63 | H8: CAUFIELD | I8: 65 | J8: KONECNY | K8: 68 | L8: BJORKSTRAND | M8: 59 | N8: KARLSSON W. | O8: 60 | P8: MCTAVICH | Q8: 42 | R8: TERAVAINEN | S8: 53 | T8: MARCHESSAULT | U8: 69 | V8: NORRIS | W8: 30 | X8: MEIER | Y8: 52 | AA8: CONSTANTIN | AB8: =SUMPRODUCT(LARGE(O2:O13,{1;2;3;4;5;6;7;8})) -> 562 | AC8: =SUMPRODUCT(LARGE(O14:O18,{1;2;3})) -> 175 | AD8: =LARGE(O19:O20,1) -> 98 | AE8: =O21 -> 98 | AG8: pts | AH8: =W2 -> 61 | AL8: KANE P. | AM8: 47 | AN8: SVECHNIKOV | AO8: 69 | AQ8: BURNS | AR8: 43 | AS8: KARLSSON E. | AT8: 101
A9: 8 | B9: FANTILLI | C9: 27 | D9: BOLDY | E9: 69 | F9: TERRY | G9: 54 | H9: MERCER | I9: 33 | J9: KANE E. | K9: 44 | L9: EHLERS | M9: 61 | N9: JOHNSTON | O9: 65 | P9: BERTUZZI | Q9: 43 | R9: BYFIELD | S9: 55 | T9: BARZAL | U9: 80 | V9: NUGENT-HOPKINS | W9: 67 | X9: RAYMOND | Y9: 72 | AA9: LESSARD | AB9: =SUMPRODUCT(LARGE(Q2:Q13,{1;2;3;4;5;6;7;8})) -> 555 | AC9: =SUMPRODUCT(LARGE(Q14:Q18,{1;2;3})) -> 143 | AD9: =LARGE(Q19:Q20,1) -> 72 | AE9: =Q21 -> 109 | AG9: pts/gp | AH9: =AH8/AH7 -> 0.92424242 | AL9: SVECHNIKOV | AM9: 52 | AN9: NYLANDER | AO9: 80 | AQ9: SEVERSON | AR9: 28 | AS9: DURZI | AT9: 38
A10: 9 | B10: CARLSSON | C10: 29 | D10: LAINE | E10: 9 | F10: SEGUIN | G10: 52 | H10: KNIES | I10: 35 | J10: NICHUSHKIN | K10: 53 | L10: HYMAN | M10: 77 | N10: HAGEL | O10: 75 | P10: DEBRINCAT | Q10: 67 | R10: KUZMENKO | S10: 46 | T10: RUST | U10: 56 | V10: VILARDI | W10: 36 | X10: DACH | Y10: 2 | AA10: ROBB | AB10: =SUMPRODUCT(LARGE(S2:S13,{1;2;3;4;5;6;7;8})) -> 587 | AC10: =SUMPRODUCT(LARGE(S14:S18,{1;2;3})) -> 109 | AD10: =LARGE(S19:S20,1) -> 22 | AE10: =S21 -> 47 | AG10: Matchs potentiels | AH10: =82-(AH13-AH7) -> 68 | AL10: KUZNETSOV | AM10: 24 | AN10: KELLER | AO10: 63 | AR10: 193 | AT10: 192
A11: 10 | B11: REICHEL | C11: 16 | D11: KADRI | E11: 75 | F11: STONE | G11: 53 | H11: ZACHA | I11: 59 | J11: SKINNER | K11: 46 | L11: KOPITAR | M11: 70 | N11: DEBRUSK | O11: 40 | P11: REINHART | Q11: 94 | R11: BATHERSON | S11: 66 | T11: BENNETT | U11: 41 | V11: MCCANN | W11: 62 | X11: ZIBANEJAD | Y11: 72 | AA11: MOROTTI | AB11: =SUMPRODUCT(LARGE(U2:U13,{1;2;3;4;5;6;7;8})) -> 605 | AC11: =SUMPRODUCT(LARGE(U14:U18,{1;2;3})) -> 147 | AD11: =LARGE(U19:U20,1) -> 65 | AE11: =U21 -> 107 | AG11: Projection | AH11: =AH10*AH9 -> 62.848485 | AL11: MCTAVICH | AM11: 42 | AN11: JOHANSEN | AO11: 63
A12: 11 | B12: SMITH W. | C12: 0 | D12: KREIDER | E12: 75 | F12: STEPHENSON | G12: 51 | H12: DUCHENE | I12: 65 | J12: HARTMAN | K12: 45 | L12: BENN | M12: 60 | N12: ERIKSSON EK | O12: 64 | P12: MITTELSTADT | Q12: 57 | R12: BARBASHEV | S12: 45 | T12: HALL | U12: 4 | V12: PERFETTI | W12: 38 | X12: HAYTON | Y12: 10 | AA12: HENAULT | AB12: =SUMPRODUCT(LARGE(W2:W13,{1;2;3;4;5;6;7;8})) -> 486 | AC12: =SUMPRODUCT(LARGE(W14:W18,{1;2;3})) -> 150 | AD12: =LARGE(W19:W20,1) -> 83 | AE12: =W21 -> 110 | AL12: BERTUZZI | AM12: 43 | AN12: DUBE | AO12: 32
A13: 12 | B13: SCHMALTZ | C13: 61 | D13: STROME D. | E13: 67 | F13: COUTURE | G13: 1 | H13: LAFRENIERE | I13: 57 | J13: TIPPETT | K13: 53 | L13: NOVAK | M13: 45 | N13: WRIGHT | O13: 5 | P13: BURAKOVSKY | Q13: 16 | R13: DROUIN | S13: 56 | T13: RAKELL | U13: 37 | V13: KALIYEV | W13: 15 | X13: HERTL | Y13: 38 | AA13: DIEGO | AB13: =SUMPRODUCT(LARGE(Y2:Y13,{1;2;3;4;5;6;7;8})) -> 640 | AC13: =SUMPRODUCT(LARGE(Y14:Y18,{1;2;3})) -> 180 | AD13: =LARGE(Y19:Y20,1) -> 68 | AE13: =Y21 -> 104 | AG13: Hawks GP | AH13: 80 | AL13: DEBRINCAT | AM13: 67 | AN13: VORACEK | AO13: 62
A14: 1 | B14: SANDERSON | C14: 38 | D14: FOX | E14: 73 | F14: HAMILTON | G14: 16 | H14: HEISKANEN | I14: 54 | J14: SERGACHEV | K14: 19 | L14: HUGHES Q. | M14: 92 | N14: HUGHES L. | O14: 47 | P14: TOEWS D. | Q14: 50 | R14: MILLER KA. | S14: 30 | T14: MORRISSEY | U14: 69 | V14: DOBSON | W14: 70 | X14: DUNN | Y14: 46 | AL14: REINHART | AM14: 94 | AN14: RADULOV | AO14: 22
A15: 2 | B15: DRYSDALE | C15: 10 | D15: DAHLIN | E15: 59 | F15: MAKAR | G15: 90 | H15: SEIDER | I15: 42 | J15: JOSI | K15: 85 | L15: RIELLY | M15: 58 | N15: HEDMAN | O15: 76 | P15: NURSE | Q15: 32 | R15: ANDERSSON | S15: 39 | T15: DEANGELO | U15: 11 | V15: MCAVOY | W15: 47 | X15: THEODORE | Y15: 42 | AL15: MITTELSTADT | AM15: 56 | AN15: ARVIDSSON | AO15: 49
A16: 3 | B16: MATHESON | C16: 62 | D16: DOUGHTY | E16: 50 | F16: ADDISON | G16: 17 | H16: WERENSKI | I16: 57 | J16: EKBLAD | K16: 18 | L16: KLINGBERG | M16: 5 | N16: FOWLER | O16: 39 | P16: CARLSON | Q16: 52 | R16: JONES S. | S16: 31 | T16: EKHOLM | U16: 45 | V16: POWER | W16: 33 | X16: CHABOT | Y16: 30 | AL16: BURAKOVSKY | AM16: 16 | AN16: ZUCCARELLO | AO16: 79
A17: 4 | B17: CLARKE | C17: 6 | D17: SANDIN | E17: 23 | F17: FAULK | G17: 30 | H17: KARLSSON E. | I17: 56 | J17: CHYCHRUN | K17: 41 | L17: BURNS | M17: 43 | N17: LETANG | O17: 51 | P17: DURZI | Q17: 41 | R17: FORSLING | S17: 39 | T17: PIETRANGELO | U17: 33 | V17: BYRAM | W17: 29 | X17: BOUCHARD | Y17: 82 | AM17: 552 | AO17: 550
A18: 5 | B18: ZELLWEGER | C18: 9 | D18: MOSER | E18: 26 | F18: GUHLE | G18: 22 | H18: MONTOUR | I18: 33 | J18: LINDHOLM H. | K18: 26 | L18: SEVERSON | M18: 28 | N18: HRONEK | O18: 48 | P18: GIRARD | Q18: 18 | R18: VALIMAKI | S18: 17 | T18: ORLOV | U18: 26 | V18: BARRIE | W18: 15 | X18: WEEGAR | Y18: 52
A19: 1 | B19: HELLEBUYCK | C19: 93 | D19: BINNINGTON | E19: 76 | F19: ULLMARK | G19: 60 | H19: GEORGIEV | I19: 91 | J19: SAROS | K19: 88 | L19: MARKSTROM | M19: 64 | N19: BOBROVSKY | O19: 98 | P19: JARRY | Q19: 72 | R19: HUSSO | S19: 22 | T19: ANDERSEN | U19: 37 | V19: SKINNER S. | W19: 83 | X19: SWAYMAN | Y19: 68
A20: 2 | B20: VASILEVSKY | C20: 72 | D20: OETTINGER | E20: 83 | F20: KUEMPER | G20: 34 | H20: LEVI | I20: 22 | J20: GUSTAVSSON | K20: 56 | L20: SHESTERKIN | M20: 88 | N20: KORPISALO | O20: 48 | P20: SOROKIN | Q20: 71 | R20: COPLEY | S20: 13 | T20: SAMSONOV | U20: 65 | V20: HILL | W20: 48 | X20: VANECEK | Y20: 39
A21: 1 | B21: CHICAGO | C21: 52 | D21: VEGAS | E21: 98 | F21: DALLAS | G21: 113 | H21: NEW JERSEY | I21: 81 | J21: TORONTO | K21: 102 | L21: CAROLINA | M21: 111 | N21: TAMPA BAY | O21: 98 | P21: BOSTON | Q21: 109 | R21: SAN JOSE | S21: 47 | T21: COLORADO | U21: 107 | V21: FLORIDA | W21: 110 | X21: EDMONTON | Y21: 104
C22: =VLOOKUP(B1,PTS!C:H,6,FALSE) -> 702 | E22: =VLOOKUP(D1,PTS!$C:$H,6,FALSE) -> 1003 | G22: =VLOOKUP(F1,PTS!$C:$H,6,FALSE) -> 951 | I22: =VLOOKUP(H1,PTS!$C:$H,6,FALSE) -> 938 | K22: =VLOOKUP(J1,PTS!$C:$H,6,FALSE) -> 918 | M22: =VLOOKUP(L1,PTS!$C:$H,6,FALSE) -> 1036 | O22: =VLOOKUP(N1,PTS!$C:$H,6,FALSE) -> 933 | Q22: =VLOOKUP(P1,PTS!$C:$H,6,FALSE) -> 879 | S22: =VLOOKUP(R1,PTS!$C:$H,6,FALSE) -> 765 | U22: =VLOOKUP(T1,PTS!$C:$H,6,FALSE) -> 924 | W22: =VLOOKUP(V1,PTS!$C:$H,6,FALSE) -> 829 | Y22: =VLOOKUP(X1,PTS!$C:$H,6,FALSE) -> 992
B31: =D2 -> TARASENKO | C31: =E2 -> 55
B32: =D3 -> PANARIN | C32: =E3 -> 120
B33: =D4 -> STAMKOS | C33: =E4 -> 81
B34: =D5 -> TUCH | C34: =E5 -> 59
B35: =D6 -> KYROU | C35: =E6 -> 67
B36: =D7 -> NECAS | C36: =E7 -> 53
B37: =D8 -> THOMAS | C37: =E8 -> 86
B38: =D9 -> BOLDY | C38: =E9 -> 69
B39: =D10 -> LAINE | C39: =E10 -> 9
B40: =D11 -> KADRI | C40: =E11 -> 75
B41: =D12 -> KREIDER | C41: =E12 -> 75
B42: =D13 -> STROME D. | C42: =E13 -> 67
... B50: =D21 -> VEGAS | C50: =E21 -> 98
B51: =F2 -> TOFFOLI | C51: =G2 -> 55
B52: =F3 -> KUCHEROV | C52: =G3 -> 144
B53: =F4 -> PETTERSSON | C53: =G4 -> 89
B54: =F5 -> CROSBY | C54: =G5 -> 94
B55: =F6 -> OVECHKIN | C55: =G6 -> 65
B56: =F7 -> VERHAEGHE | C56: =G7 -> 72
B57: =F8 -> BUCHNEVICH | C57: =G8 -> 63
B58: =F9 -> TERRY | C58: =G9 -> 54
B59: =F10 -> SEGUIN | C59: =G10 -> 52
B60: =F11 -> STONE | C60: =G11 -> 53
B61: =F12 -> STEPHENSON | C61: =G12 -> 51
B62: =F13 -> COUTURE | C62: =G13 -> 1
... B70: =F21 -> DALLAS | C70: =G21 -> 113
B71: =H2 -> PASTRNAK | C71: =I2 -> 110
B72: =H3 -> STUTZLE | C72: =I3 -> 70
B73: =H4 -> HISCHIER | C73: =I4 -> 67
B74: =H5 -> BARKOV | C74: =I5 -> 80
B75: =H6 -> LARKIN | C75: =I6 -> 69
B76: =H7 -> FIALA | C76: =I7 -> 73
B77: =H8 -> CAUFIELD | C77: =I8 -> 65
B78: =H9 -> MERCER | C78: =I9 -> 33
B79: =H10 -> KNIES | C79: =I10 -> 35
B80: =H11 -> ZACHA | C80: =I11 -> 59
B81: =H12 -> DUCHENE | C81: =I12 -> 65
B82: =H13 -> LAFRENIERE | C82: =I13 -> 57
... B90: =H21 -> NEW JERSEY | C90: =I21 -> 81
B91: =J2 -> MARNER | C91: =K2 -> 85
B92: =J3 -> MILLER JT. | C92: =K3 -> 103
B93: =J4 -> KAPRIZOV | C93: =K4 -> 96
B94: =J5 -> SCHEIFELE | C94: =K5 -> 72
B95: =J6 -> ZEGRAS | C95: =K6 -> 15
B96: =J7 -> LINDHOLM E. | C96: =K7 -> 44
B97: =J8 -> KONECNY | C97: =K8 -> 68
B98: =J9 -> KANE E. | C98: =K9 -> 44
B99: =J10 -> NICHUSHKIN | C99: =K10 -> 53
B100: =J11 -> SKINNER | C100: =K11 -> 46
B101: =J12 -> HARTMAN | C101: =K12 -> 45
B102: =J13 -> TIPPETT | C102: =K13 -> 53
... B110: =J21 -> TORONTO | C110: =K21 -> 102
B111: =L2 -> TKACHUK M. | C111: =M2 -> 88
B112: =L3 -> MATTHEWS | C112: =M3 -> 107
B113: =L4 -> GUENTZEL | C113: =M4 -> 77
B114: =L5 -> AHO | C114: =M5 -> 89
B115: =L6 -> KEMPE | C115: =M6 -> 75
B116: =L7 -> BENIERS | C116: =M7 -> 37
B117: =L8 -> BJORKSTRAND | C117: =M8 -> 59
B118: =L9 -> EHLERS | C118: =M9 -> 61
B119: =L10 -> HYMAN | C119: =M10 -> 77
B120: =L11 -> KOPITAR | C120: =M11 -> 70
B121: =L12 -> BENN | C121: =M12 -> 60
B122: =L13 -> NOVAK | C122: =M13 -> 45
... B130: =L21 -> CAROLINA | C130: =M21 -> 111
B131: =N2 -> ROBERTSON | C131: =O2 -> 80
B132: =N3 -> PAVELSKI | C132: =O3 -> 67
B133: =N4 -> BRATT | C133: =O4 -> 83
B134: =N5 -> HORVAT | C134: =O5 -> 68
B135: =N6 -> HUBERDEAU | C135: =O6 -> 52
B136: =N7 -> WHEELER | C136: =O7 -> 21
B137: =N8 -> KARLSSON W. | C137: =O8 -> 60
B138: =N9 -> JOHNSTON | C138: =O9 -> 65
B139: =N10 -> HAGEL | C139: =O10 -> 75
B140: =N11 -> DEBRUSK | C140: =O11 -> 40
B141: =N12 -> ERIKSSON EK | C141: =O12 -> 64
B142: =N13 -> WRIGHT | C142: =O13 -> 5
... B150: =N21 -> TAMPA BAY | C150: =O21 -> 98
...

Sheet 23
A1: 2023 | B1: PICARD | D1: CHABOT | F1: BEAUCHEMIN | H1: BLIER | J1: DIEGO | L1: LESSARD | N1: ROBB | P1: MOROTTI | R1: HENAULT | T1: MIOUSSE | V1: CONSTANTIN | X1: DESROSIERS | AB1: F | AC1: D | AD1: G | AE1: T | AG1: NEW | AI1: 2022 OLD
A2: 1 | B2: MILLER JT | C2: 82 | D2: STAMKOS | E2: 84 | F2: ZIBANEJAD | G2: 91 | H2: TERRY | I2: 61 | J2: CONNOR | K2: 81 | L2: KANE P. | M2: 57 | N2: MARNER | O2: 99 | P2: MACKINNON | Q2: 111 | R2: GAUDREAU | S2: 74 | T2: MATTHEWS | U2: 85 | V2: DRAISAITL | W2: 128 | X2: MCDAVID | Y2: 153 | AA2: PICARD | AB2: =SUMPRODUCT(LARGE(C2:C13,{1;2;3;4;5;6;7;8})) -> 610 | AC2: =SUMPRODUCT(LARGE(C14:C18,{1;2;3})) -> 133 | AD2: =LARGE(C19:C20,1) -> 103 | AE2: =C21 -> 91 | AG2: STAMKOS | AH2: 84 | AI2: DRAISAITL | AJ2: 110
A3: 2 | B3: KAPRIZOV | C3: 75 | D3: TKACHUK M | E3: 109 | F3: BARKOV | G3: 78 | H3: OVECHKIN | I3: 75 | J3: RANTANEN | K3: 105 | L3: TAVARES | M3: 80 | N3: KADRI | O3: 56 | P3: TKACHUK B | Q3: 83 | R3: EICHEL | S3: 66 | T3: DUCHENE | U3: 56 | V3: HUBERDEAU | W3: 55 | X3: MARCHAND | Y3: 67 | AA3: CHABOT | AB3: =SUMPRODUCT(LARGE(E2:E13,{1;2;3;4;5;6;7;8})) -> 613 | AC3: =SUMPRODUCT(LARGE(E14:E18,{1;2;3})) -> 186 | AD3: =LARGE(E19:E20,1) -> 102 | AE3: =E21 -> 109 | AG3: TKACHUK M | AH3: 109 | AI3: DEBRINCAT | AJ3: 78
A4: 3 | B4: LINDHOLM E. | C4: 64 | D4: DEBRINCAT | E4: 66 | F4: FIALA | G4: 72 | H4: CROSBY | I4: 93 | J4: REINHART | K4: 67 | L4: SVECHNIKOV | M4: 55 | N4: HINTZ | O4: 75 | P4: MARCHESSAULT | Q4: 57 | R4: FORSBERG | S4: 42 | T4: GUENTZEL | U4: 73 | V4: PAVELSKI | W4: 77 | X4: KUCHEROV | Y4: 112 | AA4: BEAUCHEMIN | AB4: =SUMPRODUCT(LARGE(G2:G13,{1;2;3;4;5;6;7;8})) -> 613 | AC4: =SUMPRODUCT(LARGE(G14:G18,{1;2;3})) -> 192 | AD4: =LARGE(G19:G20,1) -> 88 | AE4: =G21 -> 81 | AG4: DEBRINCAT | AH4: 66 | AI4: KOPITAR | AJ4: 67
A5: 4 | B5: ROBERTSON | C5: 109 | D5: THOMAS | E5: 65 | F5: LARKIN | G5: 79 | H5: BUCHNEVICH | I5: 67 | J5: MEIER | K5: 66 | L5: KELLER | M5: 86 | N5: TERAVAINEN | O5: 37 | P5: BARZAL | Q5: 51 | R5: JOHNSON K. | S5: 40 | T5: AHO | U5: 67 | V5: WHEELER | W5: 55 | X5: BERGERON | Y5: 58 | AA5: BLIER | AB5: =SUMPRODUCT(LARGE(I2:I13,{1;2;3;4;5;6;7;8})) -> 661 | AC5: =SUMPRODUCT(LARGE(I14:I18,{1;2;3})) -> 181 | AD5: =LARGE(I19:I20,1) -> 44 | AE5: =I21 -> 113 | AG5: THOMAS | AH5: 65 | AI5: ERIKSSON EK | AJ5: 50
A6: 5 | B6: SCHEIFELE | C6: 68 | D6: KYROU | E6: 73 | F6: HISCHIER | G6: 80 | H6: PETTERSSON | I6: 102 | J6: HUGHES J. | K6: 99 | L6: JOHANSEN | M6: 28 | N6: LANDESKOG | O6: 0 | P6: POINT | Q6: 95 | R6: NORRIS | S6: 3 | T6: PASTRNAK | U6: 113 | V6: SMITH R. | W6: 56 | X6: GIROUX | Y6: 79 | AA6: DIEGO | AB6: =SUMPRODUCT(LARGE(K2:K13,{1;2;3;4;5;6;7;8})) -> 648 | AC6: =SUMPRODUCT(LARGE(K14:K18,{1;2;3})) -> 146 | AD6: =LARGE(K19:K20,1) -> 89 | AE6: =K21 -> 93 | AG6: KYROU | AH6: 73 | AI6: TKACHUK M. | AJ6: 104
A7: 6 | B7: ZEGRAS | C7: 65 | D7: SUZUKI | E7: 66 | F7: STUTZLE | G7: 90 | H7: SCHENN | I7: 65 | J7: DACH | K7: 38 | L7: VORACEK | M7: 6 | N7: SCHWARTZ | O7: 40 | P7: RUST | Q7: 46 | R7: ROSLOVIC | S7: 44 | T7: EHLERS | U7: 38 | V7: HORVAT | W7: 70 | X7: SEGUIN | Y7: 50 | AA7: LESSARD | AB7: =SUMPRODUCT(LARGE(M2:M13,{1;2;3;4;5;6;7;8})) -> 523 | AC7: =SUMPRODUCT(LARGE(M14:M18,{1;2;3})) -> 151 | AD7: =LARGE(M19:M20,1) -> 75 | AE7: =M21 -> 95 | AG7: SUZUKI | AH7: 66 | AI7: LAINE | AJ7: 56
A8: 7 | B8: BACKSTROM | C8: 21 | D8: DUBOIS | E8: 63 | F8: CAUFIELD | G8: 36 | H8: VERHAEGHE | I8: 73 | J8: NYLANDER | K8: 87 | L8: PERRON | M8: 56 | N8: KAKKO | O8: 40 | P8: BENNETT | Q8: 40 | R8: CIRELLI | S8: 29 | T8: SHARANGOVICH | U8: 30 | V8: PACIORETTY | W8: 3 | X8: MALKIN | Y8: 83 | AA8: ROBB | AB8: =SUMPRODUCT(LARGE(O2:O13,{1;2;3;4;5;6;7;8})) -> 478 | AC8: =SUMPRODUCT(LARGE(O14:O18,{1;2;3})) -> 164 | AD8: =LARGE(O19:O20,1) -> 73 | AE8: =O21 -> 92 | AG8: DUBOIS | AH8: 63 | AI8: DUBOIS | AJ8: 60
A9: 8 | B9: KANE E. | C9: 28 | D9: LAINE | E9: 52 | F9: ERIKSSON EK | G9: 61 | H9: STONE | I9: 38 | J9: RAYMOND | K9: 45 | L9: ARVIDSSON | M9: 59 | N9: BYFIELD | O9: 22 | P9: MANTHA | Q9: 27 | R9: THOMPSON | S9: 94 | T9: HAYES | U9: 54 | V9: KARLSSON W. | W9: 53 | X9: PANARIN | Y9: 92 | AA9: MOROTTI | AB9: =SUMPRODUCT(LARGE(Q2:Q13,{1;2;3;4;5;6;7;8})) -> 551 | AC9: =SUMPRODUCT(LARGE(Q14:Q18,{1;2;3})) -> 100 | AD9: =LARGE(Q19:Q20,1) -> 93 | AE9: =Q21 -> 98 | AG9: LAINE | AH9: 52 | AI9: SUZUKI | AJ9: 61
A10: 9 | B10: KREIDER | C10: 54 | D10: NECAS | E10: 71 | F10: LAFRENIERE | G10: 39 | H10: VRANA | I10: 16 | J10: HYMAN | K10: 83 | L10: KUZNETSOV | M10: 55 | N10: BUNTING | O10: 49 | P10: ZUCCARELLO | Q10: 67 | R10: MANGIAPANE | S10: 43 | T10: BENIERS | U10: 57 | V10: COUTURIER | W10: 0 | X10: TARASENKO | Y10: 50 | AA10: HENAULT | AB10: =SUMPRODUCT(LARGE(S2:S13,{1;2;3;4;5;6;7;8})) -> 450 | AC10: =SUMPRODUCT(LARGE(S14:S18,{1;2;3})) -> 160 | AD10: =LARGE(S19:S20,1) -> 88 | AE10: =S21 -> 111 | AG10: NECAS | AH10: 71 | AI10: THOMAS | AJ10: 77
A11: 10 | B11: KOPITAR | C11: 74 | D11: BOLDY | E11: 63 | F11: BATHERSON | G11: 62 | H11: HERTL | I11: 63 | J11: JARVIS | K11: 39 | L11: BERTUZZI | M11: 30 | N11: BOESER | O11: 55 | P11: HALL | Q11: 36 | R11: LUNDELL | S11: 33 | T11: O'REILLY | U11: 30 | V11: BRATT | W11: 73 | X11: STROME R. | Y11: 41 | AA11: MIOUSSE | AB11: =SUMPRODUCT(LARGE(U2:U13,{1;2;3;4;5;6;7;8})) -> 572 | AC11: =SUMPRODUCT(LARGE(U14:U18,{1;2;3})) -> 150 | AD11: =LARGE(U19:U20,1) -> 97 | AE11: =U21 -> 103 | AG11: BOLDY | AH11: 63 | AI11: FARABEE | AJ11: 34
A12: 11 | B12: TOFFOLI | C12: 73 | D12: TUCH | E12: 79 | F12: SCHMALTZ | G12: 58 | H12: SKINNER | I12: 82 | J12: COPP | K12: 42 | L12: MCTAVICH | M12: 43 | N12: TROCHECK | O12: 64 | P12: GRANLUND | Q12: 41 | R12: NICHUSHKIN | S12: 47 | T12: BJORKSTRAND | U12: 45 | V12: HARTMAN | W12: 37 | X12: SLAFKOVSKY | Y12: 10 | AA12: CONSTANTIN | AB12: =SUMPRODUCT(LARGE(W2:W13,{1;2;3;4;5;6;7;8})) -> 579 | AC12: =SUMPRODUCT(LARGE(W14:W18,{1;2;3})) -> 149 | AD12: =LARGE(W19:W20,1) -> 54 | AE12: =W21 -> 109 | AG12: TUCH | AH12: 79 | AI12: PALAT | AJ12: 49
A13: 12 | B13: KONECNY | C13: 61 | D13: ROSSI | E13: 1 | F13: MERCER | G13: 56 | H13: NUGENT-HOPKINS | I13: 104 | J13: RAKELL | K13: 60 | L13: NELSON | M13: 75 | N13: WRIGHT | O13: 2 | P13: KESSEL | Q13: 36 | R13: QUINN | S13: 37 | T13: KEMPE | U13: 67 | V13: STEPHENSON | W13: 65 | X13: BURAKOVSKY | Y13: 39 | AA13: DESROSIERS | AB13: =SUMPRODUCT(LARGE(Y2:Y13,{1;2;3;4;5;6;7;8})) -> 694 | AC13: =SUMPRODUCT(LARGE(Y14:Y18,{1;2;3})) -> 178 | AD13: =LARGE(Y19:Y20,1) -> 66 | AE13: =Y21 -> 107 | AG13: ROSSI | AH13: 1 | AI13: KYROU | AJ13: 75
A14: 1 | B14: FORSLING | C14: 41 | D14: DAHLIN | E14: 73 | F14: WERENSKI | G14: 8 | H14: MAKAR | I14: 66 | J14: SANDERSON | K14: 32 | L14: CARLSON | M14: 29 | N14: HUGHES Q. | O14: 76 | P14: SEVERSON | Q14: 33 | R14: MCAVOY | S14: 52 | T14: FOX | U14: 72 | V14: HEDMAN | W14: 49 | X14: JOSI | Y14: 59 | AG14: DAHLIN | AH14: 73 | AI14: HUGHES | AJ14: 68
A15: 2 | B15: EKBLAD | C15: 38 | D15: DRYSDALE | E15: 0 | F15: SEIDER | G15: 42 | H15: GIORDANO | I15: 24 | J15: THEODORE | K15: 41 | L15: KRUG | M15: 32 | N15: JONES S. | O15: 37 | P15: SLAVIN | Q15: 27 | R15: WEEGAR | S15: 31 | T15: GIRARD | U15: 37 | V15: LETANG | W15: 41 | X15: DUNN | Y15: 64 | AG15: DRYSDALE | AH15: 0 | AI15: MCAVOY | AJ15: 56
A16: 3 | B16: PIETRANGELO | C16: 54 | D16: BURNS | E16: 61 | F16: DOBSON | G16: 49 | H16: HAMILTON | I16: 74 | J16: BOUCHARD | K16: 40 | L16: NURSE | M16: 43 | N16: ANDERSSON | O16: 49 | P16: PIONK | Q16: 33 | R16: HEISKANEN | S16: 73 | T16: RIELLY | U16: 41 | V16: TOEWS D. | W16: 50 | X16: ELLIS | Y16: 0 | AG16: BURNS | AH16: 61 | AI16: KARLSSON | AJ16: 35
A17: 4 | B17: CHYCHRUN | C17: 33 | D17: DOUGHTY | E17: 52 | F17: KARLSSON E. | G17: 101 | H17: GOSTISBEHERE | I17: 41 | J17: CHABOT | K17: 41 | L17: MORRISSEY | M17: 76 | N17: HANIFIN | O17: 38 | P17: EKHOLM | Q17: 32 | R17: BYRAM | S17: 24 | T17: KLINGBERG | U17: 33 | V17: FAULK | W17: 50 | X17: BARRIE | Y17: 55 | AG17: DOUGHTY | AH17: 52 | AI17: DRYSDALE | AJ17: 32
A18: 5 | B18: BOQVIST | C18: 22 | D18: TROUBA | E18: 30 | F18: DURZI | G18: 38 | H18: ADDISON | I18: 29 | J18: SERGACHEV | K18: 64 | L18: EDVINSSON | M18: 2 | N18: HRONEK | O18: 39 | P18: SPURGEON | Q18: 34 | R18: POWER | S18: 35 | T18: PETRY | U18: 31 | V18: FOWLER | W18: 48 | X18: DEANGELO | Y18: 42 | AG18: TROUBA | AH18: 30 | AI18: SUBBAN | AJ18: 22
A19: 1 | B19: SAROS | C19: 81 | D19: BINNINGTON | E19: 70 | F19: HELLEBUYCK | G19: 88 | H19: DEMKO | I19: 37 | J19: SOROKIN | K19: 89 | L19: JARRY | M19: 65 | N19: CAMPBELL | O19: 51 | P19: SHESTERKIN | Q19: 93 | R19: VASILEVSKY | S19: 88 | T19: ULLMARK | U19: 97 | V19: BOBROVSKY | W19: 54 | X19: FLEURY | Y19: 60 | AG19: BINNINGTON | AH19: 70 | AI19: KUEMPER | AJ19: 93
A20: 2 | B20: GEORGIEV | C20: 103 | D20: OETTINGER | E20: 102 | F20: MERZLIKINS | G20: 18 | H20: QUICK | I20: 44 | J20: SWAYMAN | K20: 64 | L20: SAMSONOV | M20: 75 | N20: HUSSO | O20: 73 | P20: ANDERSEN | Q20: 48 | R20: MURRAY | S20: 33 | T20: MARKSTROM | U20: 65 | V20: TALBOT | W20: 39 | X20: KUEMPER | Y20: 66 | AG20: OETTINGER | AH20: 102 | AI20: BINNINGTON | AJ20: 46
A21: 1 | B21: PITTSBURGH | C21: 91 | D21: EDMONTON | E21: 109 | F21: ST LOUIS | G21: 81 | H21: CAROLINA | I21: 113 | J21: CALGARY | K21: 93 | L21: WINNIPEG | M21: 95 | N21: FLORIDA | O21: 92 | P21: TAMPA BAY | Q21: 98 | R21: TORONTO | S21: 111 | T21: MINNESOTA | U21: 103 | V21: COLORADO | W21: 109 | X21: NEW YORK R | Y21: 107 | AG21: EDMONTON | AH21: 109 | AI21: FLORIDA | AJ21: 122
C22: 937 | E22: 1010 | G22: 974 | I22: 999 | K22: 976 | M22: 937 | O22: 807 | Q22: 842 | S22: 809 | U22: 922 | W22: 891 | Y22: 1045
AG24: NEW | AI24: 2018 OLD
AG25: ULLMARK | AH25: 93 | AI25: QUICK | AJ25: 92
AG26: MARKSTROM | AH26: 61 | AI26: LUNDQVIST | AJ26: 67
AG28: NEW | AI28: 2019 OLD
AG29: NEW YORK R | AH29: 101 | AI29: TORONTO | AJ29: 100
B31: =D2 -> STAMKOS | C31: =E2 -> 84
B32: =D3 -> TKACHUK M | C32: =E3 -> 109
B33: =D4 -> DEBRINCAT | C33: =E4 -> 66
B34: =D5 -> THOMAS | C34: =E5 -> 65
B35: =D6 -> KYROU | C35: =E6 -> 73
B36: =D7 -> SUZUKI | C36: =E7 -> 66
B37: =D8 -> DUBOIS | C37: =E8 -> 63
B38: =D9 -> LAINE | C38: =E9 -> 52
B39: =D10 -> NECAS | C39: =E10 -> 71
B40: =D11 -> BOLDY | C40: =E11 -> 63
B41: =D12 -> TUCH | C41: =E12 -> 79
B42: =D13 -> ROSSI | C42: =E13 -> 1
... B50: =D21 -> EDMONTON | C50: =E21 -> 109
B51: =F2 -> ZIBANEJAD | C51: =G2 -> 91
B52: =F3 -> BARKOV | C52: =G3 -> 78
B53: =F4 -> FIALA | C53: =G4 -> 72
B54: =F5 -> LARKIN | C54: =G5 -> 79
B55: =F6 -> HISCHIER | C55: =G6 -> 80
B56: =F7 -> STUTZLE | C56: =G7 -> 90
B57: =F8 -> CAUFIELD | C57: =G8 -> 36
B58: =F9 -> ERIKSSON EK | C58: =G9 -> 61
B59: =F10 -> LAFRENIERE | C59: =G10 -> 39
B60: =F11 -> BATHERSON | C60: =G11 -> 62
B61: =F12 -> SCHMALTZ | C61: =G12 -> 58
B62: =F13 -> MERCER | C62: =G13 -> 56
... B70: =F21 -> ST LOUIS | C70: =G21 -> 81
B71: =H2 -> TERRY | C71: =I2 -> 61
B72: =H3 -> OVECHKIN | C72: =I3 -> 75
B73: =H4 -> CROSBY | C73: =I4 -> 93
B74: =H5 -> BUCHNEVICH | C74: =I5 -> 67
B75: =H6 -> PETTERSSON | C75: =I6 -> 102
B76: =H7 -> SCHENN | C76: =I7 -> 65
B77: =H8 -> VERHAEGHE | C77: =I8 -> 73
B78: =H9 -> STONE | C78: =I9 -> 38
B79: =H10 -> VRANA | C79: =I10 -> 16
B80: =H11 -> HERTL | C80: =I11 -> 63
B81: =H12 -> SKINNER | C81: =I12 -> 82
B82: =H13 -> NUGENT-HOPKINS | C82: =I13 -> 104
... B90: =H21 -> CAROLINA | C90: =I21 -> 113
B91: =J2 -> CONNOR | C91: =K2 -> 81
B92: =J3 -> RANTANEN | C92: =K3 -> 105
B93: =J4 -> REINHART | C93: =K4 -> 67
B94: =J5 -> MEIER | C94: =K5 -> 66
B95: =J6 -> HUGHES J. | C95: =K6 -> 99
B96: =J7 -> DACH | C96: =K7 -> 38
B97: =J8 -> NYLANDER | C97: =K8 -> 87
B98: =J9 -> RAYMOND | C98: =K9 -> 45
B99: =J10 -> HYMAN | C99: =K10 -> 83
B100: =J11 -> JARVIS | C100: =K11 -> 39
B101: =J12 -> COPP | C101: =K12 -> 42
B102: =J13 -> RAKELL | C102: =K13 -> 60
... B110: =J21 -> CALGARY | C110: =K21 -> 93
B111: =L2 -> KANE P. | C111: =M2 -> 57
B112: =L3 -> TAVARES | C112: =M3 -> 80
B113: =L4 -> SVECHNIKOV | C113: =M4 -> 55
B114: =L5 -> KELLER | C114: =M5 -> 86
B115: =L6 -> JOHANSEN | C115: =M6 -> 28
B116: =L7 -> VORACEK | C116: =M7 -> 6
B117: =L8 -> PERRON | C117: =M8 -> 56
B118: =L9 -> ARVIDSSON | C118: =M9 -> 59
B119: =L10 -> KUZNETSOV | C119: =M10 -> 55
B120: =L11 -> BERTUZZI | C120: =M11 -> 30
B121: =L12 -> MCTAVICH | C121: =M12 -> 43
B122: =L13 -> NELSON | C122: =M13 -> 75
... B130: =L21 -> WINNIPEG | C130: =M21 -> 95
B131: =N2 -> MARNER | C131: =O2 -> 99
B132: =N3 -> KADRI | C132: =O3 -> 56
B133: =N4 -> HINTZ | C133: =O4 -> 75
B134: =N5 -> TERAVAINEN | C134: =O5 -> 37
B135: =N6 -> LANDESKOG | C135: =O6 -> 0
B136: =N7 -> SCHWARTZ | C136: =O7 -> 40
B137: =N8 -> KAKKO | C137: =O8 -> 40
B138: =N9 -> BYFIELD | C138: =O9 -> 22
...

Sheet 22
A1: 2022 | B1: DESROSIERS | D1: BLIER | F1: LESSARD | H1: MOROTTI | J1: PICARD | L1: MIOUSSE | N1: BEAUCHEMIN | P1: HENAULT | R1: DIEGO | T1: CHABOT | V1: ROBB | X1: CONSTANTIN
A2: 1 | B2: ZIBANEJAD | C2: 81 | D2: STONE | E2: 30 | F2: PERRON | G2: 57 | H2: BENNETT | I2: 49 | J2: SCHEIFELE | K2: 70 | L2: KANE | M2: 92 | N2: MARNER | O2: 97 | P2: PANARIN | Q2: 96 | R2: RANTANEN | S2: 92 | T2: DRAISAITL | U2: 110 | V2: MACKINNON | W2: 88 | X2: MCDAVID | Y2: 123
A3: 2 | B3: MARCHAND | C3: 80 | D3: CROSBY | E3: 84 | F3: O'REILLY | G3: 58 | H3: CONNOR | I3: 93 | J3: BACKSTROM | K3: 31 | L3: AHO | M3: 81 | N3: BARKOV | O3: 88 | P3: MILLER | Q3: 99 | R3: BOESER | S3: 46 | T3: DEBRINCAT | U3: 78 | V3: LANDESKOG | W3: 59 | X3: HUBERDEAU | Y3: 115
A4: 3 | B4: KUCHEROV | C4: 69 | D4: BUCHNEVICH | E4: 76 | F4: TAVARES | G4: 76 | H4: POINT | I4: 58 | J4: KAPRIZOV | K4: 108 | L4: GUENTZEL | M4: 84 | N4: NECAS | O4: 40 | P4: TOFFOLI | Q4: 49 | R4: REINHART | S4: 82 | T4: KOPITAR | U4: 67 | V4: HERTL | W4: 64 | X4: PACIORETTY | Y4: 37
A5: 4 | B5: BERGERON | C5: 65 | D5: TROCHECK | E5: 51 | F5: SVECHNIKOV | G5: 69 | H5: BARZAL | I5: 59 | J5: GAUDREAU | K5: 115 | L5: PASTRNAK | M5: 77 | N5: FIALA | O5: 85 | P5: HALL | Q5: 61 | R5: MEIER | S5: 76 | T5: ERIKSSON EK | U5: 49 | V5: HINTZ | W5: 72 | X5: PAVELSKI | Y5: 81
A6: 5 | B6: EICHEL | C6: 25 | D6: SCHENN | E6: 58 | F6: NYLANDER | G6: 80 | H6: MARCHESSAULT | I6: 66 | J6: LINDHOLM | K6: 82 | L6: EHLERS | M6: 55 | N6: MANTHA | O6: 23 | P6: FORSBERG | Q6: 84 | R6: HUGHES | S6: 56 | T6: TKACHUK M. | U6: 104 | V6: NUGENT-HOPKINS | W6: 50 | X6: WHEELER | Y6: 60
A7: 6 | B7: HOFFMAN | C7: 35 | D7: KONECKNY | E7: 52 | F7: KELLER | G7: 63 | H7: TKACHUK B. | I7: 67 | J7: KAPANEN | K7: 32 | L7: OVECHKIN | M7: 90 | N7: LARKIN | O7: 69 | P7: GALLAGHER | Q7: 24 | R7: DACH | S7: 26 | T7: LAINE | U7: 56 | V7: KADRI | W7: 87 | X7: COUTURIER | Y7: 17
A8: 7 | B8: TOEWS | C8: 37 | D8: STAMKOS | E8: 106 | F8: JOHANSEN | G8: 63 | H8: EBERLE | I8: 44 | J8: LABANC | K8: 6 | L8: HORVAT | M8: 52 | N8: LAFRENIERE | O8: 31 | P8: VILARDI | Q8: 7 | R8: GLASS | S8: 1 | T8: DUBOIS | U8: 60 | V8: SCHWARTZ | W8: 23 | X8: COUTURE | Y8: 56
A9: 8 | B9: SEGUIN | C9: 49 | D9: PETTERSSON | E9: 68 | F9: DUBE | G9: 32 | H9: WILSON | I9: 52 | J9: ROBERTSON | K9: 79 | L9: HAYES | M9: 31 | N9: TARASENKO | O9: 82 | P9: CIRELLI | Q9: 43 | R9: MATTHEWS | S9: 106 | T9: SUZUKI | U9: 61 | V9: KAKKO | W9: 18 | X9: SMITH | Y9: 38
A10: 9 | B10: GIROUX | C10: 65 | D10: PERFETTI | E10: 7 | F10: VORACEK | G10: 62 | H10: BEAUVILLIER | I10: 34 | J10: BJORKSTRAND | K10: 57 | L10: DUCHENE | M10: 86 | N10: HICSHIER | O10: 60 | P10: BURAKOVSKI | Q10: 61 | R10: BAILEY | S10: 44 | T10: THOMAS | U10: 77 | V10: TERAVAINEN | W10: 65 | X10: LEE | Y10: 46
A11: 10 | B11: KUBALIK | C11: 32 | D11: VRANA | E11: 19 | F11: RADULOV | G11: 22 | H11: RUST | I11: 58 | J11: ZEGRAS | K11: 61 | L11: VAN RIEMSDYK | M11: 38 | N11: CAUFIELD | O11: 43 | P11: COPP | Q11: 53 | R11: MONAHAN | S11: 23 | T11: FARABEE | U11: 34 | V11: BYFIELD | W11: 10 | X11: KARLSSON | Y11: 35
A12: 11 | B12: MALKIN | C12: 42 | D12: GARLAND | E12: 52 | F12: ARVIDSSON | G12: 49 | H12: ATKINSON | I12: 50 | J12: HYMAN | K12: 54 | L12: COMTOIS | M12: 16 | N12: KUZNETSOV | O12: 78 | P12: ROSLOVIC | Q12: 45 | R12: DROUIN | S12: 20 | T12: PALAT | U12: 49 | V12: BENN | W12: 46 | X12: TUCH | Y12: 38
A13: 12 | B13: STROME | C13: 54 | D13: VERHAEGE | E13: 55 | F13: ZUCCARELLO | G13: 79 | H13: ROSSI | I13: 0 | J13: KESSEL | K13: 52 | L13: SHARANGOVICH | M13: 46 | N13: STUTZLE | O13: 58 | P13: NORRIS | Q13: 55 | R13: GOURDE | S13: 48 | T13: KYROU | U13: 75 | V13: STEPHENSON | W13: 64 | X13: OSHIE | Y13: 25
... A21: 1 | B21: ISLANDERS | C21: 84 | D21: TORONTO | E21: 115 | F21: COLORADO | G21: 119 | H21: BOSTON | I21: 107 | J21: MINNESOTA | K21: 113 | L21: TAMPA BAY | M21: 110 | N21: WINNIPEG | O21: 89 | P21: WASHINGTON | Q21: 100 | R21: CAROLINA | S21: 116 | T21: FLORIDA | U21: 122 | V21: VEGAS | W21: 94 | X21: EDMONTON | Y21: 104
C22: 778 | E22: 896 | G22: 890 | I22: 875 | K22: 1011 | M22: 894 | O22: 971 | Q22: 844 | S22: 895 | U22: 1006 | W22: 889 | Y22: 922

Sheet 21
A1: 2021 | B1: DESROSIERS | D1: PICARD | F1: ROBB | H1: BLIER | J1: CONSTANTIN | L1: MOROTTI | N1: CHABOT | P1: MIOUSSE | R1: HENAULT | T1: BEAUCHEMIN | V1: LESSARD | X1: DIEGO
A2: 1 | B2: SUZUKI | C2: 41 | D2: NELSON | E2: 33 | F2: SCHEIFELE | G2: 63 | H2: KANE | I2: 66 | J2: HUBERDEAU | K2: 61 | L2: PANARIN | M2: 58 | N2: EICHEL | O2: 18 | P2: PASTRNAK | Q2: 48 | R2: ZIBANEJAD | S2: 50 | T2: MACKINNON | U2: 65 | V2: DRAISAITL | W2: 84 | X2: KUCHEROV
A3: 2 | B3: MCDAVID | C3: 105 | D3: PERRON | E3: 58 | F3: TERAVAINEN | G3: 15 | H3: STAMKOS | I3: 34 | J3: PACIORETTY | K3: 51 | L3: CONNOR | M3: 50 | N3: MARNER | O3: 67 | P3: OVECHKIN | Q3: 42 | R3: MILLER | S3: 46 | T3: BARKOV | U3: 58 | V3: O'REILLY | W3: 54 | X3: VRANA | Y3: 36
A4: 3 | B4: MARCHAND | C4: 69 | D4: GAUDREAU | E4: 48 | F4: NUGENT-HOPKINS | G4: 35 | H4: PETTERSSON | I4: 21 | J4: WHEELER | K4: 46 | L4: POINT | M4: 48 | N4: LAINE | O4: 24 | P4: AHO | Q4: 57 | R4: KUZNETSOV | S4: 29 | T4: LARKIN | U4: 23 | V4: SVECHNIKOV | W4: 42 | X4: REINHART | Y4: 40
A5: 4 | B5: MATTHEWS | C5: 66 | D5: LINDHOLM | E5: 47 | F5: SCHWARTZ | G5: 21 | H5: SCHENN | I5: 36 | J5: COUTURIER | K5: 41 | L5: BARZAL | M5: 45 | N5: KOPITAR | O5: 50 | P5: STONE | Q5: 61 | R5: HALL | S5: 33 | T5: MANTHA | U5: 29 | V5: TAVARES | W5: 50 | X5: MEIER | Y5: 31
A6: 5 | B6: TOEWS | D6: BACKSTROM | E6: 53 | F6: LANDESKOG | G6: 52 | H6: CROSBY | I6: 62 | J6: RANTANEN | K6: 66 | L6: MARCHESSAULT | M6: 44 | N6: TKACHUK M. | O6: 43 | P6: EHLERS | Q6: 46 | R6: FORSBERG | S6: 32 | T6: HISCHIER | U6: 11 | V6: NYLANDER | W6: 42 | X6: BOESER | Y6: 48
A7: 6 | B7: HOFFMAN | C7: 36 | D7: HYMAN | E7: 33 | F7: KADRI | G7: 32 | H7: BAILEY | I7: 35 | J7: COUTURE | K7: 31 | L7: TKACHUK B. | M7: 36 | N7: DUBOIS | O7: 21 | P7: HORVAT | Q7: 39 | R7: DOMI | S7: 24 | T7: KASE | U7: 0 | V7: MONAHAN | W7: 28 | X7: HUGHES | Y7: 31
A8: 7 | B8: BERGERON | C8: 48 | D8: LABANC | E8: 28 | F8: HERTL | G8: 43 | H8: TROCHECK | I8: 43 | J8: PAVELSKI | K8: 51 | L8: EBERLE | M8: 33 | N8: DEBRINCAT | O8: 56 | P8: GIROUX | Q8: 43 | R8: CIRELLI | S8: 22 | T8: TARASENKO | U8: 14 | V8: KELLER | W8: 35 | X8: DROUIN | Y8: 23
A9: 8 | B9: SEGUIN | C9: 2 | D9: ARVIDSSON | E9: 25 | F9: KAKKO | G9: 17 | H9: KONECKNY | I9: 34 | J9: KOTKANIEMI | K9: 20 | L9: JOHNSON | M9: 22 | N9: MALKIN | O9: 28 | P9: GUENTZEL | Q9: 57 | R9: GALLAGHER | S9: 23 | T9: LAFRENIERE | U9: 21 | V9: JOHANSEN | W9: 22 | X9: DACH | Y9: 10
A10: 9 | B10: DZINGEL | C10: 13 | D10: KAPRIZOV | E10: 51 | F10: MITTELSTADT | G10: 22 | H10: PERFETTI | J10: SMITH | K10: 25 | L10: BEAUVILLIER | M10: 28 | N10: STROME R. | O10: 49 | P10: HAYES | Q10: 31 | R10: KREIDER | S10: 30 | T10: FIALA | U10: 40 | V10: TUCH | W10: 33 | X10: KARLSSON | Y10: 39
A11: 10 | B11: VORACEK | C11: 43 | D11: BJORKSTRAND | E11: 44 | F11: OLOFSSON | G11: 32 | H11: RUST | I11: 42 | J11: KUBALIK | K11: 38 | L11: WILSON | M11: 33 | N11: BERTUZZI | O11: 7 | P11: COYLE | Q11: 16 | R11: ZUCKER | S11: 18 | T11: YAMAMOTO | U11: 21 | V11: STAAL E | W11: 13 | X11: KANE E. | Y11: 49
A12: 11 | B12: TATAR | C12: 30 | D12: GUSEV | E12: 10 | F12: DADONOV | G12: 20 | H12: BUCHNEVICH | I12: 48 | J12: KILLORN | K12: 33 | L12: ATKINSON | M12: 34 | N12: BENN | O12: 35 | P12: SKINNER | Q12: 14 | R12: TOFFOLI | S12: 44 | T12: BURAKOVSKY | U12: 44 | V12: RADULOV | W12: 12 | X12: GURIANOV | Y12: 30
A13: 12 | B13: PULJUJARVI | C13: 25 | D13: KAPANEN | E13: 30 | F13: HINTZ | G13: 43 | H13: PALMIERI | I13: 21 | J13: LEE | K13: 19 | L13: OSHIE | M13: 43 | N13: THOMAS | O13: 12 | P13: DUCHENE | Q13: 13 | R13: VILARDI | S13: 23 | T13: NECAS | U13: 41 | V13: DUBE | W13: 19 | X13: GLASS | Y13: 10
A14: 1 | B14: DAHLIN | C14: 23 | D14: CARLSON | E14: 44 | F14: KRUG | G14: 32 | H14: FOX | I14: 47 | J14: DEANGELO | K14: 1 | L14: MAKAR | M14: 44 | N14: BOQVIST | O14: 16 | P14: DOUGHTY | Q14: 33 | R14: PIONK | S14: 32 | T14: PETRY | U14: 42 | V14: HEDMAN | W14: 45 | X14: JOSI | Y14: 33
A15: 2 | B15: THEODORE | C15: 42 | D15: PIETRANGELO | E15: 23 | F15: GOSTISBEHERE | G15: 20 | H15: WERENSKI | I15: 20 | J15: HUGHES | K15: 41 | L15: KARLSSON | M15: 22 | N15: GIRARD | O15: 32 | P15: TROUBA | Q15: 12 | R15: HEISKANEN | S15: 27 | T15: BURNS | U15: 29 | V15: SPURGEON | W15: 25 | X15: CHABOT | Y15: 31
A16: 3 | B16: DUMBA | C16: 21 | D16: EKBLAD | E16: 22 | F16: ELLIS | G16: 18 | H16: HAMILTON | I16: 42 | J16: PULOCK | K16: 17 | L16: JONES | M16: 28 | N16: EKMAN-LARSSON | O16: 24 | P16: WEBER | Q16: 19 | R16: SCHMIDT | S16: 15 | T16: SERGACHEV | U16: 30 | V16: LETANG | W16: 45 | X16: PROVOROV | Y16: 26
A17: 4 | B17: BYRAM | C17: 2 | D17: EKHOLM | E17: 23 | F17: MORRISSEY | G17: 21 | H17: GIORDANO | I17: 26 | J17: EDLER | K17: 7 | L17: KLINGBERG | M17: 36 | N17: MCAVOY | O17: 30 | P17: SLAVIN | Q17: 15 | R17: YANDLE | S17: 27 | T17: RIELLY | U17: 35 | V17: SUTER | W17: 19 | X17: CHYCHRUN | Y17: 41
A18: 5 | B18: LEHTONEN | C18: 6 | D18: BARRIE | E18: 48 | F18: BOUCHARD | G18: 5 | H18: SUBBAN | I18: 19 | J18: GUSTAFSSON | K18: 12 | L18: SHATTENKIRK | M18: 15 | N18: RISTOLAINEN | O18: 18 | P18: PARAYKO | Q18: 12 | R18: HEINOLA | S18: 0 | T18: HRONEK | U18: 26 | V18: NURSE | W18: 36 | X18: BEAR | Y18: 8
A19: 1 | B19: PRICE | C19: 32 | D19: KHUDOBIN | E19: 44 | F19: MARKSTROM | G19: 55 | H19: FLEURY | I19: 72 | J19: BINNINGTON | K19: 46 | L19: HELLEBUYCK | M19: 63 | N19: ANDERSEN | O19: 31 | P19: SAMSONOV | Q19: 35 | R19: VASILEVSKY | S19: 86 | T19: SHESTERKIN | U19: 41 | V19: RASK | W19: 42 | X19: HART | Y19: 26
A20: 2 | B20: BOBROVSKY | C20: 40 | D20: KUEMPER | E20: 29 | F20: FRANCOUZ | H20: HOLTBY | I20: 18 | J20: MRAZEK | K20: 24 | L20: HALAK | M20: 28 | N20: DEMKO | O20: 36 | P20: BISHOP | R20: GIBSON | S20: 34 | T20: GRUBAUER | U20: 86 | V20: LEHNER | W20: 33 | X20: JARRY | Y20: 67
A21: 1 | B21: COLORADO | C21: 82 | D21: DALLAS | E21: 60 | F21: ST LOUIS | G21: 63 | H21: TORONTO | I21: 77 | J21: NEW YORK R | K21: 60 | L21: BOSTON | M21: 73 | N21: CALGARY | O21: 55 | P21: WASHINGTON | Q21: 77 | R21: TAMPA BAY | S21: 75 | T21: PHILADELPHIA | U21: 58 | V21: VEGAS | W21: 82 | X21: VANCOUVER | Y21: 50
C22: 646 | E22: 586 | G22: 513 | I22: 630 | K22: 563 | M22: 602 | O22: 519 | Q22: 572 | S22: 535 | U22: 572 | W22: 618 | Y22: 526

Sheet 20
A1: 2020 | B1: DESROSIERS | D1: BEAUCHEMIN | F1: FORCIER | H1: HENAULT | J1: CHABOT | L1: ROBB | N1: BLIER | P1: PICARD | R1: MOROTTI | T1: MIOUSSE | V1: DIEGO | X1: LESSARD
A2: 1 | B2: KUCHEROV | C2: 85 | D2: MANTHA | E2: 38 | F2: WHEELER | G2: 65 | H2: HUBERDEAU | I2: 78 | J2: MARNER | K2: 67 | L2: MACKINNON | M2: 93 | N2: CROSBY | O2: 47 | P2: GAUDREAU | Q2: 58 | R2: PASTRNAK | S2: 95 | T2: KANE P. | U2: 84 | V2: HUGHES | W2: 21 | X2: MONAHAN | Y2: 48
A3: 2 | B3: DRAISAITL | C3: 110 | D3: BARKOV | E3: 62 | F3: RANTANEN | G3: 41 | H3: TKACHUK M. | I3: 61 | J3: DEBRINCAT | K3: 45 | L3: SEGUIN | M3: 50 | N3: STAMKOS | O3: 66 | P3: LINDHOLM | Q3: 54 | R3: POINT | S3: 64 | T3: AHO | U3: 66 | V3: MATTHEWS | W3: 80 | X3: TAVARES | Y3: 60
A4: 3 | B4: MARCHAND | C4: 87 | D4: PANARIN | E4: 95 | F4: SCHEIFELE | G4: 73 | H4: KUZNETSOV | I4: 52 | J4: EICHEL | K4: 78 | L4: TERAVAINEN | M4: 63 | N4: ZIBANEJAD | O4: 75 | P4: BACKSTROM | Q4: 54 | R4: DUCHENE | S4: 42 | T4: GUENTZEL | U4: 43 | V4: RADULOV | W4: 34 | X4: O'REILLY | Y4: 61
A5: 4 | B5: OVECHKIN | C5: 67 | D5: KESSEL | E5: 38 | F5: TOEWS | G5: 60 | H5: DOMI | I5: 44 | J5: DUBOIS | K5: 49 | L5: LANDESKOG | M5: 44 | N5: PETTERSSON | O5: 66 | P5: MALKIN | Q5: 74 | R5: CONNOR | S5: 73 | T5: STONE | U5: 63 | V5: KANE E. | W5: 47 | X5: ZUCCARELLO | Y5: 37
A6: 5 | B6: BERGERON | C6: 56 | D6: LARKIN | E6: 53 | F6: COUTURIER | G6: 59 | H6: DADONOV | I6: 47 | J6: LAINE | K6: 63 | L6: NUGENT-HOPKINS | M6: 61 | N6: SCHENN | O6: 58 | P6: ATKINSON | Q6: 26 | R6: BARZAL | S6: 60 | T6: SKINNER | U6: 23 | V6: BOESER | W6: 45 | X6: KELLER | Y6: 44
A7: 6 | B7: STASTNY | C7: 38 | D7: TARASENKO | E7: 10 | F7: COUTURE | G7: 39 | H7: MILLER | I7: 72 | J7: TURRIS | K7: 31 | L7: KREIDER | M7: 45 | N7: TROCHECK | O7: 38 | P7: ARVIDSSON | Q7: 28 | R7: EBERLE | S7: 40 | T7: HORVAT | U7: 53 | V7: VAN RIEMSDYK | W7: 40 | X7: SVECHNIKOV | Y7: 61
A8: 7 | B8: HYMAN | C8: 37 | D8: BENN | E8: 39 | F8: PACIORETTY | G8: 66 | H8: HALL | I8: 52 | J8: VORACEK | K8: 56 | L8: SCHWARTZ | M8: 57 | N8: SCHMALTZ | O8: 45 | P8: PERRON | Q8: 60 | R8: JOHANSSON | S8: 30 | T8: EHLERS | U8: 58 | V8: DEBRUSK | W8: 35 | X8: NAMESTNIKOV | Y8: 31
A9: 8 | B9: MCDAVID | C9: 97 | D9: HISCHIER | E9: 36 | F9: PAVELSKI | G9: 31 | H9: FORSBERG | I9: 48 | J9: KOPITAR | K9: 62 | L9: MITTELSTADT | M9: 9 | N9: KARLSSON | O9: 46 | P9: STROME | Q9: 38 | R9: HERTL | S9: 36 | T9: COYLE | U9: 37 | V9: MEIER | W9: 49 | X9: NYLANDER | Y9: 59
A10: 9 | B10: HOFFMAN | C10: 59 | D10: GALCHENYUK | E10: 24 | F10: GETZLAF | G10: 42 | H10: HAYES | I10: 41 | J10: TKACHUK B. | K10: 44 | L10: KAKKO | M10: 23 | N10: BAILEY | O10: 43 | P10: LABANC | Q10: 33 | R10: MARCHESSAULT | S10: 47 | T10: WENNBERG | U10: 22 | V10: REINHART | W10: 50 | X10: KONECNY | Y10: 61
A11: 10 | B11: STAAL E. | C11: 47 | D11: HIROSE | E11: 7 | F11: KREJCI | G11: 43 | H11: ANTHANASIOU | I11: 26 | J11: GRANLUND | K11: 30 | L11: GOURDE | M11: 30 | N11: OSHIE | O11: 49 | P11: NIEDERREITTER | Q11: 29 | R11: RAKELL | S11: 42 | T11: GIROUX | U11: 53 | V11: DROUIN | W11: 15 | X11: JOHANSEN | Y11: 36
A12: 11 | B12: CIRELLI | C12: 44 | D12: KASE | E12: 24 | F12: KOTKANIEMI | G12: 8 | H12: DZINGEL | I12: 29 | J12: GUSEV | K12: 44 | L12: KADRI | M12: 36 | N12: THORNTON | O12: 31 | P12: TATAR | Q12: 61 | R12: PARISE | S12: 46 | T12: WHITE | U12: 23 | V12: VRANA | W12: 52 | X12: NYQUIST | Y12: 42
A13: 12 | B13: NEAL | C13: 31 | D13: BUCHNEVICH | E13: 46 | F13: JOST | G13: 23 | H13: SMITH | I13: 54 | J13: COMTOIS | K13: 11 | L13: LEE | M13: 43 | N13: HINTZ | O13: 33 | P13: GALLAGHER | Q13: 43 | R13: JOHNSON | S13: 31 | T13: PALMIERI | U13: 45 | V13: TOLVANEN | W13: - | X13: TUCH | Y13: 17
A14: 1 | B14: BARRIE | C14: 39 | D14: BURNS | E14: 45 | F14: RISTOLAINEN | G14: 33 | H14: MURRAY | I14: 9 | J14: WEBER | K14: 36 | L14: MAKAR | M14: 50 | N14: HEDMAN | O14: 55 | P14: CARLSON | Q14: 75 | R14: YANDLE | S14: 45 | T14: KLINGBERG | U14: 32 | V14: CHABOT | W14: 39 | X14: GUSTAFSSON | Y14: 29
A15: 2 | B15: GOSTISBEHERE | C15: 12 | D15: SERGACHEV | E15: 34 | F15: JOSI | G15: 65 | H15: LETANG | I15: 44 | J15: DAHLIN | K15: 40 | L15: DOUGHTY | M15: 35 | N15: WERENSKI | O15: 41 | P15: PIETRANGELO | Q15: 52 | R15: KARLSSON | S15: 40 | T15: MILLER | U15: 11 | V15: HANIFIN | W15: 22 | X15: SPURGEON | Y15: 32
A16: 3 | B16: SHATTENKIRK | C16: 34 | D16: RIELLY | E16: 27 | F16: SUBBAN | G16: 18 | H16: MCDONAGH | I16: 12 | J16: HEISKANEN | K16: 35 | L16: EKMAN-LARSSON | M16: 30 | N16: HAMILTON | O16: 40 | P16: EKBLAD | Q16: 41 | R16: JONES | S16: 30 | T16: TROUBA | U16: 27 | V16: PROVOROV | W16: 36 | X16: SLAVIN | Y16: 36
A17: 4 | B17: DUMBA | C17: 24 | D17: KRUG | E17: 49 | F17: HUGHES | G17: 53 | H17: FAULK | I17: 16 | J17: MCAVOY | K17: 32 | L17: BUTCHER | M17: 21 | N17: PULOCK | O17: 35 | P17: GARDINER | Q17: 24 | R17: VLASIC | S17: 15 | T17: MORRISSEY | U17: 31 | V17: THEODORE | W17: 46 | X17: NURSE | Y17: 33
A18: 5 | B18: BRANNSTROM | C18: 4 | D18: DUNN | E18: 23 | F18: DOBSON | G18: 7 | H18: SCHMIDT | I18: 31 | J18: GIRARD | K18: 34 | L18: SCHULTZ | M18: 12 | N18: GIORDANO | O18: 31 | P18: EKHOLM | Q18: 33 | R18: BYFUGLIEN | S18: - | T18: PETRY | U18: 40 | V18: CHYCHRUN | W18: 26 | X18: ELLIS | Y18: 38
A19: 1 | B19: HELLEBUYCK | C19: 89 | D19: PRICE | E19: 72 | F19: BOBROVSKY | G19: 55 | H19: BINNINGTON | I19: 78 | J19: RINNE | K19: 63 | L19: VASILEVSKY | M19: 90 | N19: FLEURY | O19: 74 | P19: ANDERSEN | Q19: 74 | R19: JONES | S19: 44 | T19: RASK | U19: 77 | V19: HART | W19: 54 | X19: LEHNER | Y19: 46
A20: 2 | B20: BISHOP | C20: 56 | D20: DUBNYK | E20: 29 | F20: MURRAY | G20: 50 | H20: GREISS | I20: 39 | J20: GRUBAUER | K20: 46 | L20: GIBSON | M20: 48 | N20: HOLTBY | O20: 58 | P20: MRAZEK | Q20: 53 | R20: TALBOT | S20: 31 | T20: CRAWFORD | U20: 38 | V20: SCHNEIDER | W20: 13 | X20: MARKSTROM | Y20: 58
A21: 1 | B21: COLORADO | C21: 92 | D21: TORONTO | E21: 81 | F21: CALGARY | G21: 79 | H21: DALLAS | I21: 82 | J21: WASHINGTON | K21: 90 | L21: TAMPA BAY | M21: 92 | N21: VEGAS | O21: 86 | P21: ST LOUIS | Q21: 94 | R21: BOSTON | S21: 100 | T21: NASHVILLE | U21: 78 | V21: NEW JERSEY | W21: 68 | X21: SAN JOSE | Y21: 63
C22: 886 | E22: 688 | G22: 734 | I22: 715 | K22: 728 | M22: 753 | O22: 748 | Q22: 778 | S22: 728 | U22: 723 | W22: 641 | Y22: 664

Sheet 19
A1: 2019 | B1: BEAUCHEMIN | D1: FORCIER | F1: CHABOT | H1: DESROSIERS | J1: HENAULT | L1: PICARD | N1: MIOUSSE | P1: MOROTTI | R1: LESSARD | T1: DIEGO | V1: BLIER | X1: DAVID
A2: 1 | B2: BENN | C2: 53 | D2: VORACEK | E2: 66 | F2: EICHEL | G2: 82 | H2: KOPITAR | I2: 60 | J2: WHEELER | K2: 91 | L2: MALKIN | M2: 72 | N2: EHLERS | O2: 37 | P2: CONNOR | Q2: 66 | R2: KELLER | S2: 47 | T2: MCDAVID | U2: 116 | V2: STAMKOS | W2: 98 | X2: GIROUX | Y2: 85
A3: 2 | B3: KUCHEROV | C3: 128 | D3: MACKINNON | E3: 99 | F3: LAINE | G3: 50 | H3: MARCHAND | I3: 100 | J3: HALL | K3: 37 | L3: BACKSTROM | M3: 74 | N3: HUBERDEAU | O3: 92 | P3: PASTRNAK | Q3: 81 | R3: GAUDREAU | S3: 99 | T3: RADULOV | U3: 72 | V3: CROSBY | W3: 100 | X3: SEGUIN | Y3: 80
A4: 3 | B4: KESSEL | C4: 82 | D4: RANTANEN | E4: 87 | F4: MARNER | G4: 94 | H4: TAVARES | I4: 88 | J4: KUZNETSOV | K4: 72 | L4: GETZLAF | M4: 48 | N4: PAVELSKI | O4: 64 | P4: RAKELL | Q4: 43 | R4: NYLANDER | S4: 27 | T4: MATTHEWS | U4: 73 | V4: BAILEY | W4: 56 | X4: TERAVAINEN | Y4: 76
A5: 4 | B5: PANARIN | C5: 87 | D5: COUTURE | E5: 70 | F5: POINT | G5: 92 | H5: KANE | I5: 110 | J5: MARCHESSAULT | K5: 59 | L5: ARVIDSSON | M5: 48 | N5: AHO | O5: 83 | P5: BARZAL | Q5: 62 | R5: O'REILLY | S5: 77 | T5: KADRI | U5: 44 | V5: SCHENN | W5: 54 | X5: LANDESKOG | Y5: 75
A6: 5 | B6: BARKOV | C6: 96 | D6: SCHEIFELE | E6: 84 | F6: FORSBERG | G6: 50 | H6: DRAISAITL | I6: 105 | J6: GRANLUND | K6: 54 | L6: STEEN | M6: 27 | N6: STONE | O6: 73 | P6: BORGSTROM | Q6: 18 | R6: TURRIS | S6: 23 | T6: VAN RIEMSDYK | U6: 48 | V6: ZUCKER | W6: 42 | X6: DROUIN | Y6: 53
A7: 6 | B7: TARASENKO | C7: 68 | D7: PACIORETTY | E7: 40 | F7: JOHANSEN | G7: 64 | H7: BERGERON | I7: 79 | J7: MILLER | K7: 47 | L7: ATKINSON | M7: 69 | N7: SKINNER | O7: 63 | P7: EBERLE | Q7: 37 | R7: OKPOSO | S7: 29 | T7: E. KANE | U7: 56 | V7: JOHNSON | W7: 47 | X7: NUGENT-HOPKINS | Y7: 69
A8: 7 | B8: LARKIN | C8: 73 | D8: KOVALCHUK | E8: 34 | F8: REINHART | G8: 65 | H8: THORNTON | I8: 51 | J8: HOFFMAN | K8: 70 | L8: MONAHAN | M8: 82 | N8: GUENTZEL | O8: 76 | P8: DONATO | Q8: 25 | R8: KREIDER | S8: 52 | T8: SAAD | U8: 47 | V8: ZIBANEJAD | W8: 74 | X8: STAAL | Y8: 52
A9: 8 | B9: GALCHENYUK | C9: 41 | D9: COUTRURIER | E9: 76 | F9: DUBOIS | G9: 61 | H9: OVECHKIN | I9: 89 | J9: TKACHUK M. | K9: 77 | L9: SMITH | M9: 53 | N9: HORVAT | O9: 61 | P9: GALLAGHER | Q9: 52 | R9: SPEZZA | S9: 27 | T9: LUCIC | U9: 20 | V9: TROCHECK | W9: 34 | X9: MITTLESTADT | Y9: 25
A10: 9 | B10: HICSHIER | C10: 47 | D10: CARTER | E10: 33 | F10: KONECKNY | G10: 49 | H10: KARLSSON | I10: 56 | J10: DOMI | K10: 72 | L10: PERRON | M10: 46 | N10: COYLE | O10: 34 | P10: NIEDERREITTER | Q10: 53 | R10: SVECHNIKOV | S10: 37 | T10: RASK | U10: 9 | V10: PETTERSSON | W10: 66 | X10: SCHWARTZ | Y10: 36
A11: 10 | B11: OSHIE | C11: 54 | D11: TOEWS | E11: 81 | F11: PATRICK | G11: 31 | H11: STASTNY | I11: 42 | J11: DADONOV | K11: 70 | L11: HAYES | M11: 54 | N11: WENNBERG | O11: 25 | P11: JOHANSSON | Q11: 30 | R11: ZADINA | S11: 3 | T11: BOESER | U11: 56 | V11: SCHMALTZ | W11: 25 | X11: LEE | Y11: 51
A12: 11 | B12: MANTHA | C12: 48 | D12: STEPAN | E12: 35 | F12: FABBRI | G12: 6 | H12: HYMAN | I12: 41 | J12: PALMIERI | K12: 50 | L12: LINDHOLM | M12: 78 | N12: BURAKOVSKY | O12: 25 | P12: DEBRINCAT | Q12: 76 | R12: HAULA | S12: 7 | T12: DEBRUSK | U12: 42 | V12: FIALA | W12: 39 | X12: HORNQVIST | Y12: 37
A13: 12 | B13: TOLVANEN | C13: 2 | D13: TKACHUK B. | E13: 45 | F13: BRASSARD | G13: 23 | H13: NISHUSHKIN | I13: 10 | J13: GOURDE | K13: 48 | L13: TOFFOLI | M13: 34 | N13: KASE | O13: 20 | P13: DUCHENE | Q13: 70 | R13: NAMESTNIKOV | S13: 31 | T13: BROWN | U13: 51 | V13: PERRY | W13: 10 | X13: ZUCCARELLO | Y13: 40
... A21: 1 | B21: NASHVILLE | C21: 100 | D21: WINNIPEG | E21: 99 | F21: ST LOUIS | G21: 99 | H21: TORONTO | I21: 100 | J21: COLUMBUS | K21: 98 | L21: TAMPA BAY | M21: 128 | N21: LOS ANGELES | O21: 71 | P21: WASHINGTON | Q21: 104 | R21: BOSTON | S21: 107 | T21: CHICAGO | U21: 84 | V21: VEGAS | W21: 93 | X21: PITTSBURGH | Y21: 100
C22: 968 | E22: 955 | G22: 890 | I22: 999 | K22: 911 | M22: 864 | O22: 794 | Q22: 823 | S22: 759 | U22: 780 | W22: 869 | Y22: 872

Sheet 18
A1: 2018 | B1: PICARD | D1: FORCIER | F1: BEAUCHEMIN | H1: LESSARD | J1: CHABOT | L1: DESROSIERS | N1: MORROTI | P1: MIOUSSE | R1: DIEGO | T1: HENAULT | V1: BLIER
A2: 1 | B2: BACKSTROM | C2: 71 | D2: SCHEIFELE | E2: 60 | F2: TARASENKO | G2: 66 | H2: GAUDREAU | I2: 84 | J2: BENN | K2: 79 | L2: KANE | M2: 76 | N2: PASTRNAK | O2: 80 | P2: GUENTZEL | Q2: 48 | R2: VAN RIEMSDYK | S2: 54 | T2: MCDAVID | U2: 108 | V2: CROSBY | W2: 89
A3: 2 | B3: GETZALF | C3: 61 | D3: MARCHAND | E3: 85 | F3: KUCHEROV | G3: 100 | H3: VORACEK | I3: 85 | J3: LAINE | K3: 70 | L3: DRAISAITL | M3: 70 | N3: WHEELER | O3: 91 | P3: OVECHKIN | Q3: 87 | R3: MATTHEWS | S3: 63 | T3: HOFFMAN | U3: 56 | V3: ZIBANEJAD | W3: 47
A4: 3 | B4: SEGUIN | C4: 78 | D4: MALKIN | E4: 98 | F4: KESSEL | G4: 92 | H4: MONAHAN | I4: 64 | J4: EHLERS | K4: 60 | L4: TAVARES | M4: 84 | N4: JOHANSSON | O4: 14 | P4: PAVELSKI | Q4: 66 | R4: KESLER | S4: 14 | T4: KUZNETSOV | U4: 83 | V4: SCHENN | W4: 70
A5: 4 | B5: SKINNER | C5: 49 | D5: PACIORETTY | E5: 37 | F5: GIROUX | G5: 102 | H5: O'REILLY | I5: 61 | J5: JOHANSEN | K5: 54 | L5: NYLANDER W. | M5: 61 | N5: EICHEL | O5: 64 | P5: CARTER | Q5: 22 | R5: SAAD | S5: 35 | T5: HALL | U5: 93 | V5: SHEARY | W5: 30
A6: 5 | B6: ATKINSON | C6: 46 | D6: OSHIE | E6: 47 | F6: GALCHENYUK | G6: 51 | H6: TURRIS | I6: 51 | J6: FORSBERG | K6: 64 | L6: WENNBERG | M6: 35 | N6: SCHWARTZ | O6: 59 | P6: ZUCCARELLO | Q6: 53 | R6: LUCIC | S6: 34 | T6: REINHART | U6: 50 | V6: SIMMONDS | W6: 46
A7: 6 | B7: TOEWS | C7: 52 | D7: MACKINNON | E7: 97 | F7: LANDESKOG | G7: 62 | H7: PERRY | I7: 49 | J7: DROUIN | K7: 46 | L7: BERGERON | M7: 63 | N7: EBERLE | O7: 59 | P7: STONE | Q7: 62 | R7: RASK | S7: 31 | T7: DOMI | U7: 45 | V7: PALAT | W7: 35
A8: 7 | B8: STEPAN | C8: 56 | D8: RANTANEN | E8: 84 | F8: RYAN | G8: 33 | H8: PALMIERI | I8: 44 | J8: STASTNY | K8: 53 | L8: KOPITAR | M8: 92 | N8: D. SEDIN | O8: 55 | P8: TATAR | Q8: 34 | R8: NUGENT HOPKINS | S8: 48 | T8: TOFFOLI | U8: 47 | V8: KOIVU | W8: 45
A9: 8 | B9: STEEN | C9: 46 | D9: JENNER | E9: 32 | F9: PANARIN | G9: 82 | H9: OKPOSO | I9: 44 | J9: STAAL E. | K9: 76 | L9: PULJUJARVI | M9: 20 | N9: BRASSARD | O9: 46 | P9: DUCHENE | Q9: 59 | R9: STAMKOS | S9: 86 | T9: GALLAGHER | U9: 54 | V9: ANISIMOV | W9: 31
A10: 9 | B10: HUBERDEAU | C10: 69 | D10: HORVAT | E10: 44 | F10: BARKOV | G10: 78 | H10: NIELSEN | I10: 33 | J10: MARNER | K10: 69 | L10: THORNTON | M10: 36 | N10: SHARP | O10: 21 | P10: AHO | Q10: 65 | R10: KADRI | S10: 55 | T10: GRANLUND | U10: 67 | V10: JOHNSON | W10: 50
A11: 10 | B11: ARVIDSSON | C11: 61 | D11: COUTURE | E11: 61 | F11: TROCHEK | G11: 75 | H11: ZETTERBERG | I11: 56 | J11: SHIPACHYOV | K11: 1 | L11: RADULOV | M11: 72 | N11: NIEDERREITTER | O11: 32 | P11: COYLE | Q11: 37 | R11: EAVES | S11: 1 | T11: TKACHUK | U11: 49 | V11: BAILEY | W11: 71
A12: 11 | B12: SILFVERBERG | C12: 40 | D12: H. SEDIN | E12: 50 | F12: FOLIGNO | G12: 33 | H12: SPEZZA | I12: 26 | J12: LINDHOLM | K12: 44 | L12: KREJCI | M12: 44 | N12: RAKELL | O12: 69 | P12: BURAKOVSKY | Q12: 25 | R12: E. KANE | S12: 54 | T12: MARCHESSAULT | U12: 75 | V12: ZUCKER | W12: 64
A13: 12 | B13: TERAVAINEN | C13: 64 | D13: KOVALCHUK | E13: - | F13: LARKIN | G13: 62 | H13: KREIDER | I13: 37 | J13: POINT | K13: 66 | L13: HISCHIER | M13: 52 | N13: LEE | O13: 62 | P13: PEARSON | Q13: 40 | R13: DADONOV | S13: 65 | T13: MILLER | U13: 58 | V13: HORNQVIST | W13: 49
A14: 1 | B14: KEITH | C14: 32 | D14: KLINGBERG | E14: 67 | F14: ELLIS | G14: 32 | H14: BYFUGLIEN | I14: 45 | J14: LEDDY | K14: 42 | L14: SUBBAN | M14: 59 | N14: HEDMAN | O14: 63 | P14: KARLSSON | Q14: 62 | R14: BURNS | S14: 67 | T14: WERENSKI | U14: 37 | V14: KRUG | W14: 59
A15: 2 | B15: JONES | C15: 57 | D15: JOSI | E15: 53 | F15: RISTOLAINEN | G15: 41 | H15: PARAYKO | I15: 35 | J15: FAULK | K15: 31 | L15: GIORDANO | M15: 38 | N15: WEBER | O15: 16 | P15: DUMBA | Q15: 50 | R15: GOSTISBEHERE | S15: 65 | T15: EKMAN LARSON | U15: 42 | V15: HAMILTON | W15: 44
A16: 3 | B16: GARDINER | C16: 52 | D16: MCDONAGH | E16: 29 | F16: FOWLER | G16: 32 | H16: YANDLE | I16: 55 | J16: SHATTENKIRK | K16: 23 | L16: EKBLAD | M16: 38 | N16: LARSON | O16: 13 | P16: BARRIE | Q16: 57 | R16: VATANEN | S16: 32 | T16: HAMONIC | U16: 11 | V16: SCHULTZ | W16: 27
A17: 4 | B17: PIETRANGELO | C17: 54 | D17: SUTER | E17: 51 | F17: LETANG | G17: 51 | H17: SEABROOK | I17: 26 | J17: DOUGHTY | K17: 60 | L17: CARLSON | M17: 68 | N17: VLASIC | O17: 32 | P17: SKJEI | Q17: 25 | R17: HANIFIN | S17: 32 | T17: KLEFBOM | U17: 21 | V17: TROUBA | W17: 24
A18: 5 | B18: BRODIE | C18: 32 | D18: CHABOT | E18: 25 | F18: THEODORE | G18: 29 | H18: MUZZIN | I18: 42 | J18: MCAVOY | K18: 32 | L18: PROVOROV | M18: 41 | N18: GREEN | O18: 33 | P18: CHYCHRUN | Q18: 14 | R18: SLAVIN | S18: 30 | T18: ZAITSEV | U18: 13 | V18: GOLIGOSKY | W18: 35
A19: 1 | B19: GIBSON | C19: 83 | D19: PRICE | E19: 42 | F19: RINNE | G19: 114 | H19: JONES | I19: 78 | J19: BISHOP | K19: 74 | L19: TALBOT | M19: 70 | N19: MURRAY | O19: 62 | P19: QUICK | Q19: 92 | R19: BOBROVSKY | S19: 101 | T19: ANDERSEN | U19: 98 | V19: HOLTBY | W19: 72
A20: 2 | B20: ALLEN | C20: 62 | D20: RASK | E20: 86 | F20: DUBNYK | G20: 98 | H20: CRAWFORD | I20: 40 | J20: VASILEVSKI | K20: 119 | L20: VARLAMOV | M20: 63 | N20: ELLIOTT | O20: 58 | P20: LUNDQVIST | Q20: 67 | R20: ANDERSON | S20: 58 | T20: SMITH | U20: 69 | V20: FLEURY | W20: 76
A21: 1 | B21: MINNESOTA | C21: 101 | D21: NASHVILLE | E21: 117 | F21: ANAHEIM | G21: 101 | H21: SAN JOSE | I21: 100 | J21: TAMPA BAY | K21: 113 | L21: DALLAS | M21: 92 | N21: WASHINGTON | O21: 105 | P21: PITTSBURGH | Q21: 100 | R21: CHICAGO | S21: 76 | T21: COLUMBUS | U21: 97 | V21: EDMONTON | W21: 78
A22: Total | C22: 859 | E22: 956 | G22: 996 | I22: 814 | K22: 904 | M22: 900 | O22: 833 | Q22: 841 | S22: 801 | U22: 889 | W22: 756

Sheet 17
A1: 2017 | B1: FORCIER | D1: LESSARD | F1: MOROTTI | H1: PICARD | J1: DESROSIERS | L1: CHABOT | N1: BEAUCHEMIN | P1: MIOUSSE | R1: HENAULT | T1: DIEGO
A2: 1 | B2: CROSBY | C2: 89 | D2: BENN | E2: 69 | F2: KANE | G2: 89 | H2: SEGUIN | I2: 72 | J2: MCDAVID | K2: 100 | L2: SCHEIFELE | M2: 82 | N2: BACKSTROM | O2: 86 | P2: OVECHKIN | Q2: 69 | R2: GAUDREAU | S2: 61 | T2: PANARIN | U2: 74
A3: 2 | B3: MALKIN | C3: 72 | D3: BARKOV | E3: 52 | F3: JOHNSON | G3: 45 | H3: TARASENKO | I3: 75 | J3: TAVARES | K3: 66 | L3: JOHANSEN | M3: 61 | N3: GIROUX | O3: 58 | P3: PAVELSKI | Q3: 68 | R3: KUZNETSOV | S3: 59 | T3: STAMKOS | U3: 20
A4: 3 | B4: MACKINNON | C4: 53 | D4: PERRY | E4: 53 | F4: WHEELER | G4: 74 | H4: GETZLAF | I4: 73 | J4: KOPITAR | K4: 52 | L4: FORSBERG | M4: 58 | N4: KUCHEROV | O4: 85 | P4: DUCHENE | Q4: 41 | R4: HALL | S4: 53 | T4: THORNTON | U4: 50
A5: 4 | B5: PACIORRETY | C5: 67 | D5: MONAHAN | E5: 58 | F5: EICHEL | G5: 57 | H5: HUBERDEAU | I5: 26 | J5: BERGERON | K5: 53 | L5: LAINE | M5: 64 | N5: GALCHENYUK | O5: 44 | P5: CARTER | Q5: 66 | R5: COUTURE | S5: 52 | T5: LUCIC | U5: 50
A6: 5 | B6: MARCHAND | C6: 85 | D6: VORACEK | E6: 61 | F6: EBERLE | G6: 51 | H6: TOEWS | I6: 58 | J6: SIMMONDS | K6: 54 | L6: VAN RIEMSDYK | M6: 62 | N6: KESSEL | O6: 70 | P6: ZUCCARELLO | Q6: 59 | R6: DOMI | S6: 38 | T6: MATTHEWS | U6: 69
A7: 6 | B7: OSHIE | C7: 56 | D7: O'REILLY | E7: 55 | F7: SCHWARTZ | G7: 55 | H7: SEDIN D. | I7: 44 | J7: PULJUJARVI | K7: 8 | L7: DROUIN | M7: 53 | N7: PARISE | O7: 42 | P7: STONE | Q7: 54 | R7: TOFFOLI | S7: 34 | T7: SPEZZA | U7: 50
A8: 7 | B8: SEDIN H. | C8: 51 | D8: OKPOSO | E8: 45 | F8: LITTLE | G8: 47 | H8: STEPAN | I8: 55 | J8: STROME D. | K8: 1 | L8: ZIBANEJAD | M8: 37 | N8: NEAL | O8: 41 | P8: SCHENN | Q8: 55 | R8: LARKIN | S8: 32 | T8: NUGENT-HOPKINS | U8: 43
A9: 8 | B9: DUCLAIR | C9: 15 | D9: TURRIS | E9: 55 | F9: BRASSARD | G9: 39 | H9: SKINNER | I9: 63 | J9: DARISAITL | K9: 77 | L9: TROCHEK | M9: 54 | N9: LANGDESKOG | O9: 33 | P9: MARLEAU | Q9: 46 | R9: HOFFMAN | S9: 61 | T9: SAAD | U9: 53
A10: 9 | B10: NASH | C10: 38 | D10: PALMIERI | E10: 53 | F10: SHARP | G10: 18 | H10: ATKINSON | I10: 62 | J10: NYLANDER W. | K10: 61 | L10: RADULOV | M10: 54 | N10: PALAT | O10: 52 | P10: SPOONER | Q10: 39 | R10: GALLAGHER | S10: 29 | T10: HORNQVIST | U10: 44
A11: 10 | B11: JENNER | C11: 34 | D11: LADD | E11: 31 | F11: JOHANSSON | G11: 58 | H11: HANZAL | I11: 39 | J11: JAGR | K11: 46 | L11: HENRIQUE | M11: 40 | N11: ERIKSSON | O11: 24 | P11: COUTURIER | Q11: 34 | R11: REINHART | S11: 47 | T11: RASK | U11: 45
A12: 11 | B12: HERTL | C12: 22 | D12: NIELSEN | E12: 41 | F12: STASTNY | G12: 40 | H12: KOIVU | I12: 58 | J12: WENNBERG | K12: 59 | L12: STEEN | M12: 51 | N12: RYAN | O12: 25 | P12: TATAR | Q12: 46 | R12: NYQUIST | S12: 48 | T12: KESLER | U12: 58
A13: 12 | B13: RANTANEN | C13: 38 | D13: JOKINEN | E13: 28 | F13: HUDLER | G13: 11 | H13: ZETTERBERG | I13: 68 | J13: KREJCI | K13: 54 | L13: EHLERS | M13: 64 | N13: VESEY | O13: 27 | P13: PASTRNAK | Q13: 70 | R13: BOEDKER | S13: 26 | T13: PLECANEK | U13: 28
... A21: 1 | B21: ANAHEIM | C21: 105 | D21: TAMPA BAY | E21: 94 | F21: WASHINGTON | G21: 118 | H21: CHICAGO | I21: 109 | J21: FLORIDA | K21: 81 | L21: ST. LOUIS | M21: 99 | N21: PITTSBURGH | O21: 111 | P21: LOS ANGELES | Q21: 86 | R21: DALLAS | S21: 79 | T21: SAN JOSE | U21: 99
A22: Total | C22: 874 | E22: 824 | G22: 803 | I22: 895 | K22: 804 | M22: 808 | O22: 843 | Q22: 748 | S22: 698 | U22: 730

Sheet His
B2: 2024 | C2: WINNER | D2: PTS | F2: 2023 | G2: WINNER | H2: PTS | J2: FRANCHISE | K2: 2024 | L2: 2023 | M2: 2022 | N2: 2021 | O2: 2020 | P2: 2019 | Q2: 2018 | R2: 2017 | S2: AVG | T2: PD | U2: PTS | X2: BEST 2024 | AB2: BEST 2023 | AF2: WORST 2024 | AJ2: WORST 2023
B3: MIOUSSE | D3: 1036 | F3: DESROSIERS | H3: 1045 | J3: DESROSIERS | K3: 12 | L3: 1 | M3: 12 | N3: 1 | O3: 1 | P3: 1 | Q3: 4 | R3: 6 | S3: =AVERAGE(K3:R3) -> 4.75 | T3: =COUNTIF(K3:R3,"<=3") -> 4 | U3: 120 | X3: OFFENCE | Y3: MIOUSSE | Z3: 644 | AB3: OFFENCE | AC3: DESROSIERS | AD3: 694 | AF3: OFFENCE | AG3: DESROSIERS | AH3: 447 | AJ3: OFFENCE | AK3: HENAULT | AL3: 450 | AR3: 2024 | AS3: WINNER | AT3: PTS | AV3: 2023 | AW3: WINNER | AX3: PTS | AZ3: 2022 | BA3: WINNER | BB3: PTS
B4: MATTHEWS | D4: 107 | F4: MCDAVID | H4: 153 | J4: PICARD | K4: 8 | L4: 6 | M4: 1 | N4: 5 | O4: 2 | P4: 8 | Q4: 6 | R4: 1 | S4: =AVERAGE(K4:R4) -> 4.625 | T4: =COUNTIF(K4:R4,"<=3") -> 3 | U4: 102 | Y4: MATTHEWS | Z4: 107 | AC4: MCDAVID | AD4: 153 | AG4: SUZUKI | AH4: 77 | AK4: THOMPSON | AL4: 94 | AR4: MIOUSSE | AT4: 1036 | AV4: DESROSIERS | AX4: 1045 | AZ4: PICARD | BB4: 1011
B5: AHO | D5: 89 | F5: KUCHEROV | H5: 112 | J5: BEAUCHEMIN | K5: 5 | L5: 5 | M5: 3 | N5: 7 | O5: 10 | P5: 2 | Q5: 1 | R5: 3 | S5: =AVERAGE(K5:R5) -> 4.5 | T5: =COUNTIF(K5:R5,"<=3") -> 4 | U5: 100 | Y5: AHO | Z5: 89 | AC5: KUCHEROV | AD5: 112 | AG5: KELLER | AH5: 76 | AK5: GAUDREAU | AL5: 74 | AR5: MATTHEWS | AT5: 107 | AV5: MCDAVID | AX5: 153 | AZ5: GAUDREAU | BB5: 115
B6: TKACHUK | D6: 88 | F6: PANARIN | H6: 92 | J6: CHABOT | K6: 2 | L6: 2 | M6: 2 | N6: 10 | O6: 7 | P6: 5 | Q6: 3 | R6: 5 | S6: =AVERAGE(K6:R6) -> 4.5 | T6: =COUNTIF(K6:R6,"<=3") -> 4 | U6: 96 | Y6: TKACHUK | Z6: 88 | AC6: PANARIN | AD6: 92 | AG6: SCHMALTZ | AH6: 61 | AK6: EICHEL | AL6: 66 | AR6: AHO | AT6: 89 | AV6: KUCHEROV | AX6: 112 | AZ6: KAPRIZOV | BB6: 108
B7: GUENTZEL | D7: 77 | F7: MALKIN | H7: 83 | J7: CON/FOR | K7: 6 | L7: 8 | M7: 4 | N7: 8 | O7: 5 | P7: 3 | Q7: 2 | R7: 2 | S7: =AVERAGE(K7:R7) -> 4.75 | T7: =COUNTIF(K7:R7,"<=3") -> 3 | U7: 89 | Y7: GUENTZEL | Z7: 77 | AC7: MALKIN | AD7: 83 | AG7: MACCELLI | AH7: 57 | AK7: NICHUSHKIN | AL7: 47 | AR7: TKACHUK | AT7: 88 | AV7: PANARIN | AX7: 92 | AZ7: LINDHOLM | BB7: 82
B8: HYMAN | D8: 77 | F8: GIROUX | H8: 79 | J8: BLIER | K8: 4 | L8: 3 | M8: 5 | N8: 2 | O8: 4 | P8: 7 | Q8: 11 | R8: - | S8: =AVERAGE(K8:R8) -> 5.1428571 | T8: =COUNTIF(K8:R8,"<=3") -> 2 | U8: 73 | Y8: HYMAN | Z8: 77 | AC8: GIROUX | AD8: 79 | AG8: THOMPSON | AH8: 56 | AK8: ROSLOVIC | AL8: 44 | AR8: GUENTZEL | AT8: 77 | AV8: MALKIN | AX8: 83 | AZ8: ROBERTSON | BB8: 79
B9: KEMPE | D9: 75 | F9: MARCHAND | H9: 67 | J9: FORCIER | K9: - | L9: - | M9: - | N9: - | O9: 5 | P9: 3 | Q9: 2 | R9: 2 | S9: =AVERAGE(K9:R9) -> 3 | T9: =COUNTIF(K9:R9,"<=3") -> 3 | U9: 61 | Y9: KEMPE | Z9: 75 | AC9: MARCHAND | AD9: 67 | AG9: COZENS | AH9: 47 | AK9: MANGIAPANE | AL9: 43 | AR9: HYMAN | AT9: 77 | AV9: GIROUX | AX9: 79 | AZ9: SCHEIFELE | BB9: 70
B10: KOPITAR | D10: 70 | F10: BERGERON | H10: 58 | J10: MIOUSSE | K10: 1 | L10: 7 | M10: 7 | N10: 6 | O10: 8 | P10: 10 | Q10: 7 | R10: 8 | S10: =AVERAGE(K10:R10) -> 6.75 | T10: =COUNTIF(K10:R10,"<=3") -> 1 | U10: 60 | Y10: KOPITAR | Z10: 70 | AC10: BERGERON | AD10: 58 | AG10: COOLEY | AH10: 44 | AK10: FORSBERG | AL10: 42 | AR10: KEMPE | AT10: 75 | AV10: MARCHAND | AX10: 67 | AZ10: ZEGRAS | BB10: 61
B11: EHLERS | D11: 61 | F11: TARASENKO | H11: 50 | J11: MOROTTI | K11: 7 | L11: 10 | M11: 10 | N11: 4 | O11: 6 | P11: 9 | Q11: 8 | R11: 7 | S11: =AVERAGE(K11:R11) -> 7.625 | T11: =COUNTIF(K11:R11,"<=3") -> 0 | U11: 40 | Y11: EHLERS | Z11: 61 | AC11: TARASENKO | AD11: 50 | AG11: CARLSSON L. | AH11: 29 | AK11: JOHNSON K. | AL11: 40 | AR11: KOPITAR | AT11: 70 | AV11: BERGERON | AX11: 58 | AZ11: BJORKSTRAND | BB11: 57
B12: HUGHES Q. | D12: 92 | F12: DUNN | H12: 64 | J12: DIEGO | K12: 3 | L12: 4 | M12: 6 | N12: 11 | O12: 12 | P12: 11 | Q12: 10 | R12: 9 | S12: =AVERAGE(K12:R12) -> 8.25 | T12: =COUNTIF(K12:R12,"<=3") -> 1 | U12: 38 | X12: DEFENCE | Y12: MIOUSSE | Z12: 193 | AB12: DEFENCE | AC12: BEAUCHEMIN | AD12: 192 | AF12: DEFENCE | AG12: ROBB | AJ12: DEFENCE | AK12: MOROTTI | AL12: 100 | AR12: EHLERS | AT12: 61 | AV12: TARASENKO | AX12: 50 | AZ12: HYMAN | BB12: 54
B13: RIELLY | D13: 58 | F13: JOSI | H13: 59 | J13: LESSARD | K13: 9 | L13: 9 | M13: 8 | N13: 3 | O13: 11 | P13: 12 | Q13: 9 | R13: 4 | S13: =AVERAGE(K13:R13) -> 8.125 | T13: =COUNTIF(K13:R13,"<=3") -> 1 | U13: 36 | Y13: HUGHES Q. | Z13: 92 | AC13: KARLSSON | AD13: 101 | AG13: ANDERSSON | AH13: 39 | AK13: SPURGEON | AL13: 34 | AR13: HUGHES Q. | AT13: 92 | AV13: DUNN | AX13: 64 | AZ13: CARLSON | BB13: 71
B14: BURNS | D14: 43 | F14: BARRIE | H14: 55 | J14: HENAULT | K14: 10 | L14: 11 | M14: 11 | N14: 9 | O14: 9 | P14: 4 | Q14: 5 | R14: 10 | S14: =AVERAGE(K14:R14) -> 8.625 | T14: =COUNTIF(K14:R14,"<=3") -> 0 | U14: 28 | Y14: RIELLY | Z14: 58 | AC14: DOBSON | AD14: 49 | AG14: FORSLING | AH14: 39 | AK14: SEVERSON | AL14: 33 | AR14: RIELLY | AT14: 58 | AV14: JOSI | AX14: 59 | AZ14: EKBLAD | BB14: 57
B15: SHESTERKIN | D15: 88 | F15: KUEMPER | H15: 66 | J15: CONSTANTIN | K15: 6 | L15: 8 | M15: 4 | N15: 8 | O15: - | P15: - | Q15: - | R15: - | S15: =AVERAGE(K15:R15) -> 6.5 | T15: =COUNTIF(K15:R15,"<=3") -> 0 | U15: 28 | Y15: BURNS | Z15: 43 | AC15: SEIDER | AD15: 42 | AG15: JONES | AH15: 31 | AK15: PIONK | AL15: 33 | AR15: BURNS | AT15: 43 | AV15: BARRIE | AX15: 55 | AZ15: DEANGELO | BB15: 51
B16: CAROLINA | D16: 111 | F16: NEW YORK R | H16: 107 | J16: ROB/DAV | K16: 11 | L16: 12 | M16: 9 | N16: 12 | O16: 3 | P16: 6 | Q16: - | R16: - | S16: =AVERAGE(K16:R16) -> 8.8333333 | T16: =COUNTIF(K16:R16,"<=3") -> 1 | U16: 25 | X16: GOALIE | Y16: CONSTANTIN | AB16: GOALIE | AC16: PICARD | AF16: GOALIE | AG16: ROBB | AJ16: GOALIE | AK16: BLIER | AR16: SHESTERKIN | AT16: 88 | AV16: KUEMPER | AX16: 66 | AZ16: ANDERSEN | BB16: 93
J17: ROBB | K17: 11 | L17: 12 | M17: 9 | N17: 12 | O17: 3 | P17: - | Q17: - | R17: - | S17: =AVERAGE(K17:R17) -> 9.4 | T17: =COUNTIF(K17:R17,"<=3") -> 1 | U17: 17 | Y17: BOBROVSKY | Z17: 98 | AC17: GEORGIEV | AD17: 103 | AG17: HUSSO | AH17: 22 | AK17: QUICK | AL17: 44 | AR17: CAROLINA | AT17: 111 | AV17: NEW YORK R | AX17: 107 | AZ17: MINNESOTA | BB17: 113
B18: 2022 | C18: WINNER | D18: PTS | F18: 2021 | G18: WINNER | H18: PTS | J18: DAVID | K18: - | L18: - | M18: - | N18: - | O18: - | P18: 6 | Q18: - | R18: - | S18: =AVERAGE(K18:R18) -> 6 | T18: =COUNTIF(K18:R18,"<=3") -> 0 | U18: 8 | X18: TEAM | Y18: BLIER | AB18: TEAM | AC18: BLIER | AF18: TEAM | AG18: ROBB | AJ18: TEAM | AK18: BEAUCHEMIN
B19: PICARD | D19: 1011 | F19: DESROSIERS | H19: 646 | Y19: DALLAS | Z19: 113 | AC19: CAROLINA | AD19: 113 | AG19: SAN JOSE | AH19: 37 | AK19: ST. LOUIS | AL19: 81 | AV19: 2021 | AW19: WINNER | AX19: PTS
B20: GAUDREAU | D20: 115 | F20: MCDAVID | G20: MCDAVID | H20: 105 | J20: PLACE | K20: 1 | L20: 2 | M20: 3 | N20: 4 | O20: 5 | P20: 6 | Q20: 7 | R20: 8 | S20: 9 | T20: 10 | AV20: DESROSIERS | AX20: 646
B21: KAPRIZOV | D21: 108 | F21: MARCHAND | G21: MARCHAND | H21: 69 | J21: POINTS | K21: 25 | L21: 18 | M21: 15 | N21: 12 | O21: 10 | P21: 8 | Q21: 6 | R21: 4 | S21: 2 | T21: 1 | AV21: MCDAVID | AW21: MCDAVID | AX21: 105
B22: LINDHOLM | D22: 82 | F22: MATTHEWS | G22: MATTHEWS | H22: 66 | X22: BEST 2022 | AB22: BEST 2021 | AF22: WORST 2022 | AJ22: WORST 2021 | AV22: MARCHAND | AW22: MARCHAND | AX22: 69
B23: ROBERTSON | D23: 79 | F23: BERGERON | G23: BERGERON | H23: 48 | X23: OFFENCE | Y23: CHABOT | Z23: 632 | AB23: OFFENCE | AC23: DESROSIERS | AD23: 438 | AF23: OFFENCE | AG23: MOROTTI | AH23: 503 | AJ23: OFFENCE | AK23: HENAULT | AL23: 288 | AV23: MATTHEWS | AW23: MATTHEWS | AX23: 66
B24: SCHEIFELE | D24: 70 | F24: VORACEK | G24: VORACEK | H24: 43 | Y24: DRAISAITL | Z24: 110 | AC24: MCDAVID | AD24: 105 | AG24: CONNOR | AH24: 93 | AK24: ZIBANEJAD | AL24: 50 | AV24: BERGERON | AW24: BERGERON | AX24: 48
B25: ZEGRAS | D25: 61 | F25: SUZUKI | G25: SUZUKI | H25: 41 | Y25: TKACHUK | Z25: 104 | AC25: MARCHAND | AD25: 69 | AG25: TKACHUK | AH25: 67 | AK25: MILLER | AL25: 46 | AV25: VORACEK | AW25: VORACEK | AX25: 43
B26: BJORKSTRAND | D26: 57 | F26: HOFFMAN | G26: HOFFMAN | H26: 36 | Y26: DEBRINCAT | Z26: 78 | AC26: MATTHEWS | AD26: 66 | AG26: MARCHESSAULT | AH26: 66 | AK26: TOFFOLI | AL26: 44 | AV26: SUZUKI | AW26: SUZUKI | AX26: 41
B27: HYMAN | D27: 54 | F27: TATAR | G27: TATAR | H27: 30 | Y27: THOMAS | Z27: 77 | AC27: BERGERON | AD27: 48 | AG27: BARZAL | AH27: 59 | AK27: HALL | AL27: 33 | AV27: HOFFMAN | AW27: HOFFMAN | AX27: 36
B28: CARLSON | D28: 71 | F28: THEODORE | H28: 42 | Y28: KYROU | Z28: 75 | AC28: VORACEK | AD28: 43 | AG28: POINT | AH28: 58 | AK28: FORSBERG | AL28: 32 | AV28: TATAR | AW28: TATAR | AX28: 30
B29: EKBLAD | D29: 57 | F29: DHALIN | H29: 23 | Y29: KOPITAR | Z29: 67 | AC29: SUZUKI | AD29: 41 | AG29: RUST | AH29: 58 | AK29: KREIDER | AL29: 30 | AV29: THEODORE | AX29: 42
B30: DEANGELO | D30: 51 | F30: DUMBA | H30: 21 | Y30: SUZUKI | Z30: 61 | AC30: HOFFMAN | AD30: 36 | AG30: WILSON | AH30: 52 | AK30: KUZNETSOV | AL30: 29 | AV30: DHALIN | AX30: 23
B31: ANDERSEN | D31: 93 | F31: BOBROVSKY | H31: 40 | Y31: DUBOIS | Z31: 60 | AC31: TATAR | AD31: 30 | AG31: ATKINSON | AH31: 50 | AK31: DOMI | AL31: 24 | AV31: DUMBA | AX31: 21
B32: MINNESOTA | D32: 113 | F32: COLORADO | H32: 82 | X32: DEFENCE | Y32: DIEGO | Z32: 191 | AB32: DEFENCE | AC32: LESSARD | AD32: 126 | AF32: DEFENCE | AG32: MIOUSSE | AH32: 107 | AJ32: DEFENCE | AK32: MIOUSSE | AL32: 67 | AV32: BOBROVSKY | AX32: 40
Y33: JOSI | Z33: 96 | AC33: HEDMAN | AD33: 45 | AG33: BARRIE | AH33: 41 | AK33: DOUGHTY | AL33: 33 | AV33: COLORADO | AX33: 82
B34: 2020 | C34: WINNER | D34: PTS | F34: 2019 | G34: WINNER | H34: PTS | Y34: THEODORE | Z34: 52 | AC34: LETANG | AD34: 45 | AG34: PARAYKO | AH34: 35 | AK34: WEBER | AL34: 19
B35: DESROSIERS | D35: 886 | F35: DESROSIERS | H35: 999 | Y35: BOUCHARD | Z35: 43 | AC35: NURSE | AD35: 36 | AG35: DOUGHTY | AH35: 31 | AK35: SLAVIN | AL35: 15
B36: DRAISAITL | D36: 110 | F36: KANE | H36: 110 | X36: GOALIE | Y36: BLIER | AB36: GOALIE | AC36: BEAUCHEMIN | AF36: GOALIE | AG36: DIEGO | AJ36: GOALIE | AK36: MIOUSSE
B37: MCDAVID | D37: 97 | F37: DRAISAITL | H37: 105 | Y37: MARKSTROM | Z37: 116 | AC37: GRUBAUER | AD37: 86 | AG37: HART | AH37: 38 | AK37: SAMSONOV | AL37: 35
B38: MARCHAND | D38: 87 | F38: MARCHAND | H38: 100 | X38: TEAM | Y38: CHABOT | AB38: TEAM | AC38: DES/LES | AF38: TEAM | AG38: DESROSIERS | AJ38: TEAM | AK38: DIEGO
B39: KUCHEROV | D39: 85 | F39: OVECHKIN | H39: 89 | Y39: FLORIDA | Z39: 122 | AC39: COL/VGK | AD39: 82 | AG39: NEW YORK I | AH39: 84 | AK39: VANCOUVER | AL39: 50
B40: OVECHKIN | D40: 67 | F40: TAVARES | H40: 88
B41: HOFFMAN | D41: 59 | F41: BERGERON | H41: 79 | X41: BEST 2020 | AB41: BEST 2019 | AF41: WORST 2020 | AJ41: WORST 2019
B42: BERGERON | D42: 56 | F42: KOPITAR | H42: 60 | X42: OFFENCE | Y42: DESROSIERS | Z42: 608 | AB42: OFFENCE | AC42: DESROSIERS | AD42: 687 | AF42: OFFENCE | AG42: DIEGO | AH42: 397 | AJ42: OFFENCE | AK42: LESSARD | AL42: 399
B43: E. STAAL | D43: 47 | F43: KARLSSON | H43: 56 | Y43: DRAISAITL | Z43: 110 | AC43: KANE | AD43: 110 | AG43: MATTHEWS | AH43: 80 | AK43: GAUDREAU | AL43: 99
B44: BARRIE | D44: 39 | F44: GIORDANO | H44: 74 | Y44: MCDAVID | Z44: 97 | AC44: DRAISAITL | AD44: 105 | AG44: VRANA | AH44: 52 | AK44: O'REILLY | AL44: 77
B45: SHATTENRKIRK | D45: 34 | F45: GOSTISBEHERE | H45: 37 | Y45: MARCHAND | Z45: 87 | AC45: MARCHAND | AD45: 100 | AG45: RAINHART | AH45: 50 | AK45: KREIDER | AL45: 52
B46: DUMBA | D46: 24 | F46: GREEN | H46: 26 | Y46: KUCHEROV | Z46: 85 | AC46: OVECHKIN | AD46: 89 | AG46: MEIER | AH46: 49 | AK46: KELLER | AL46: 47
B47: HELLEBUYCK | D47: 89 | F47: RASK | H47: 75 | Y47: OVECHKIN | Z47: 67 | AC47: TAVARES | AD47: 88 | AG47: KANE E. | AH47: 47 | AK47: SVECHNIKOV | AL47: 37
B48: COLORADO | D48: 92 | F48: TORONTO | H48: 100 | Y48: HOFFMAN | Z48: 59 | AC48: BERGERON | AD48: 79 | AG48: BOESER | AH48: 45 | AK48: NAMESTNIKOV | AL48: 31
Y49: BERGERON | Z49: 56 | AC49: KOPITAR | AD49: 60 | AG49: VAN RIEMSDYK | AH49: 40 | AK49: OKPOSO | AL49: 29
B50: 2018 | C50: WINNER | D50: PTS | F50: 2017 | G50: WINNER | H50: PTS | Y50: E. STAAL | Z50: 47 | AC50: KARLSSON | AD50: 56 | AG50: RADULOV | AH50: 34 | AK50: SPEZZA | AL50: 27
B51: BEAUCHEMIN | D51: 996 | F51: PICARD | H51: 895 | X51: DEFENCE | Y51: PICARD | Z51: 168 | AB51: DEFENCE | AC51: HENAULT | AD51: 172 | AF51: DEFENCE | AG51: HENAULT | AH51: 91 | AJ51: DEFENCE | AK51: MIOUSSE | AL51: 108
B52: KUCHEROV | D52: 102 | F52: TARASENKO | H52: 75 | Y52: CARLSON | Z52: 75 | AC52: CARLSON | AD52: 70 | AG52: LETANG | AH52: 44 | AK52: SUTER | AL52: 47
B53: GIROUX | D53: 100 | F53: GETZLAF | H53: 73 | Y53: PIETRANGELO | Z53: 52 | AC53: LETANG | AD53: 56 | AG53: SCHMIDT | AH53: 31 | AK53: MYERS | AL53: 31
B54: KESSEL | D54: 92 | F54: SEGUIN | H54: 72 | Y54: EKBLAD | Z54: 41 | AC54: MCDONAGH | AD54: 46 | AG54: FAULK | AH54: 16 | AK54: BUTCHER | AL54: 30
B55: PANARIN | D55: 82 | F55: ZETTERBERG | H55: 68 | X55: GOALIE | Y55: ROBB | AB55: GOALIE | AC55: BEAUCHEMIN | AF55: GOALIE | AG55: MOROTTI | AJ55: GOALIE | AK55: DIEGO
B56: BARKOV | D56: 78 | F56: SKINNER | H56: 63 | Y56: VASILEVSKI | Z56: 90 | AC56: VASILEVSKI | AD56: 106 | AG56: JONES | AH56: 44 | AK56: QUICK | AL56: 49
B57: TROCHECK | D57: 75 | F57: ATKINSON | H57: 62 | X57: TEAM | Y57: MOROTTI | AB57: TEAM | AC57: PICARD | AF57: TEAM | AG57: LESSARD | AJ57: TEAM | AK57: MIOUSSE
B58: TARASENKO | D58: 66 | F58: KOIVU | H58: 58 | Y58: BOSTON | Z58: 100 | AC58: TAMPA BAY | AD58: 128 | AG58: SAN JOSE | AH58: 63 | AK58: LOS ANGELES | AL58: 71
B59: LANDESKOG | D59: 62 | F59: TOEWS | H59: 58
B60: LETANG | D60: 51 | F60: HEDMAN | H60: 72 | X60: BEST 2018 | AB60: BEST 2017 | AF60: WORST 2018 | AJ60: WORST 2017
B61: RISTOLAINEN | D61: 41 | F61: SUTER | H61: 40 | X61: OFFENCE | Y61: BEAUCHEMIN | Z61: 657 | AB61: OFFENCE | AC61: PICARD | AD61: 529 | AF61: OFFENCE | AG61: DIEGO | AH61: 460 | AJ61: OFFENCE | AK61: HENAULT | AL61: 419
B62: ELLIS | D62: 32 | F62: FAULK | H62: 37 | Y62: GIROUX | Z62: 102 | AC62: TARASENKO | AD62: 75 | AG62: STAMKOS | AH62: 86 | AK62: GAUDREAU | AL62: 61
B63: RINNE | D63: 114 | F63: RASK | H63: 107 | Y63: KUCHEROV | Z63: 100 | AC63: GETZLAF | AD63: 73 | AG63: DADONOV | AH63: 65 | AK63: HOFFMAN | AL63: 61
B64: ANAHEIM | D64: 101 | F64: CHICAGO | H64: 109 | Y64: KESSEL | Z64: 92 | AC64: SEGUIN | AD64: 72 | AG64: MATTHEWS | AH64: 63 | AK64: KUZNETSOV | AL64: 59
Y65: PANARIN | Z65: 82 | AC65: ZETTERBERG | AD65: 68 | AG65: KADRI | AH65: 55 | AK65: HALL | AL65: 53
Y66: BARKOV | Z66: 78 | AC66: SKINNER | AD66: 63 | AG66: VAN RIEMSDYK | AH66: 54 | AK66: COUTURE | AL66: 52
Y67: TROCHEK | Z67: 75 | AC67: ATKINSON | AD67: 62 | AG67: KANE E. | AH67: 54 | AK67: NYQUIST | AL67: 48
Y68: TARASENKO | Z68: 66 | AC68: TOEWS | AD68: 58 | AG68: NUGENT HOPKINS | AH68: 48 | AK68: REINHART | AL68: 47
Y69: LANDESKOG | Z69: 62 | AC69: KOIVU | AD69: 58 | AG69: SAAD | AH69: 35 | AK69: DOMI | AL69: 38
X70: DEFENCE | Y70: FORCIER | Z70: 171 | AB70: DEFENCE | AC70: LESSARD | AD70: 161 | AF70: DEFENCE | AG70: HENAULT | AH70: 100 | AJ70: DEFENCE | AK70: DIEGO | AL70: 108
Y71: KLINGBERG | Z71: 67 | AC71: BURNS | AD71: 76 | AG71: EKMAN LARSON | AH71: 42 | AK71: YANDLE | AL71: 41
Y72: JOSI | Z72: 53 | AC72: KLINGBERG | AD72: 49 | AG72: WERENSKI | AH72: 37 | AK72: GOSTISBEHERE | AL72: 39
Y73: SUTER | Z73: 51 | AC73: BRODIE | AD73: 36 | AG73: KLEFBOM | AH73: 21 | AK73: VLASIC | AL73: 28
X74: GOALIE | Y74: CHABOT | AB74: GOALIE | AC74: BEAUCHEMIN | AF74: GOALIE | AG74: MOROTTI | AJ74: GOALIE | AK74: MIOUSSE
Y75: VASILEVSKI | Z75: 119 | AC75: HOLTBY | AD75: 117 | AG75: MURRAY | AH75: 62 | AK75: FLEURY | AL75: 46
X76: TEAM | Y76: FORCIER | AB76: TEAM | AC76: MOROTTI | AF76: TEAM | AG76: DIEGO | AJ76: TEAM | AK76: HENAULT
Y77: NASHVILLE | Z77: 117 | AC77: WASHINGTON | AD77: 118 | AG77: CHIACGO | AH77: 76 | AK77: DALLAS | AL77: 79

Sheet DAT
C2: POS | D2: PLAYER | E2: SEASONS | F2: RINGS | G2: ALLSTAR | H2: Sum | I2: AVG | J2: 24 | K2: 23 | L2: 22 | M2: 21 | N2: 20 | O2: 19 | P2: 18 | Q2: 17 | S2: POOLER | U2: TEAM | V2: AVG | W2: 2024 | X2: 2023 | Y2: 2022 | Z2: 2021 | AA2: 2020 | AB2: 2019 | AC2: 2018 | AD2: 2017 | AF2: 2023 ALL STAR TEAM | AP2: SEASON | AQ2: POOLER | AR2: POS | AS2: PLAYER | AT2: PTS | AU2: COUNT | AX2: COUNT | AY2: (Tous)
B3: 1 | C3: F | D3: MCDAVID | E3: =COUNT(Tableau2[[#This Row],[24]:[17]]) -> 8 | F3: 3 | G3: 8 | H3: =SUM(Tableau2[[#This Row],[24]:[17]]) -> 934 | I3: =IFERROR(AVERAGE(Tableau2[[#This Row],[24]:[17]]),0) -> 116.75 | J3: 132 | K3: 153 | L3: 123 | M3: 105 | N3: 97 | O3: 116 | P3: 108 | Q3: 100 | S3: DESROSIERS | U3: VGK | V3: =AVERAGE(Tableau1[[#This Row],[2024]:[2017]]) -> 10 | W3: 11 | X3: 10 | Y3: 11 | Z3: 12 | AA3: 12 | AB3: 9 | AC3: 5 | AD3: - | AF3: KUCHEROV | AG3: 144 | AH3: BLIER | AP3: 20-21 | AQ3: CONSTANTIN | AR3: D | AS3: GUSTAFSSON | AT3: 12 | AU3: YES
B4: =B3+1 -> 2 | C4: T | D4: TAMPA BAY | E4: =COUNT(Tableau2[[#This Row],[24]:[17]]) -> 8 | G4: 1 | H4: =SUM(Tableau2[[#This Row],[24]:[17]]) -> 808 | I4: =IFERROR(AVERAGE(Tableau2[[#This Row],[24]:[17]]),0) -> 101 | J4: 98 | K4: 98 | L4: 110 | M4: 75 | N4: 92 | O4: 128 | P4: 113 | Q4: 94 | S4: CONSTANTIN | U4: TBL | V4: =AVERAGE(Tableau1[[#This Row],[2024]:[2017]]) -> 9.5 | W4: 9 | X4: 8 | Y4: 9 | Z4: 10 | AA4: 12 | AB4: 10 | AC4: 10 | AD4: 8 | AF4: MACKINNON | AG4: 140 | AH4: ROBB | AP4: 20-21 | AQ4: MIOUSSE | AR4: D | AS4: SLAVIN | AT4: 15 | AU4: YES | AX4: PLAYER | AY4: SEASON | AZ4: # Seasons | BA4: Somme de PTS | BB4: Moyenne de PTS
B5: =B4+1 -> 3 | C5: F | D5: DRAISAITL | E5: =COUNT(Tableau2[[#This Row],[24]:[17]]) -> 8 | F5: 2 | G5: 7 | H5: =SUM(Tableau2[[#This Row],[24]:[17]]) -> 790 | I5: =IFERROR(AVERAGE(Tableau2[[#This Row],[24]:[17]]),0) -> 98.75 | J5: 106 | K5: 128 | L5: 110 | M5: 84 | N5: 110 | O5: 105 | P5: 70 | Q5: 77 | S5: MOROTTI | U5: COL | V5: =AVERAGE(Tableau1[[#This Row],[2024]:[2017]]) -> 9 | W5: 11 | X5: 10 | Y5: 11 | Z5: 11 | AA5: 10 | AB5: 7 | AC5: 6 | AD5: 6 | AF5: MCDAVID | AG5: 132 | AH5: DIEGO | AP5: 19-20 | AQ5: HENAULT | AR5: D | AS5: FAULK | AT5: 16 | AU5: YES | AX5: LAINE | AZ5: 8 | BA5: 388 | BB5: 48.5
B6: =B5+1 -> 4 | C6: F | D6: MACKINNON | E6: =COUNT(Tableau2[[#This Row],[24]:[17]]) -> 8 | G6: 6 | H6: =SUM(Tableau2[[#This Row],[24]:[17]]) -> 746 | I6: =IFERROR(AVERAGE(Tableau2[[#This Row],[24]:[17]]),0) -> 93.25 | J6: 140 | K6: 111 | L6: 88 | M6: 65 | N6: 93 | O6: 99 | P6: 97 | Q6: 53 | S6: MIOUSSE | U6: STL | V6: =AVERAGE(Tableau1[[#This Row],[2024]:[2017]]) -> 9 | W6: 5 | X6: 9 | Y6: 11 | Z6: 11 | AA6: 10 | AB6: 11 | AC6: 7 | AD6: 8 | AF6: PANARIN | AG6: 120 | AH6: CHABOT | AP6: 20-21 | AQ6: CONSTANTIN | AR6: D | AS6: PULOCK | AT6: 17 | AU6: YES | AX6: MARNER | AZ6: 4 | BA6: 297 | BB6: 74.25
B7: =B6+1 -> 5 | C7: F | D7: KUCHEROV | E7: =COUNT(Tableau2[[#This Row],[24]:[17]]) -> 8 | F7: 3 | G7: 6 | H7: =SUM(Tableau2[[#This Row],[24]:[17]]) -> 723 | I7: =IFERROR(AVERAGE(Tableau2[[#This Row],[24]:[17]]),0) -> 90.375 | J7: 144 | K7: 112 | L7: 69 | M7: 0 | N7: 85 | O7: 128 | P7: 100 | Q7: 85 | S7: LESSARD | U7: TOR | V7: =AVERAGE(Tableau1[[#This Row],[2024]:[2017]]) -> 8.875 | W7: 10 | X7: 11 | Y7: 10 | Z7: 8 | AA7: 9 | AB7: 11 | AC7: 8 | AD7: 4 | AF7: PASTRNAK | AG7: 110 | AH7: BEAUCHEMIN | AP7: 20-21 | AQ7: MIOUSSE | AR7: D | AS7: WEBER | AT7: 19 | AU7: YES | AX7: TKACHUK M. | AZ7: 3 | BA7: 256 | BB7: 85.333333
B8: =B7+1 -> 6 | C8: F | D8: PANARIN | E8: =COUNT(Tableau2[[#This Row],[24]:[17]]) -> 8 | F8: 2 | G8: 2 | H8: =SUM(Tableau2[[#This Row],[24]:[17]]) -> 704 | I8: =IFERROR(AVERAGE(Tableau2[[#This Row],[24]:[17]]),0) -> 88 | J8: 120 | K8: 92 | L8: 96 | M8: 58 | N8: 95 | O8: 87 | P8: 82 | Q8: 74 | S8: BLIER | U8: WPG | V8: =AVERAGE(Tableau1[[#This Row],[2024]:[2017]]) -> 8.875 | W8: 8 | X8: 9 | Y8: 10 | Z8: 10 | AA8: 8 | AB8: 11 | AC8: 7 | AD8: 8 | AF8: MATTHEWS | AG8: 107 | AH8: MIOUSSE | AP8: 20-21 | AQ8: ROBB | AR8: D | AS8: GOSTISBEHERE | AT8: 20 | AU8: YES | AX8: DUBOIS | AZ8: 5 | BA8: 254 | BB8: 50.8
B9: =B8+1 -> 7 | C9: F | D9: PASTRNAK | E9: =COUNT(Tableau2[[#This Row],[24]:[17]]) -> 8 | G9: 3 | H9: =SUM(Tableau2[[#This Row],[24]:[17]]) -> 674 | I9: =IFERROR(AVERAGE(Tableau2[[#This Row],[24]:[17]]),0) -> 84.25 | J9: 110 | K9: 113 | L9: 77 | M9: 48 | N9: 95 | O9: 81 | P9: 80 | Q9: 70 | S9: PICARD | U9: BOS | V9: =AVERAGE(Tableau1[[#This Row],[2024]:[2017]]) -> 8.625 | W9: 9 | X9: 8 | Y9: 7 | Z9: 10 | AA9: 11 | AB9: 10 | AC9: 7 | AD9: 7 | AF9: DRAISAITL | AG9: 106 | AH9: MOROTTI | AP9: 16-17 | AQ9: HENAULT | AR9: D | AS9: LINDHOLM H. | AT9: 20 | AU9: YES | AX9: DEBRINCAT | AZ9: 4 | BA9: 245 | BB9: 61.25
B10: =B9+1 -> 8 | C10: F | D10: CROSBY | E10: =COUNT(Tableau2[[#This Row],[24]:[17]]) -> 8 | G10: 2 | H10: =SUM(Tableau2[[#This Row],[24]:[17]]) -> 658 | I10: =IFERROR(AVERAGE(Tableau2[[#This Row],[24]:[17]]),0) -> 82.25 | J10: 94 | K10: 93 | L10: 84 | M10: 62 | N10: 47 | O10: 100 | P10: 89 | Q10: 89 | S10: CHABOT | U10: CAR | V10: =AVERAGE(Tableau1[[#This Row],[2024]:[2017]]) -> 8.625 | W10: 11 | X10: 11 | Y10: 9 | Z10: 8 | AA10: 10 | AB10: 8 | AC10: 8 | AD10: 4 | AF10: RANTANEN | AG10: 104 | AH10: LESSARD | AP10: 20-21 | AQ10: DESROSIERS | AR10: D | AS10: DUMBA | AT10: 21 | AU10: YES | AX10: THOMAS | AZ10: 4 | BA10: 240 | BB10: 60
B11: =B10+1 -> 9 | C11: G | D11: VASILEVSKY | E11: =COUNT(Tableau2[[#This Row],[24]:[17]]) -> 7 | G11: 4 | H11: =SUM(Tableau2[[#This Row],[24]:[17]]) -> 652 | I11: =IFERROR(AVERAGE(Tableau2[[#This Row],[24]:[17]]),0) -> 93.142857 | J11: 72 | K11: 88 | L11: 91 | M11: 86 | N11: 90 | O11: 106 | P11: 119 | S11: ROBB | U11: FLO | V11: =AVERAGE(Tableau1[[#This Row],[2024]:[2017]]) -> 8.625 | W11: 12 | X11: 10 | Y11: 10 | Z11: 5 | AA11: 7 | AB11: 9 | AC11: 6 | AD11: 10 | AF11: HUGHES Q. | AG11: 92 | AH11: MIOUSSE | AP11: 17-18 | AQ11: HENAULT | AR11: D | AS11: KLEFBOM | AT11: 21 | AU11: YES | AX11: DAHLIN | AZ11: 4 | BA11: 216 | BB11: 54
B12: =B11+1 -> 10 | C12: F | D12: MATTHEWS | E12: =COUNT(Tableau2[[#This Row],[24]:[17]]) -> 8 | F12: 2 | G12: 3 | H12: =SUM(Tableau2[[#This Row],[24]:[17]]) -> 649 | I12: =IFERROR(AVERAGE(Tableau2[[#This Row],[24]:[17]]),0) -> 81.125 | J12: 107 | K12: 85 | L12: 106 | M12: 66 | N12: 80 | O12: 73 | P12: 63 | Q12: 69 | S12: BEAUCHEMIN | U12: MIN | V12: =AVERAGE(Tableau1[[#This Row],[2024]:[2017]]) -> 8.25 | W12: 6 | X12: 11 | Y12: 11 | Z12: 5 | AA12: 7 | AB12: 10 | AC12: 10 | AD12: 6 | AF12: MAKAR | AG12: 90 | AH12: BLIER | AP12: 20-21 | AQ12: ROBB | AR12: D | AS12: MORRISSEY | AT12: 21 | AU12: YES | AX12: KYROU | AZ12: 3 | BA12: 215 | BB12: 71.666667
B13: =B12+1 -> 11 | C13: G | D13: BOBROVSKY | E13: =COUNT(Tableau2[[#This Row],[24]:[17]]) -> 8 | F13: 1 | G13: 1 | H13: =SUM(Tableau2[[#This Row],[24]:[17]]) -> 648 | I13: =IFERROR(AVERAGE(Tableau2[[#This Row],[24]:[17]]),0) -> 81 | J13: 98 | K13: 54 | L13: 90 | M13: 40 | N13: 55 | O13: 102 | P13: 101 | Q13: 108 | S13: HENAULT | U13: EDM | V13: =AVERAGE(Tableau1[[#This Row],[2024]:[2017]]) -> 8.25 | W13: 10 | X13: 10 | Y13: 9 | Z13: 9 | AA13: 6 | AB13: 7 | AC13: 6 | AD13: 9 | AF13: JOSI | AG13: 85 | AH13: PICARD | AP13: 20-21 | AQ13: BEAUCHEMIN | AR13: F | AS13: YAMAMOTO | AT13: 21 | AU13: YES | AX13: BISHOP | AZ13: 3 | BA13: 199 | BB13: 66.333333
B14: =B13+1 -> 12 | C14: F | D14: MARCHAND | E14: =COUNT(Tableau2[[#This Row],[24]:[17]]) -> 8 | F14: 4 | G14: 4 | H14: =SUM(Tableau2[[#This Row],[24]:[17]]) -> 640 | I14: =IFERROR(AVERAGE(Tableau2[[#This Row],[24]:[17]]),0) -> 80 | J14: 67 | K14: 67 | L14: 80 | M14: 69 | N14: 87 | O14: 100 | P14: 85 | Q14: 85 | S14: DIEGO | U14: NYR | V14: =AVERAGE(Tableau1[[#This Row],[2024]:[2017]]) -> 8.25 | W14: 10 | X14: 12 | Y14: 8 | Z14: 12 | AA14: 6 | AB14: 5 | AC14: 6 | AD14: 7 | AF14: BOBROSVKY | AG14: 98 | AH14: CONSTANTIN | AP14: 20-21 | AQ14: ROBB | AR14: F | AS14: MITTELSTADT | AT14: 22 | AU14: YES | AX14: ST LOUIS | AZ14: 2 | BA14: 198 | BB14: 99
B15: =B14+1 -> 13 | C15: F | D15: KANE P. | E15: =COUNT(Tableau2[[#This Row],[24]:[17]]) -> 8 | F15: 1 | G15: 4 | H15: =SUM(Tableau2[[#This Row],[24]:[17]]) -> 621 | I15: =IFERROR(AVERAGE(Tableau2[[#This Row],[24]:[17]]),0) -> 77.625 | J15: 47 | K15: 57 | L15: 92 | M15: 66 | N15: 84 | O15: 110 | P15: 76 | Q15: 89 | S15: DAVID | U15: DAL | V15: =AVERAGE(Tableau1[[#This Row],[2024]:[2017]]) -> 8.125 | W15: 10 | X15: 6 | Y15: 7 | Z15: 11 | AA15: 9 | AB15: 9 | AC15: 6 | AD15: 7 | AF15: DALLAS | AG15: 113 | AH15: BLIER | AP15: 20-21 | AQ15: DESROSIERS | AR15: D | AS15: DAHLIN | AT15: 23 | AU15: YES | AX15: BINNINGTON | AZ15: 3 | BA15: 192 | BB15: 64
B16: =B15+1 -> 14 | C16: F | D16: RANTANEN | E16: =COUNT(Tableau2[[#This Row],[24]:[17]]) -> 8 | G16: 3 | H16: =SUM(Tableau2[[#This Row],[24]:[17]]) -> 618 | I16: =IFERROR(AVERAGE(Tableau2[[#This Row],[24]:[17]]),0) -> 77.25 | J16: 104 | K16: 105 | L16: 92 | M16: 66 | N16: 41 | O16: 87 | P16: 84 | Q16: 39 | S16: FORCIER | U16: NAS | V16: =AVERAGE(Tableau1[[#This Row],[2024]:[2017]]) -> 8.125 | W16: 5 | X16: 6 | Y16: 8 | Z16: 7 | AA16: 13 | AB16: 11 | AC16: 9 | AD16: 6 | AP16: 20-21 | AQ16: BEAUCHEMIN | AR16: F | AS16: LARKIN | AT16: 23 | AU16: YES | AX16: OETTINGER | AZ16: 2 | BA16: 185 | BB16: 92.5
B17: =B16+1 -> 15 | C17: F | D17: GAUDREAU | E17: =COUNT(Tableau2[[#This Row],[24]:[17]]) -> 8 | F17: 1 | G17: 2 | H17: =SUM(Tableau2[[#This Row],[24]:[17]]) -> 599 | I17: =IFERROR(AVERAGE(Tableau2[[#This Row],[24]:[17]]),0) -> 74.875 | J17: 60 | K17: 74 | L17: 115 | M17: 48 | N17: 58 | O17: 99 | P17: 84 | Q17: 61 | U17: PIT | V17: =AVERAGE(Tableau1[[#This Row],[2024]:[2017]]) -> 8.125 | W17: 8 | X17: 10 | Y17: 7 | Z17: 8 | AA17: 6 | AB17: 8 | AC17: 11 | AD17: 7 | AP17: 20-21 | AQ17: PICARD | AR17: D | AS17: PIETRANGELO | AT17: 23 | AU17: YES | AX17: JOHANSEN | AZ17: 3 | BA17: 179 | BB17: 59.666667
B18: =B17+1 -> 16 | C18: T | D18: WASHINGTON | E18: =COUNT(Tableau2[[#This Row],[24]:[17]]) -> 6 | G18: 1 | H18: =SUM(Tableau2[[#This Row],[24]:[17]]) -> 594 | I18: =IFERROR(AVERAGE(Tableau2[[#This Row],[24]:[17]]),0) -> 99 | L18: 100 | M18: 77 | N18: 90 | O18: 104 | P18: 105 | Q18: 118 | U18: WAS | V18: =AVERAGE(Tableau1[[#This Row],[2024]:[2017]]) -> 7.875 | W18: 5 | X18: 6 | Y18: 10 | Z18: 9 | AA18: 8 | AB18: 8 | AC18: 8 | AD18: 9 | AF18: 2023 ALL STAR TEAM | AP18: 20-21 | AQ18: HENAULT | AR18: F | AS18: DOMI | AT18: 24 | AU18: YES | AX18: KOPITAR | AZ18: 3 | BA18: 179 | BB18: 59.666667
B19: =B18+1 -> 17 | C19: F | D19: BARKOV | E19: =COUNT(Tableau2[[#This Row],[24]:[17]]) -> 8 | F19: 1 | H19: =SUM(Tableau2[[#This Row],[24]:[17]]) -> 592 | I19: =IFERROR(AVERAGE(Tableau2[[#This Row],[24]:[17]]),0) -> 74 | J19: 80 | K19: 78 | L19: 88 | M19: 58 | N19: 62 | O19: 96 | P19: 78 | Q19: 52 | U19: CGY | V19: =AVERAGE(Tableau1[[#This Row],[2024]:[2017]]) -> 7.625 | W19: 5 | X19: 10 | Y19: 8 | Z19: 8 | AA19: 9 | AB19: 7 | AC19: 8 | AD19: 6 | AF19: MCDAVID | AG19: 153 | AH19: DESROSIERS | AP19: 19-20 | AQ19: DESROSIERS | AR19: D | AS19: DUMBA | AT19: 24 | AU19: YES | AX19: MCAVOY | AZ19: 5 | BA19: 178 | BB19: 35.6
B20: =B19+1 -> 18 | C20: T | D20: TORONTO | E20: =COUNT(Tableau2[[#This Row],[24]:[17]]) -> 6 | F20: 1 | H20: =SUM(Tableau2[[#This Row],[24]:[17]]) -> 586 | I20: =IFERROR(AVERAGE(Tableau2[[#This Row],[24]:[17]]),0) -> 97.666667 | J20: 102 | K20: 111 | L20: 115 | M20: 77 | N20: 81 | O20: 100 | U20: CBJ | V20: =AVERAGE(Tableau1[[#This Row],[2024]:[2017]]) -> 7.25 | W20: 6 | X20: 7 | Y20: 6 | Z20: 7 | AA20: 7 | AB20: 9 | AC20: 9 | AD20: 7 | AF20: DRAISAITL | AG20: 128 | AH20: CONSTANTIN | AP20: 20-21 | AQ20: CHABOT | AR20: D | AS20: EKMAN-LARSSON | AT20: 24 | AU20: YES | AX20: EICHEL | AZ20: 3 | BA20: 178 | BB20: 59.333333
B21: =B20+1 -> 19 | C21: F | D21: OVECHKIN | E21: =COUNT(Tableau2[[#This Row],[24]:[17]]) -> 8 | F21: 2 | H21: =SUM(Tableau2[[#This Row],[24]:[17]]) -> 584 | I21: =IFERROR(AVERAGE(Tableau2[[#This Row],[24]:[17]]),0) -> 73 | J21: 65 | K21: 75 | L21: 90 | M21: 42 | N21: 67 | O21: 89 | P21: 87 | Q21: 69 | U21: SJS | V21: =AVERAGE(Tableau1[[#This Row],[2024]:[2017]]) -> 7.25 | W21: 5 | X21: 2 | Y21: 6 | Z21: 7 | AA21: 11 | AB21: 9 | AC21: 8 | AD21: 10 | AF21: PASTRNAK | AG21: 113 | AH21: MIOUSSE | AP21: 20-21 | AQ21: CHABOT | AR21: F | AS21: LAINE | AT21: 24 | AU21: YES | AX21: FORSBERG | AZ21: 3 | BA21: 172 | BB21: 57.333333
B22: =B21+1 -> 20 | C22: F | D22: MARNER | E22: =COUNT(Tableau2[[#This Row],[24]:[17]]) -> 7 | G22: 1 | H22: =SUM(Tableau2[[#This Row],[24]:[17]]) -> 578 | I22: =IFERROR(AVERAGE(Tableau2[[#This Row],[24]:[17]]),0) -> 82.571429 | J22: 85 | K22: 99 | L22: 97 | M22: 67 | N22: 67 | O22: 94 | P22: 69 | U22: PHI | V22: =AVERAGE(Tableau1[[#This Row],[2024]:[2017]]) -> 7.125 | W22: 3 | X22: 5 | Y22: 10 | Z22: 9 | AA22: 9 | AB22: 9 | AC22: 6 | AD22: 6 | AF22: KUCHEROV | AG22: 112 | AH22: DESROSIERS | AP22: 20-21 | AQ22: BLIER | AR22: D | AS22: GIORDANO | AT22: 26 | AU22: YES | AX22: STAMKOS | AZ22: 2 | BA22: 165 | BB22: 82.5
B23: =B22+1 -> 21 | C23: F | D23: STAMKOS | E23: =COUNT(Tableau2[[#This Row],[24]:[17]]) -> 8 | G23: 1 | H23: =SUM(Tableau2[[#This Row],[24]:[17]]) -> 575 | I23: =IFERROR(AVERAGE(Tableau2[[#This Row],[24]:[17]]),0) -> 71.875 | J23: 81 | K23: 84 | L23: 106 | M23: 34 | N23: 66 | O23: 98 | P23: 86 | Q23: 20 | U23: MTL | V23: =AVERAGE(Tableau1[[#This Row],[2024]:[2017]]) -> 6.625 | W23: 5 | X23: 4 | Y23: 7 | Z23: 11 | AA23: 8 | AB23: 4 | AC23: 6 | AD23: 8 | AF23: MACKINNON | AG23: 111 | AH23: MOROTTI | AP23: 18-19 | AQ23: DESROSIERS | AR23: D | AS23: GREEN | AT23: 26 | AU23: YES | AX23: DOUGHTY | AZ23: 3 | BA23: 162 | BB23: 54
B24: =B23+1 -> 22 | C24: F | D24: SCHEIFELE | E24: =COUNT(Tableau2[[#This Row],[24]:[17]]) -> 8 | F24: 1 | G24: 1 | H24: =SUM(Tableau2[[#This Row],[24]:[17]]) -> 572 | I24: =IFERROR(AVERAGE(Tableau2[[#This Row],[24]:[17]]),0) -> 71.5 | J24: 72 | K24: 68 | L24: 70 | M24: 63 | N24: 73 | O24: 84 | P24: 60 | Q24: 82 | U24: NJD | V24: =AVERAGE(Tableau1[[#This Row],[2024]:[2017]]) -> 6.375 | W24: 8 | X24: 8 | Y24: 7 | Z24: 4 | AA24: 8 | AB24: 6 | AC24: 6 | AD24: 4 | AF24: TKACHUK | AG24: 109 | AH24: CHABOT | AP24: 20-21 | AQ24: HENAULT | AR24: D | AS24: HEISKANEN | AT24: 27 | AU24: YES | AX24: POINT | AZ24: 2 | BA24: 158 | BB24: 79
B25: =B24+1 -> 23 | C25: F | D25: TAVARES | E25: =COUNT(Tableau2[[#This Row],[24]:[17]]) -> 8 | F25: 1 | H25: =SUM(Tableau2[[#This Row],[24]:[17]]) -> 569 | I25: =IFERROR(AVERAGE(Tableau2[[#This Row],[24]:[17]]),0) -> 71.125 | J25: 65 | K25: 80 | L25: 76 | M25: 50 | N25: 60 | O25: 88 | P25: 84 | Q25: 66 | U25: BUF | V25: =AVERAGE(Tableau1[[#This Row],[2024]:[2017]]) -> 6.125 | W25: 8 | X25: 6 | Y25: 2 | Z25: 7 | AA25: 8 | AB25: 8 | AC25: 5 | AD25: 5 | AF25: ROBERTSON | AG25: 109 | AH25: PICARD | AP25: 21-22 | AQ25: DESROSIERS | AR25: D | AS25: PETRY | AT25: 27 | AU25: YES | AX25: TUCH | AZ25: 2 | BA25: 138 | BB25: 69
B26: =B25+1 -> 24 | C26: F | D26: GIROUX | E26: =COUNT(Tableau2[[#This Row],[24]:[17]]) -> 8 | F26: 2 | G26: 1 | H26: =SUM(Tableau2[[#This Row],[24]:[17]]) -> 549 | I26: =IFERROR(AVERAGE(Tableau2[[#This Row],[24]:[17]]),0) -> 68.625 | J26: 64 | K26: 79 | L26: 65 | M26: 43 | N26: 53 | O26: 85 | P26: 102 | Q26: 58 | U26: NYI | V26: =AVERAGE(Tableau1[[#This Row],[2024]:[2017]]) -> 6.125 | W26: 5 | X26: 5 | Y26: 8 | Z26: 8 | AA26: 7 | AB26: 6 | AC26: 5 | AD26: 5 | AF26: RANTANEN | AG26: 105 | AH26: DIEGO | AP26: 18-19 | AQ26: LESSARD | AR26: F | AS26: SPEZZA | AT26: 27 | AU26: YES | AX26: BOLDY | AZ26: 2 | BA26: 132 | BB26: 66
B27: =B26+1 -> 25 | C27: F | D27: HUBERDEAU | E27: =COUNT(Tableau2[[#This Row],[24]:[17]]) -> 8 | G27: 1 | H27: =SUM(Tableau2[[#This Row],[24]:[17]]) -> 548 | I27: =IFERROR(AVERAGE(Tableau2[[#This Row],[24]:[17]]),0) -> 68.5 | J27: 52 | K27: 55 | L27: 115 | M27: 61 | N27: 78 | O27: 92 | P27: 69 | Q27: 26 | U27: LAK | V27: =AVERAGE(Tableau1[[#This Row],[2024]:[2017]]) -> 6 | W27: 9 | X27: 7 | Y27: 4 | Z27: 3 | AA27: 2 | AB27: 8 | AC27: 7 | AD27: 8 | AF27: KARLSSON | AG27: 101 | AH27: BEAUCHEMIN | AP27: 20-21 | AQ27: HENAULT | AR27: D | AS27: YANDLE | AT27: 27 | AU27: YES | AX27: SUZUKI | AZ27: 2 | BA27: 127 | BB27: 63.5
B28: =B27+1 -> 26 | C28: F | D28: MALKIN | E28: =COUNT(Tableau2[[#This Row],[24]:[17]]) -> 8 | F28: 1 | G28: 1 | H28: =SUM(Tableau2[[#This Row],[24]:[17]]) -> 536 | I28: =IFERROR(AVERAGE(Tableau2[[#This Row],[24]:[17]]),0) -> 67 | J28: 67 | K28: 83 | L28: 42 | M28: 28 | N28: 74 | O28: 72 | P28: 98 | Q28: 72 | U28: OTT | V28: =AVERAGE(Tableau1[[#This Row],[2024]:[2017]]) -> 5.75 | W28: 9 | X28: 10 | Y28: 4 | Z28: 4 | AA28: 4 | AB28: 2 | AC28: 7 | AD28: 6 | AF28: HUGHES | AG28: 76 | AH28: ROBB | AP28: 20-21 | AQ28: MOROTTI | AR28: D | AS28: JONES S. | AT28: 28 | AU28: YES | AX28: EHLERS | AZ28: 2 | BA28: 124 | BB28: 62
B29: =B28+1 -> 27 | C29: F | D29: TKACHUK M. | E29: =COUNT(Tableau2[[#This Row],[24]:[17]]) -> 7 | F29: 1 | G29: 2 | H29: =SUM(Tableau2[[#This Row],[24]:[17]]) -> 531 | I29: =IFERROR(AVERAGE(Tableau2[[#This Row],[24]:[17]]),0) -> 75.857143 | J29: 88 | K29: 109 | L29: 104 | M29: 43 | N29: 61 | O29: 77 | P29: 49 | U29: CHI | V29: =AVERAGE(Tableau1[[#This Row],[2024]:[2017]]) -> 5.75 | W29: 5 | X29: 1 | Y29: 6 | Z29: 6 | AA29: 5 | AB29: 7 | AC29: 9 | AD29: 7 | AF29: MORRISSEY | AG29: 76 | AH29: LESSARD | AP29: 20-21 | AQ29: CHABOT | AR29: F | AS29: MALKIN | AT29: 28 | AU29: YES | AX29: NECAS | AZ29: 2 | BA29: 124 | BB29: 62
B30: =B29+1 -> 28 | C30: F | D30: ZIBANEJAD | E30: =COUNT(Tableau2[[#This Row],[24]:[17]]) -> 8 | H30: =SUM(Tableau2[[#This Row],[24]:[17]]) -> 527 | I30: =IFERROR(AVERAGE(Tableau2[[#This Row],[24]:[17]]),0) -> 65.875 | J30: 72 | K30: 91 | L30: 81 | M30: 50 | N30: 75 | O30: 74 | P30: 47 | Q30: 37 | U30: VAN | V30: =AVERAGE(Tableau1[[#This Row],[2024]:[2017]]) -> 5.75 | W30: 6 | X30: 6 | Y30: 8 | Z30: 10 | AA30: 6 | AB30: 4 | AC30: 3 | AD30: 3 | AF30: GEORGIEV | AG30: 103 | AH30: PICARD | AP30: 20-21 | AQ30: LESSARD | AR30: F | AS30: MONAHAN | AT30: 28 | AU30: YES | AX30: FLORIDA | AZ30: 1 | BA30: 122 | BB30: 122
B31: =B30+1 -> 29 | C31: F | D31: KOPITAR | E31: =COUNT(Tableau2[[#This Row],[24]:[17]]) -> 8 | F31: 2 | G31: 1 | H31: =SUM(Tableau2[[#This Row],[24]:[17]]) -> 527 | I31: =IFERROR(AVERAGE(Tableau2[[#This Row],[24]:[17]]),0) -> 65.875 | J31: 70 | K31: 74 | L31: 67 | M31: 50 | N31: 62 | O31: 60 | P31: 92 | Q31: 52 | U31: SEA | V31: =AVERAGE(Tableau1[[#This Row],[2024]:[2017]]) -> 5.6666667 | W31: 6 | X31: 6 | Y31: 5 | Z31: - | AA31: - | AB31: - | AC31: - | AD31: - | AF31: CAROLINA | AG31: 113 | AH31: BLIER | AP31: 16-17 | AQ31: DIEGO | AR31: D | AS31: VLASIC | AT31: 28 | AU31: YES | AX31: PANARIN | AZ31: 1 | BA31: 120 | BB31: 120
B32: =B31+1 -> 30 | C32: F | D32: NYLANDER | E32: =COUNT(Tableau2[[#This Row],[24]:[17]]) -> 8 | H32: =SUM(Tableau2[[#This Row],[24]:[17]]) -> 523 | I32: =IFERROR(AVERAGE(Tableau2[[#This Row],[24]:[17]]),0) -> 65.375 | J32: 98 | K32: 87 | L32: 80 | M32: 50 | N32: 59 | O32: 27 | P32: 61 | Q32: 61 | U32: ANA | V32: =AVERAGE(Tableau1[[#This Row],[2024]:[2017]]) -> 5.5 | W32: 6 | X32: 6 | Y32: 3 | Z32: 2 | AA32: 4 | AB32: 6 | AC32: 9 | AD32: 8 | AG32: =SUM(AG19:AG31) -> 1409 | AP32: 21-22 | AQ32: CONSTANTIN | AR32: D | AS32: EKMAN-LARSSON | AT32: 29 | AU32: YES | AX32: VASILEVSKY | AZ32: 1 | BA32: 119 | BB32: 119
B33: =B32+1 -> 31 | C33: F | D33: POINT | E33: =COUNT(Tableau2[[#This Row],[24]:[17]]) -> 7 | H33: =SUM(Tableau2[[#This Row],[24]:[17]]) -> 513 | I33: =IFERROR(AVERAGE(Tableau2[[#This Row],[24]:[17]]),0) -> 73.285714 | J33: 90 | K33: 95 | L33: 58 | M33: 48 | N33: 64 | O33: 92 | P33: 66 | U33: ARI | V33: =AVERAGE(Tableau1[[#This Row],[2024]:[2017]]) -> 5.25 | W33: 8 | X33: 3 | Y33: 3 | Z33: 4 | AA33: 6 | AB33: 8 | AC33: 5 | AD33: 5 | AP33: 20-21 | AQ33: HENAULT | AR33: F | AS33: KUZNETSOV | AT33: 29 | AU33: YES | AX33: ANDERSEN | AZ33: 2 | BA33: 115 | BB33: 57.5
B34: =B33+1 -> 32 | C34: T | D34: COLORADO | E34: =COUNT(Tableau2[[#This Row],[24]:[17]]) -> 5 | F34: 2 | G34: 1 | H34: =SUM(Tableau2[[#This Row],[24]:[17]]) -> 509 | I34: =IFERROR(AVERAGE(Tableau2[[#This Row],[24]:[17]]),0) -> 101.8 | J34: 107 | K34: 109 | L34: 119 | M34: 82 | N34: 92 | U34: DET | V34: =AVERAGE(Tableau1[[#This Row],[2024]:[2017]]) -> 5.25 | W34: 6 | X34: 7 | Y34: 5 | Z34: 4 | AA34: 3 | AB34: 4 | AC34: 7 | AD34: 6 | AP34: 20-21 | AQ34: BEAUCHEMIN | AR34: F | AS34: MANTHA | AT34: 29 | AU34: YES | AX34: BENN | AZ34: 2 | BA34: 114 | BB34: 57
B35: =B34+1 -> 33 | C35: F | D35: AHO | E35: =COUNT(Tableau2[[#This Row],[24]:[17]]) -> 7 | F35: 1 | H35: =SUM(Tableau2[[#This Row],[24]:[17]]) -> 508 | I35: =IFERROR(AVERAGE(Tableau2[[#This Row],[24]:[17]]),0) -> 72.571429 | J35: 89 | K35: 67 | L35: 81 | M35: 57 | N35: 66 | O35: 83 | P35: 65 | W35: =SUBTOTAL(109,Tableau1[2024]) -> 240 | X35: =SUM(X3:X34) -> 240 | Y35: =SUM(Y3:Y34) -> 240 | Z35: =SUM(Z3:Z34) -> 240 | AA35: =SUM(AA3:AA34) -> 241 | AB35: =SUM(AB3:AB34) -> 241 | AC35: =SUM(AC3:AC34) -> 220 | AD35: =SUM(AD3:AD34) -> 200 | AF35: 2022 ALL STAR TEAM | AP35: 18-19 | AQ35: LESSARD | AR35: F | AS35: OKPOSO | AT35: 29 | AU35: YES | AX35: TAMPA BAY | AZ35: 1 | BA35: 113 | BB35: 113
B36: =B35+1 -> 34 | C36: G | D36: FLEURY | E36: =COUNT(Tableau2[[#This Row],[24]:[17]]) -> 7 | H36: =SUM(Tableau2[[#This Row],[24]:[17]]) -> 508 | I36: =IFERROR(AVERAGE(Tableau2[[#This Row],[24]:[17]]),0) -> 72.571429 | K36: 60 | L36: 77 | M36: 72 | N36: 74 | O36: 103 | P36: 76 | Q36: 46 | AF36: MCDAVID | AG36: 123 | AH36: CONSTANTIN | AP36: 21-22 | AQ36: DESROSIERS | AR36: D | AS36: BRODIN | AT36: 30 | AU36: YES | AX36: DRAISAITL | AZ36: 1 | BA36: 110 | BB36: 110
B37: =B36+1 -> 35 | C37: F | D37: MILLER JT. | E37: =COUNT(Tableau2[[#This Row],[24]:[17]]) -> 7 | H37: =SUM(Tableau2[[#This Row],[24]:[17]]) -> 507 | I37: =IFERROR(AVERAGE(Tableau2[[#This Row],[24]:[17]]),0) -> 72.428571 | J37: 103 | K37: 82 | L37: 99 | M37: 46 | N37: 72 | O37: 47 | P37: 58 | AF37: GAUDREAU | AG37: 115 | AH37: PICARD | AP37: 18-19 | AQ37: MIOUSSE | AR37: D | AS37: BUTCHER | AT37: 30 | AU37: YES | AX37: EDMONTON | AZ37: 1 | BA37: 109 | BB37: 109
B38: =B37+1 -> 36 | C38: F | D38: PAVELSKI | E38: =COUNT(Tableau2[[#This Row],[24]:[17]]) -> 8 | H38: =SUM(Tableau2[[#This Row],[24]:[17]]) -> 505 | I38: =IFERROR(AVERAGE(Tableau2[[#This Row],[24]:[17]]),0) -> 63.125 | J38: 67 | K38: 77 | L38: 81 | M38: 51 | N38: 31 | O38: 64 | P38: 66 | Q38: 68 | AF38: HUBERDEAU | AG38: 115 | AH38: CONSTANTIN | AP38: 19-20 | AQ38: ROBB | AR38: D | AS38: EKMAN-LARSSON | AT38: 30 | AU38: YES | AX38: KARLSSON E. | AZ38: 2 | BA38: 106 | BB38: 53
B39: =B38+1 -> 37 | C39: F | D39: WHEELER | E39: =COUNT(Tableau2[[#This Row],[24]:[17]]) -> 8 | H39: =SUM(Tableau2[[#This Row],[24]:[17]]) -> 503 | I39: =IFERROR(AVERAGE(Tableau2[[#This Row],[24]:[17]]),0) -> 62.875 | J39: 21 | K39: 55 | L39: 60 | M39: 46 | N39: 65 | O39: 91 | P39: 91 | Q39: 74 | AF39: DRAISAITL | AG39: 110 | AH39: CHABOT | AP39: 20-21 | AQ39: DIEGO | AR39: F | AS39: GURIANOV | AT39: 30 | AU39: YES | AX39: DROUIN | AZ39: 2 | BA39: 99 | BB39: 49.5
B40: =B39+1 -> 38 | C40: G | D40: HELLEBUYCK | E40: =COUNT(Tableau2[[#This Row],[24]:[17]]) -> 6 | F40: 1 | H40: =SUM(Tableau2[[#This Row],[24]:[17]]) -> 500 | I40: =IFERROR(AVERAGE(Tableau2[[#This Row],[24]:[17]]),0) -> 83.333333 | J40: 93 | K40: 88 | L40: 84 | M40: 63 | N40: 89 | O40: 83 | AF40: KAPRIZOV | AG40: 108 | AH40: PICARD | AP40: 16-17 | AQ40: CHABOT | AR40: D | AS40: JONES S. | AT40: 42 | AU40: YES | AX40: RIELLY | AZ40: 2 | BA40: 99 | BB40: 49.5
B41: =B40+1 -> 39 | C41: D | D41: HEDMAN | E41: =COUNT(Tableau2[[#This Row],[24]:[17]]) -> 8 | F41: 1 | G41: 4 | H41: =SUM(Tableau2[[#This Row],[24]:[17]]) -> 499 | I41: =IFERROR(AVERAGE(Tableau2[[#This Row],[24]:[17]]),0) -> 62.375 | J41: 76 | K41: 49 | L41: 85 | M41: 45 | N41: 55 | O41: 54 | P41: 63 | Q41: 72 | AF41: MATTHEWS | AG41: 106 | AH41: DIEGO | AP41: 20-21 | AQ41: HENAULT | AR41: F | AS41: KREIDER | AT41: 30 | AU41: YES | AX41: VEGAS | AZ41: 1 | BA41: 98 | BB41: 98
B42: =B41+1 -> 40 | C42: T | D42: BOSTON | E42: =COUNT(Tableau2[[#This Row],[24]:[17]]) -> 5 | G42: 1 | H42: =SUM(Tableau2[[#This Row],[24]:[17]]) -> 496 | I42: =IFERROR(AVERAGE(Tableau2[[#This Row],[24]:[17]]),0) -> 99.2 | J42: 109 | L42: 107 | M42: 73 | N42: 100 | O42: 107 | AF42: STAMKOS | AG42: 106 | AH42: BLIER | AP42: 20-21 | AQ42: CHABOT | AR42: D | AS42: MCAVOY | AT42: 30 | AU42: YES | AX42: KUEMPER | AZ42: 1 | BA42: 93 | BB42: 93
B43: =B42+1 -> 41 | C43: D | D43: JOSI | E43: =COUNT(Tableau2[[#This Row],[24]:[17]]) -> 8 | F43: 1 | G43: 3 | H43: =SUM(Tableau2[[#This Row],[24]:[17]]) -> 496 | I43: =IFERROR(AVERAGE(Tableau2[[#This Row],[24]:[17]]),0) -> 62 | J43: 85 | K43: 59 | L43: 96 | M43: 33 | N43: 65 | O43: 56 | P43: 53 | Q43: 49 | AF43: TKACHUK M | AG43: 104 | AH43: CHABOT | AP43: 20-21 | AQ43: BEAUCHEMIN | AR43: D | AS43: SERGACHEV | AT43: 30 | AU43: YES | AX43: WASHINGTON | AZ43: 1 | BA43: 90 | BB43: 90
B44: =B43+1 -> 42 | C44: F | D44: REINHART | E44: =COUNT(Tableau2[[#This Row],[24]:[17]]) -> 8 | H44: =SUM(Tableau2[[#This Row],[24]:[17]]) -> 495 | I44: =IFERROR(AVERAGE(Tableau2[[#This Row],[24]:[17]]),0) -> 61.875 | J44: 94 | K44: 67 | L44: 82 | M44: 40 | N44: 50 | O44: 65 | P44: 50 | Q44: 47 | AF44: JOSI | AG44: 96 | AH44: DIEGO | AP44: 20-21 | AQ44: DESROSIERS | AR44: F | AS44: TATAR | AT44: 30 | AU44: YES | AX44: SCHEIFELE | AZ44: 1 | BA44: 82 | BB44: 82
B45: =B44+1 -> 43 | C45: F | D45: NUGENT-HOPKINS | E45: =COUNT(Tableau2[[#This Row],[24]:[17]]) -> 8 | H45: =SUM(Tableau2[[#This Row],[24]:[17]]) -> 477 | I45: =IFERROR(AVERAGE(Tableau2[[#This Row],[24]:[17]]),0) -> 59.625 | J45: 67 | K45: 104 | L45: 50 | M45: 35 | N45: 61 | O45: 69 | P45: 48 | Q45: 43 | AF45: MAKAR | AG45: 86 | AH45: MOROTTI | AP45: 18-19 | AQ45: LESSARD | AR45: D | AS45: BYFUGLIEN | AT45: 31 | AU45: YES | AX45: STAAL E. | AZ45: 1 | BA45: 76 | BB45: 76
B46: =B45+1 -> 44 | C46: F | D46: FORSBERG | E46: =COUNT(Tableau2[[#This Row],[24]:[17]]) -> 8 | H46: =SUM(Tableau2[[#This Row],[24]:[17]]) -> 472 | I46: =IFERROR(AVERAGE(Tableau2[[#This Row],[24]:[17]]),0) -> 59 | J46: 94 | K46: 42 | L46: 84 | M46: 32 | N46: 48 | O46: 50 | P46: 64 | Q46: 58 | AF46: HEDMAN | AG46: 85 | AH46: LESSARD | AP46: 20-21 | AQ46: DIEGO | AR46: D | AS46: CHABOT | AT46: 31 | AU46: YES | AX46: KREIDER | AZ46: 1 | BA46: 75 | BB46: 75
B47: =B46+1 -> 45 | C47: G | D47: ANDERSEN | E47: =COUNT(Tableau2[[#This Row],[24]:[17]]) -> 7 | F47: 1 | H47: =SUM(Tableau2[[#This Row],[24]:[17]]) -> 465 | I47: =IFERROR(AVERAGE(Tableau2[[#This Row],[24]:[17]]),0) -> 66.428571 | J47: 37 | K47: 48 | L47: 93 | M47: 31 | N47: 74 | O47: 84 | P47: 98 | AF47: MARKSTROM | AG47: 116 | AH47: BLIER | AP47: 21-22 | AQ47: MIOUSSE | AR47: D | AS47: DOUGHTY | AT47: 31 | AU47: YES | AX47: KADRI | AZ47: 1 | BA47: 75 | BB47: 75
B48: =B47+1 -> 46 | C48: F | D48: LARKIN | E48: =COUNT(Tableau2[[#This Row],[24]:[17]]) -> 8 | H48: =SUM(Tableau2[[#This Row],[24]:[17]]) -> 461 | I48: =IFERROR(AVERAGE(Tableau2[[#This Row],[24]:[17]]),0) -> 57.625 | J48: 69 | K48: 79 | L48: 69 | M48: 23 | N48: 53 | O48: 73 | P48: 63 | Q48: 32 | AF48: FLORIDA | AG48: 122 | AH48: CHABOT | AP48: 20-21 | AQ48: DIEGO | AR48: F | AS48: HUGHES J. | AT48: 31 | AU48: YES | AX48: FOX | AZ48: 1 | BA48: 73 | BB48: 73
B49: =B48+1 -> 47 | C49: F | D49: GUENTZEL | E49: =COUNT(Tableau2[[#This Row],[24]:[17]]) -> 7 | F49: 1 | H49: =SUM(Tableau2[[#This Row],[24]:[17]]) -> 458 | I49: =IFERROR(AVERAGE(Tableau2[[#This Row],[24]:[17]]),0) -> 65.428571 | J49: 77 | K49: 73 | L49: 84 | M49: 57 | N49: 43 | O49: 76 | P49: 48 | AG49: =SUM(AG36:AG48) -> 1392 | AP49: 20-21 | AQ49: DIEGO | AR49: F | AS49: MEIER | AT49: 31 | AU49: YES | AX49: HUGHES Q. | AZ49: 1 | BA49: 68 | BB49: 68
B50: =B49+1 -> 48 | C50: F | D50: EICHEL | E50: =COUNT(Tableau2[[#This Row],[24]:[17]]) -> 8 | H50: =SUM(Tableau2[[#This Row],[24]:[17]]) -> 458 | I50: =IFERROR(AVERAGE(Tableau2[[#This Row],[24]:[17]]),0) -> 57.25 | J50: 68 | K50: 66 | L50: 25 | M50: 18 | N50: 78 | O50: 82 | P50: 64 | Q50: 57 | AP50: 19-20 | AQ50: MIOUSSE | AR50: D | AS50: MORRISSEY | AT50: 31 | AU50: YES | AX50: HEISKANEN | AZ50: 2 | BA50: 68 | BB50: 34
B51: =B50+1 -> 49 | C51: D | D51: BURNS | E51: =COUNT(Tableau2[[#This Row],[24]:[17]]) -> 8 | F51: 1 | G51: 3 | H51: =SUM(Tableau2[[#This Row],[24]:[17]]) -> 458 | I51: =IFERROR(AVERAGE(Tableau2[[#This Row],[24]:[17]]),0) -> 57.25 | J51: 43 | K51: 61 | L51: 54 | M51: 29 | N51: 45 | O51: 83 | P51: 67 | Q51: 76 | AF51: 2021 ALL STAR TEAM | AP51: 18-19 | AQ51: MIOUSSE | AR51: D | AS51: MYERS | AT51: 31 | AU51: YES | AX51: STROME D. | AZ51: 1 | BA51: 67 | BB51: 67
B52: =B51+1 -> 50 | C52: T | D52: VEGAS | E52: =COUNT(Tableau2[[#This Row],[24]:[17]]) -> 5 | H52: =SUM(Tableau2[[#This Row],[24]:[17]]) -> 453 | I52: =IFERROR(AVERAGE(Tableau2[[#This Row],[24]:[17]]),0) -> 90.6 | J52: 98 | L52: 94 | M52: 82 | N52: 86 | O52: 93 | AF52: MCDAVID | AG52: 105 | AH52: DESROSIERS | AP52: 18-19 | AQ52: LESSARD | AR52: F | AS52: NAMESTNIKOV | AT52: 31 | AU52: YES | AX52: GIRARD | AZ52: 2 | BA52: 66 | BB52: 33
B53: =B52+1 -> 51 | C53: F | D53: KUZNETSOV | E53: =COUNT(Tableau2[[#This Row],[24]:[17]]) -> 8 | H53: =SUM(Tableau2[[#This Row],[24]:[17]]) -> 452 | I53: =IFERROR(AVERAGE(Tableau2[[#This Row],[24]:[17]]),0) -> 56.5 | J53: 24 | K53: 55 | L53: 78 | M53: 29 | N53: 52 | O53: 72 | P53: 83 | Q53: 59 | AF53: DRAISAITL | AG53: 84 | AH53: LESSARD | AP53: 21-22 | AQ53: BLIER | AR53: D | AS53: PROVOROV | AT53: 31 | AU53: YES | AX53: REINHART | AZ53: 1 | BA53: 65 | BB53: 65
B54: =B53+1 -> 52 | C54: D | D54: CARLSON | E54: =COUNT(Tableau2[[#This Row],[24]:[17]]) -> 8 | F54: 1 | G54: 2 | H54: =SUM(Tableau2[[#This Row],[24]:[17]]) -> 446 | I54: =IFERROR(AVERAGE(Tableau2[[#This Row],[24]:[17]]),0) -> 55.75 | J54: 52 | K54: 29 | L54: 71 | M54: 44 | N54: 75 | O54: 70 | P54: 68 | Q54: 37 | AF54: MARCHAND | AG54: 69 | AH54: DESROSIERS | AP54: 19-20 | AQ54: HENAULT | AR54: D | AS54: SCHMIDT | AT54: 31 | AU54: YES | AX54: RINNE | AZ54: 1 | BA54: 63 | BB54: 63
B55: =B54+1 -> 53 | C55: F | D55: TROCHECK | E55: =COUNT(Tableau2[[#This Row],[24]:[17]]) -> 8 | F55: 1 | H55: =SUM(Tableau2[[#This Row],[24]:[17]]) -> 436 | I55: =IFERROR(AVERAGE(Tableau2[[#This Row],[24]:[17]]),0) -> 54.5 | J55: 77 | K55: 64 | L55: 51 | M55: 43 | N55: 38 | O55: 34 | P55: 75 | Q55: 54 | AF55: MARNER | AG55: 67 | AH55: CHABOT | AP55: 20-21 | AQ55: HENAULT | AR55: F | AS55: FORSBERG | AT55: 32 | AU55: YES | AX55: VAN RIEMSDYK | AZ55: 1 | BA55: 62 | BB55: 62
B56: =B55+1 -> 54 | C56: T | D56: ST LOUIS | E56: =COUNT(Tableau2[[#This Row],[24]:[17]]) -> 5 | H56: =SUM(Tableau2[[#This Row],[24]:[17]]) -> 436 | I56: =IFERROR(AVERAGE(Tableau2[[#This Row],[24]:[17]]),0) -> 87.2 | K56: 81 | M56: 63 | N56: 94 | O56: 99 | Q56: 99 | AF56: KANE P. | AG56: 66 | AH56: BLIER | AP56: 17-18 | AQ56: BEAUCHEMIN | AR56: D | AS56: FOWLER | AT56: 32 | AU56: YES | AX56: SUBBAN | AZ56: 2 | BA56: 62 | BB56: 31
B57: =B56+1 -> 55 | C57: F | D57: STONE | E57: =COUNT(Tableau2[[#This Row],[24]:[17]]) -> 8 | H57: =SUM(Tableau2[[#This Row],[24]:[17]]) -> 434 | I57: =IFERROR(AVERAGE(Tableau2[[#This Row],[24]:[17]]),0) -> 54.25 | J57: 53 | K57: 38 | L57: 30 | M57: 61 | N57: 63 | O57: 73 | P57: 62 | Q57: 54 | AF57: RANTANEN | AG57: 66 | AH57: CONSTANTIN | AP57: 20-21 | AQ57: CHABOT | AR57: D | AS57: GIRARD | AT57: 32 | AU57: YES | AX57: BURNS | AZ57: 1 | BA57: 61 | BB57: 61
B58: =B57+1 -> 56 | C58: F | D58: SEGUIN | E58: =COUNT(Tableau2[[#This Row],[24]:[17]]) -> 8 | F58: 1 | H58: =SUM(Tableau2[[#This Row],[24]:[17]]) -> 433 | I58: =IFERROR(AVERAGE(Tableau2[[#This Row],[24]:[17]]),0) -> 54.125 | J58: 52 | K58: 50 | L58: 49 | M58: 2 | N58: 50 | O58: 80 | P58: 78 | Q58: 72 | AF58: MATTHEWS | AG58: 66 | AH58: DIEGO | AP58: 20-21 | AQ58: ROBB | AR58: F | AS58: KADRI | AT58: 32 | AU58: YES | AX58: SCHNEIDER | AZ58: 1 | BA58: 57 | BB58: 57
B59: =B58+1 -> 57 | C59: F | D59: DUCHENE | E59: =COUNT(Tableau2[[#This Row],[24]:[17]]) -> 8 | H59: =SUM(Tableau2[[#This Row],[24]:[17]]) -> 432 | I59: =IFERROR(AVERAGE(Tableau2[[#This Row],[24]:[17]]),0) -> 54 | J59: 65 | K59: 56 | L59: 86 | M59: 13 | N59: 42 | O59: 70 | P59: 59 | Q59: 41 | AF59: MACKINNON | AG59: 65 | AH59: BEAUCHEMIN | AP59: 19-20 | AQ59: MIOUSSE | AR59: D | AS59: KLINGBERG | AT59: 32 | AU59: YES | AX59: VORACEK | AZ59: 1 | BA59: 56 | BB59: 56
B60: =B59+1 -> 58 | C60: D | D60: KARLSSON E. | E60: =COUNT(Tableau2[[#This Row],[24]:[17]]) -> 8 | G60: 2 | H60: =SUM(Tableau2[[#This Row],[24]:[17]]) -> 432 | I60: =IFERROR(AVERAGE(Tableau2[[#This Row],[24]:[17]]),0) -> 54 | J60: 56 | K60: 101 | L60: 35 | M60: 22 | N60: 40 | O60: 45 | P60: 62 | Q60: 71 | AF60: BARRIE | AG60: 48 | AH60: PICARD | AP60: 20-21 | AQ60: ROBB | AR60: D | AS60: KRUG | AT60: 32 | AU60: YES | AX60: CALGARY | AZ60: 1 | BA60: 55 | BB60: 55
B61: =B60+1 -> 59 | C61: T | D61: DALLAS | E61: =COUNT(Tableau2[[#This Row],[24]:[17]]) -> 5 | G61: 1 | H61: =SUM(Tableau2[[#This Row],[24]:[17]]) -> 426 | I61: =IFERROR(AVERAGE(Tableau2[[#This Row],[24]:[17]]),0) -> 85.2 | J61: 113 | M61: 60 | N61: 82 | P61: 92 | Q61: 79 | AF61: FOX | AG61: 47 | AH61: BLIER | AP61: 22-23 | AQ61: LESSARD | AR61: D | AS61: KRUG | AT61: 32 | AU61: YES | AX61: TARASENKO | AZ61: 1 | BA61: 55 | BB61: 55
B62: =B61+1 -> 60 | C62: F | D62: CONNOR | E62: =COUNT(Tableau2[[#This Row],[24]:[17]]) -> 6 | H62: =SUM(Tableau2[[#This Row],[24]:[17]]) -> 424 | I62: =IFERROR(AVERAGE(Tableau2[[#This Row],[24]:[17]]),0) -> 70.666667 | J62: 61 | K62: 81 | L62: 93 | M62: 50 | N62: 73 | O62: 66 | AF62: HEDMAN | AG62: 45 | AH62: LESSARD | AP62: 17-18 | AQ62: CHABOT | AR62: D | AS62: MCAVOY | AT62: 32 | AU62: YES | AX62: RADULOV | AZ62: 1 | BA62: 54 | BB62: 54
B63: =B62+1 -> 61 | C63: F | D63: BERGERON | E63: =COUNT(Tableau2[[#This Row],[24]:[17]]) -> 7 | F63: 4 | H63: =SUM(Tableau2[[#This Row],[24]:[17]]) -> 422 | I63: =IFERROR(AVERAGE(Tableau2[[#This Row],[24]:[17]]),0) -> 60.285714 | K63: 58 | L63: 65 | M63: 48 | N63: 56 | O63: 79 | P63: 63 | Q63: 53 | AF63: VASILEVSKI | AG63: 86 | AH63: HENAULT | AP63: 20-21 | AQ63: ROBB | AR63: F | AS63: OLOFSSON | AT63: 32 | AU63: YES | AX63: TROCHECK | AZ63: 1 | BA63: 54 | BB63: 54
B64: =B63+1 -> 62 | C64: F | D64: TARASENKO | E64: =COUNT(Tableau2[[#This Row],[24]:[17]]) -> 8 | F64: 3 | H64: =SUM(Tableau2[[#This Row],[24]:[17]]) -> 420 | I64: =IFERROR(AVERAGE(Tableau2[[#This Row],[24]:[17]]),0) -> 52.5 | J64: 55 | K64: 50 | L64: 82 | M64: 14 | N64: 10 | O64: 68 | P64: 66 | Q64: 75 | AF64: COLORADO | AG64: 82 | AH64: DESROSIERS | AP64: 20-21 | AQ64: HENAULT | AR64: D | AS64: PIONK | AT64: 32 | AU64: YES | AX64: STASTNY | AZ64: 1 | BA64: 53 | BB64: 53
B65: =B64+1 -> 63 | C65: F | D65: EHLERS | E65: =COUNT(Tableau2[[#This Row],[24]:[17]]) -> 8 | F65: 1 | H65: =SUM(Tableau2[[#This Row],[24]:[17]]) -> 419 | I65: =IFERROR(AVERAGE(Tableau2[[#This Row],[24]:[17]]),0) -> 52.375 | J65: 61 | K65: 38 | L65: 55 | M65: 46 | N65: 58 | O65: 37 | P65: 60 | Q65: 64 | AG65: =SUM(AG52:AG64) -> 896 | AP65: 17-18 | AQ65: DIEGO | AR65: D | AS65: VATANEN | AT65: 32 | AU65: YES | AX65: STEEN | AZ65: 1 | BA65: 51 | BB65: 51
B66: =B65+1 -> 64 | C66: F | D66: MARCHESSAULT | E66: =COUNT(Tableau2[[#This Row],[24]:[17]]) -> 7 | H66: =SUM(Tableau2[[#This Row],[24]:[17]]) -> 417 | I66: =IFERROR(AVERAGE(Tableau2[[#This Row],[24]:[17]]),0) -> 59.571429 | J66: 69 | K66: 57 | L66: 66 | M66: 44 | N66: 47 | O66: 59 | P66: 75 | AF66: 2020 ALL STAR TEAM | AP66: 17-18 | AQ66: MOROTTI | AR66: D | AS66: VLASIC | AT66: 32 | AU66: YES | AX66: SHATTENKIRK | AZ66: 2 | BA66: 51 | BB66: 25.5
B67: =B66+1 -> 65 | C67: F | D67: LINDHOLM E. | E67: =COUNT(Tableau2[[#This Row],[24]:[17]]) -> 7 | F67: 1 | H67: =SUM(Tableau2[[#This Row],[24]:[17]]) -> 413 | I67: =IFERROR(AVERAGE(Tableau2[[#This Row],[24]:[17]]),0) -> 59 | J67: 44 | K67: 64 | L67: 82 | M67: 47 | N67: 54 | O67: 78 | P67: 44 | AF67: DRAISAITL | AG67: 110 | AH67: DESROSIERS | AP67: 20-21 | AQ67: MIOUSSE | AR67: D | AS67: DOUGHTY | AT67: 33 | AU67: YES | AX67: KONECNY | AZ67: 1 | BA67: 49 | BB67: 49
B68: =B67+1 -> 66 | C68: F | D68: PETTERSSON | E68: =COUNT(Tableau2[[#This Row],[24]:[17]]) -> 6 | H68: =SUM(Tableau2[[#This Row],[24]:[17]]) -> 412 | I68: =IFERROR(AVERAGE(Tableau2[[#This Row],[24]:[17]]),0) -> 68.666667 | J68: 89 | K68: 102 | L68: 68 | M68: 21 | N68: 66 | O68: 66 | AF68: MCDAVID | AG68: 97 | AH68: DESROSIERS | AP68: 17-18 | AQ68: MOROTTI | AR68: D | AS68: GREEN | AT68: 33 | AU68: YES | AX68: STROME R. | AZ68: 1 | BA68: 49 | BB68: 49
B69: =B68+1 -> 67 | C69: T | D69: FLORIDA | E69: =COUNT(Tableau2[[#This Row],[24]:[17]]) -> 4 | G69: 1 | H69: =SUM(Tableau2[[#This Row],[24]:[17]]) -> 405 | I69: =IFERROR(AVERAGE(Tableau2[[#This Row],[24]:[17]]),0) -> 101.25 | J69: 110 | K69: 92 | L69: 122 | Q69: 81 | AF69: PASTRNAK | AG69: 95 | AH69: MOROTTI | AP69: 20-21 | AQ69: HENAULT | AR69: F | AS69: HALL | AT69: 33 | AU69: YES | AX69: ERIKSSON EK | AZ69: 1 | BA69: 49 | BB69: 49
B70: =B69+1 -> 68 | C70: T | D70: PITTSBURGH | E70: =COUNT(Tableau2[[#This Row],[24]:[17]]) -> 4 | H70: =SUM(Tableau2[[#This Row],[24]:[17]]) -> 402 | I70: =IFERROR(AVERAGE(Tableau2[[#This Row],[24]:[17]]),0) -> 100.5 | K70: 91 | O70: 100 | P70: 100 | Q70: 111 | AF70: PANARIN | AG70: 95 | AH70: BEAUCHEMIN | AP70: 18-19 | AQ70: DIEGO | AR70: D | AS70: HANIFIN | AT70: 33 | AU70: YES | AX70: PALAT | AZ70: 1 | BA70: 49 | BB70: 49
B71: =B70+1 -> 69 | C71: F | D71: ZUCCARELLO | E71: =COUNT(Tableau2[[#This Row],[24]:[17]]) -> 7 | H71: =SUM(Tableau2[[#This Row],[24]:[17]]) -> 398 | I71: =IFERROR(AVERAGE(Tableau2[[#This Row],[24]:[17]]),0) -> 56.857143 | J71: 63 | K71: 67 | L71: 79 | N71: 37 | O71: 40 | P71: 53 | Q71: 59 | AF71: MACKINNON | AG71: 93 | AH71: ROBB | AP71: 18-19 | AQ71: CHABOT | AR71: D | AS71: HEISKANEN | AT71: 33 | AU71: YES | AX71: GRUBAUER | AZ71: 1 | BA71: 46 | BB71: 46
B72: =B71+1 -> 70 | C72: F | D72: O'REILLY | E72: =COUNT(Tableau2[[#This Row],[24]:[17]]) -> 7 | H72: =SUM(Tableau2[[#This Row],[24]:[17]]) -> 396 | I72: =IFERROR(AVERAGE(Tableau2[[#This Row],[24]:[17]]),0) -> 56.571429 | K72: 30 | L72: 58 | M72: 54 | N72: 61 | O72: 77 | P72: 61 | Q72: 55 | AF72: MARCHAND | AG72: 87 | AH72: DESROSIERS | AP72: 20-21 | AQ72: PICARD | AR72: F | AS72: HYMAN | AT72: 33 | AU72: YES | AX72: GUSEV | AZ72: 1 | BA72: 44 | BB72: 44
B73: =B72+1 -> 71 | C73: F | D73: SCHENN | E73: =COUNT(Tableau2[[#This Row],[24]:[17]]) -> 7 | H73: =SUM(Tableau2[[#This Row],[24]:[17]]) -> 396 | I73: =IFERROR(AVERAGE(Tableau2[[#This Row],[24]:[17]]),0) -> 56.571429 | K73: 65 | L73: 58 | M73: 36 | N73: 58 | O73: 54 | P73: 70 | Q73: 55 | AF73: KUCHEROV | AG73: 85 | AH73: DESROSIERS | AP73: 20-21 | AQ73: DIEGO | AR73: D | AS73: JOSI | AT73: 33 | AU73: YES | AX73: LINDHOLM E. | AZ73: 1 | BA73: 44 | BB73: 44
B74: =B73+1 -> 72 | C74: T | D74: EDMONTON | E74: =COUNT(Tableau2[[#This Row],[24]:[17]]) -> 4 | H74: =SUM(Tableau2[[#This Row],[24]:[17]]) -> 395 | I74: =IFERROR(AVERAGE(Tableau2[[#This Row],[24]:[17]]),0) -> 98.75 | J74: 104 | K74: 109 | L74: 104 | P74: 78 | AF74: KANE | AG74: 84 | AH74: MIOUSSE | AP74: 20-21 | AQ74: CONSTANTIN | AR74: F | AS74: KILLORN | AT74: 33 | AU74: YES | AX74: TKACHUK B. | AZ74: 1 | BA74: 44 | BB74: 44
B75: =B74+1 -> 73 | C75: D | D75: LETANG | E75: =COUNT(Tableau2[[#This Row],[24]:[17]]) -> 8 | F75: 1 | H75: =SUM(Tableau2[[#This Row],[24]:[17]]) -> 390 | I75: =IFERROR(AVERAGE(Tableau2[[#This Row],[24]:[17]]),0) -> 48.75 | J75: 51 | K75: 41 | L75: 68 | M75: 45 | N75: 44 | O75: 56 | P75: 51 | Q75: 34 | AF75: CARLSSON | AG75: 75 | AH75: PICARD | AP75: 20-21 | AQ75: PICARD | AR75: F | AS75: NELSON | AT75: 33 | AU75: YES | AX75: JONES S. | AZ75: 1 | BA75: 42 | BB75: 42
B76: =B75+1 -> 74 | C76: F | D76: BACKSTROM | E76: =COUNT(Tableau2[[#This Row],[24]:[17]]) -> 7 | G76: 1 | H76: =SUM(Tableau2[[#This Row],[24]:[17]]) -> 390 | I76: =IFERROR(AVERAGE(Tableau2[[#This Row],[24]:[17]]),0) -> 55.714286 | K76: 21 | L76: 31 | M76: 53 | N76: 54 | O76: 74 | P76: 71 | Q76: 86 | AF76: JOSI | AG76: 65 | AH76: FORCIER | AP76: 19-20 | AQ76: LESSARD | AR76: D | AS76: NURSE | AT76: 33 | AU76: YES | AX76: LEDDY | AZ76: 1 | BA76: 42 | BB76: 42
B77: =B76+1 -> 75 | C77: F | D77: LAINE | E77: =COUNT(Tableau2[[#This Row],[24]:[17]]) -> 8 | H77: =SUM(Tableau2[[#This Row],[24]:[17]]) -> 389 | I77: =IFERROR(AVERAGE(Tableau2[[#This Row],[24]:[17]]),0) -> 48.625 | J77: 9 | K77: 52 | L77: 56 | M77: 24 | N77: 63 | O77: 50 | P77: 71 | Q77: 64 | AF77: HEDMAN | AG77: 55 | AH77: BLIER | AP77: 22-23 | AQ77: MOROTTI | AR77: D | AS77: PIONK | AT77: 33 | AU77: YES | AX77: HENRIQUE | AZ77: 1 | BA77: 40 | BB77: 40
B78: =B77+1 -> 76 | C78: F | D78: DEBRINCAT | E78: =COUNT(Tableau2[[#This Row],[24]:[17]]) -> 6 | H78: =SUM(Tableau2[[#This Row],[24]:[17]]) -> 388 | I78: =IFERROR(AVERAGE(Tableau2[[#This Row],[24]:[17]]),0) -> 64.666667 | J78: 67 | K78: 66 | L78: 78 | M78: 56 | N78: 45 | O78: 76 | AF78: VASILEVSKI | AG78: 90 | AH78: ROBB | AP78: 19-20 | AQ78: FORCIER | AR78: D | AS78: RISTOLAINEN | AT78: 33 | AU78: YES | AX78: KLEFBOM | AZ78: 1 | BA78: 38 | BB78: 38
B79: =B78+1 -> 77 | C79: F | D79: HORVAT | E79: =COUNT(Tableau2[[#This Row],[24]:[17]]) -> 7 | H79: =SUM(Tableau2[[#This Row],[24]:[17]]) -> 387 | I79: =IFERROR(AVERAGE(Tableau2[[#This Row],[24]:[17]]),0) -> 55.285714 | J79: 68 | K79: 70 | L79: 52 | M79: 39 | N79: 53 | O79: 61 | P79: 44 | AF79: BOSTON | AG79: 100 | AH79: MOROTTI | AP79: 22-23 | AQ79: MOROTTI | AR79: D | AS79: SEVERSON | AT79: 33 | AU79: YES | AX79: ZIBANEJAD | AZ79: 1 | BA79: 37 | BB79: 37
B80: =B79+1 -> 78 | C80: G | D80: RASK T. | E80: =COUNT(Tableau2[[#This Row],[24]:[17]]) -> 5 | F80: 2 | H80: =SUM(Tableau2[[#This Row],[24]:[17]]) -> 387 | I80: =IFERROR(AVERAGE(Tableau2[[#This Row],[24]:[17]]),0) -> 77.4 | M80: 42 | N80: 77 | O80: 75 | P80: 86 | Q80: 107 | AG80: =SUM(AG67:AG79) -> 1131 | AP80: 16-17 | AQ80: DESROSIERS | AR80: D | AS80: TROUBA | AT80: 33 | AU80: YES | AX80: WEBER | AZ80: 1 | BA80: 36 | BB80: 36
B81: =B80+1 -> 79 | C81: F | D81: KADRI | E81: =COUNT(Tableau2[[#This Row],[24]:[17]]) -> 7 | H81: =SUM(Tableau2[[#This Row],[24]:[17]]) -> 385 | I81: =IFERROR(AVERAGE(Tableau2[[#This Row],[24]:[17]]),0) -> 55 | J81: 75 | K81: 56 | L81: 87 | M81: 32 | N81: 36 | O81: 44 | P81: 55 | AF81: 2019 ALL STAR TEAM | AP81: 20-21 | AQ81: LESSARD | AR81: F | AS81: TUCH | AT81: 33 | AU81: YES | AX81: DEMKO | AZ81: 1 | BA81: 36 | BB81: 36
B82: =B81+1 -> 80 | C82: F | D82: BENN | E82: =COUNT(Tableau2[[#This Row],[24]:[17]]) -> 7 | H82: =SUM(Tableau2[[#This Row],[24]:[17]]) -> 381 | I82: =IFERROR(AVERAGE(Tableau2[[#This Row],[24]:[17]]),0) -> 54.428571 | J82: 60 | L82: 46 | M82: 35 | N82: 39 | O82: 53 | P82: 79 | Q82: 69 | AF82: KUCHEROV | AG82: 128 | AH82: BEAUCHEMIN | AP82: 20-21 | AQ82: MOROTTI | AR82: F | AS82: ATKINSON | AT82: 34 | AU82: YES | AX82: FARABEE | AZ82: 1 | BA82: 34 | BB82: 34
B83: =B82+1 -> 81 | C83: F | D83: VORACEK | E83: =COUNT(Tableau2[[#This Row],[24]:[17]]) -> 7 | F83: 1 | H83: =SUM(Tableau2[[#This Row],[24]:[17]]) -> 379 | I83: =IFERROR(AVERAGE(Tableau2[[#This Row],[24]:[17]]),0) -> 54.142857 | K83: 6 | L83: 62 | M83: 43 | N83: 56 | O83: 66 | P83: 85 | Q83: 61 | AF83: MCDAVID | AG83: 116 | AH83: DIEGO | AP83: 20-21 | AQ83: BLIER | AR83: F | AS83: KONECNY | AT83: 34 | AU83: YES | AX83: DRYSDALE | AZ83: 2 | BA83: 32 | BB83: 16
B84: =B83+1 -> 82 | C84: F | D84: TERAVAINEN | E84: =COUNT(Tableau2[[#This Row],[24]:[17]]) -> 7 | H84: =SUM(Tableau2[[#This Row],[24]:[17]]) -> 373 | I84: =IFERROR(AVERAGE(Tableau2[[#This Row],[24]:[17]]),0) -> 53.285714 | J84: 53 | K84: 37 | L84: 65 | M84: 15 | N84: 63 | O84: 76 | P84: 64 | AF84: KANE | AG84: 110 | AH84: DESROSIERS | AP84: 19-20 | AQ84: BEAUCHEMIN | AR84: D | AS84: SERGACHEV | AT84: 34 | AU84: YES | AX84: PATRICK | AZ84: 1 | BA84: 31 | BB84: 31
B85: =B84+1 -> 83 | C85: F | D85: KESSEL | E85: =COUNT(Tableau2[[#This Row],[24]:[17]]) -> 6 | F85: 1 | G85: 1 | H85: =SUM(Tableau2[[#This Row],[24]:[17]]) -> 370 | I85: =IFERROR(AVERAGE(Tableau2[[#This Row],[24]:[17]]),0) -> 61.666667 | K85: 36 | L85: 52 | N85: 38 | O85: 82 | P85: 92 | Q85: 70 | AF85: DRAISAITL | AG85: 105 | AH85: DESROSIERS | AP85: 19-20 | AQ85: DESROSIERS | AR85: D | AS85: SHATTENKIRK | AT85: 34 | AU85: YES | AX85: FAULK | AZ85: 1 | BA85: 31 | BB85: 31
B86: =B85+1 -> 84 | C86: F | D86: HALL | E86: =COUNT(Tableau2[[#This Row],[24]:[17]]) -> 8 | G86: 1 | H86: =SUM(Tableau2[[#This Row],[24]:[17]]) -> 369 | I86: =IFERROR(AVERAGE(Tableau2[[#This Row],[24]:[17]]),0) -> 46.125 | J86: 4 | K86: 36 | L86: 61 | M86: 33 | N86: 52 | O86: 37 | P86: 93 | Q86: 53 | AF86: MARCHAND | AG86: 100 | AH86: DESROSIERS | AP86: 22-23 | AQ86: MOROTTI | AR86: D | AS86: SPURGEON | AT86: 34 | AU86: YES | AX86: TURRIS | AZ86: 1 | BA86: 31 | BB86: 31
B87: =B86+1 -> 85 | C87: G | D87: TALBOT | E87: =COUNT(Tableau2[[#This Row],[24]:[17]]) -> 6 | H87: =SUM(Tableau2[[#This Row],[24]:[17]]) -> 362 | I87: =IFERROR(AVERAGE(Tableau2[[#This Row],[24]:[17]]),0) -> 60.333333 | K87: 39 | L87: 79 | N87: 31 | O87: 30 | P87: 70 | Q87: 113 | AF87: CROSBY | AG87: 100 | AH87: BLIER | AP87: 20-21 | AQ87: BLIER | AR87: F | AS87: BAILEY | AT87: 35 | AU87: YES | AX87: GRANLUND | AZ87: 1 | BA87: 30 | BB87: 30
B88: =B87+1 -> 86 | C88: G | D88: MARKSTROM | E88: =COUNT(Tableau2[[#This Row],[24]:[17]]) -> 5 | G88: 1 | H88: =SUM(Tableau2[[#This Row],[24]:[17]]) -> 358 | I88: =IFERROR(AVERAGE(Tableau2[[#This Row],[24]:[17]]),0) -> 71.6 | J88: 64 | K88: 65 | L88: 116 | M88: 55 | N88: 58 | AF88: MACKINNON | AG88: 99 | AH88: FORCIER | AP88: 20-21 | AQ88: CHABOT | AR88: F | AS88: BENN | AT88: 35 | AU88: YES | AX88: TROUBA | AZ88: 1 | BA88: 30 | BB88: 30
B89: =B88+1 -> 87 | C89: F | D89: BARZAL | E89: =COUNT(Tableau2[[#This Row],[24]:[17]]) -> 6 | H89: =SUM(Tableau2[[#This Row],[24]:[17]]) -> 357 | I89: =IFERROR(AVERAGE(Tableau2[[#This Row],[24]:[17]]),0) -> 59.5 | J89: 80 | K89: 51 | L89: 59 | M89: 45 | N89: 60 | O89: 62 | AF89: GAUDREAU | AG89: 99 | AH89: LESSARD | AP89: 19-20 | AQ89: DIEGO | AR89: F | AS89: DEBRUSK | AT89: 35 | AU89: YES | AX89: MALKIN | AZ89: 1 | BA89: 28 | BB89: 28
B90: =B89+1 -> 88 | C90: F | D90: HISCHIER | E90: =COUNT(Tableau2[[#This Row],[24]:[17]]) -> 7 | H90: =SUM(Tableau2[[#This Row],[24]:[17]]) -> 353 | I90: =IFERROR(AVERAGE(Tableau2[[#This Row],[24]:[17]]),0) -> 50.428571 | J90: 67 | K90: 80 | L90: 60 | M90: 11 | N90: 36 | O90: 47 | P90: 52 | AF90: BURNS | AG90: 83 | AH90: LESSARD | AP90: 19-20 | AQ90: ROBB | AR90: D | AS90: DOUGHTY | AT90: 35 | AU90: YES | AX90: MOSER
B91: =B90+1 -> 89 | C91: D | D91: DOUGHTY | E91: =COUNT(Tableau2[[#This Row],[24]:[17]]) -> 8 | H91: =SUM(Tableau2[[#This Row],[24]:[17]]) -> 352 | I91: =IFERROR(AVERAGE(Tableau2[[#This Row],[24]:[17]]),0) -> 44 | J91: 50 | K91: 52 | L91: 31 | M91: 33 | N91: 35 | O91: 45 | P91: 62 | Q91: 44 | AF91: GIORDANO | AG91: 74 | AH91: DESROSIERS | AP91: 21-22 | AQ91: BLIER | AR91: D | AS91: GIORDANO | AT91: 35 | AU91: YES | AX91: MOSER | AY91: 23-24 | AZ91: 1 | BA91: 26 | BB91: 26
B92: =B91+1 -> 90 | C92: D | D92: BARRIE | E92: =COUNT(Tableau2[[#This Row],[24]:[17]]) -> 8 | F92: 2 | G92: 1 | H92: =SUM(Tableau2[[#This Row],[24]:[17]]) -> 352 | I92: =IFERROR(AVERAGE(Tableau2[[#This Row],[24]:[17]]),0) -> 44 | J92: 15 | K92: 55 | L92: 41 | M92: 48 | N92: 39 | O92: 59 | P92: 57 | Q92: 38 | AF92: RIELLY | AG92: 72 | AH92: CHABOT | AP92: 17-18 | AQ92: BLIER | AR92: D | AS92: GOLIGOSKY | AT92: 35 | AU92: YES | AX92: EKMAN-LARSSON | AZ92: 1 | BA92: 24 | BB92: 24
B93: =B92+1 -> 91 | C93: F | D93: KELLER | E93: =COUNT(Tableau2[[#This Row],[24]:[17]]) -> 6 | H93: =SUM(Tableau2[[#This Row],[24]:[17]]) -> 351 | I93: =IFERROR(AVERAGE(Tableau2[[#This Row],[24]:[17]]),0) -> 58.5 | J93: 76 | K93: 86 | L93: 63 | M93: 35 | N93: 44 | O93: 47 | AF93: VASILEVSKI | AG93: 106 | AH93: BEAUCHEMIN | AP93: 19-20 | AQ93: CHABOT | AR93: D | AS93: HEISKANEN | AT93: 35 | AU93: YES | AX93: BRASSARD | AZ93: 1 | BA93: 23 | BB93: 23
B94: =B93+1 -> 92 | C94: F | D94: TKACHUK B. | E94: =COUNT(Tableau2[[#This Row],[24]:[17]]) -> 6 | H94: =SUM(Tableau2[[#This Row],[24]:[17]]) -> 349 | I94: =IFERROR(AVERAGE(Tableau2[[#This Row],[24]:[17]]),0) -> 58.166667 | J94: 74 | K94: 83 | L94: 67 | M94: 36 | N94: 44 | O94: 45 | AF94: TAMPA BAY | AG94: 128 | AH94: PICARD | AP94: 21-22 | AQ94: CHABOT | AR94: D | AS94: KARLSSON E. | AT94: 35 | AU94: YES | AX94: SANDIN
B95: =B94+1 -> 93 | C95: D | D95: PIETRANGELO | E95: =COUNT(Tableau2[[#This Row],[24]:[17]]) -> 8 | H95: =SUM(Tableau2[[#This Row],[24]:[17]]) -> 349 | I95: =IFERROR(AVERAGE(Tableau2[[#This Row],[24]:[17]]),0) -> 43.625 | J95: 33 | K95: 54 | L95: 44 | M95: 23 | N95: 52 | O95: 41 | P95: 54 | Q95: 48 | AG95: =SUM(AG82:AG94) -> 1320 | AP95: 20-21 | AQ95: LESSARD | AR95: F | AS95: KELLER | AT95: 35 | AU95: YES | AX95: SANDIN | AY95: 23-24 | AZ95: 1 | BA95: 23 | BB95: 23
B96: =B95+1 -> 94 | C96: G | D96: HOLTBY | E96: =COUNT(Tableau2[[#This Row],[24]:[17]]) -> 5 | G96: 1 | H96: =SUM(Tableau2[[#This Row],[24]:[17]]) -> 347 | I96: =IFERROR(AVERAGE(Tableau2[[#This Row],[24]:[17]]),0) -> 69.4 | M96: 18 | N96: 58 | O96: 82 | P96: 72 | Q96: 117 | AF96: 2018 ALL STAR TEAM | AP96: 20-21 | AQ96: ROBB | AR96: F | AS96: NUGENT-HOPKINS | AT96: 35 | AU96: YES | AX96: RISTOLAINEN | AZ96: 1 | BA96: 18 | BB96: 18
B97: =B96+1 -> 95 | C97: D | D97: KLINGBERG | E97: =COUNT(Tableau2[[#This Row],[24]:[17]]) -> 8 | G97: 1 | H97: =SUM(Tableau2[[#This Row],[24]:[17]]) -> 343 | I97: =IFERROR(AVERAGE(Tableau2[[#This Row],[24]:[17]]),0) -> 42.875 | J97: 5 | K97: 33 | L97: 47 | M97: 36 | N97: 32 | O97: 74 | P97: 67 | Q97: 49 | AF97: MCDAVID | AG97: 108 | AH97: HENAULT | AP97: 21-22 | AQ97: MIOUSSE | AR97: D | AS97: PARAYKO | AT97: 35 | AU97: YES | AX97: BOQVIST | AZ97: 1 | BA97: 16 | BB97: 16
B98: =B97+1 -> 96 | C98: T | D98: CAROLINA | E98: =COUNT(Tableau2[[#This Row],[24]:[17]]) -> 3 | F98: 1 | G98: 1 | H98: =SUM(Tableau2[[#This Row],[24]:[17]]) -> 340 | I98: =IFERROR(AVERAGE(Tableau2[[#This Row],[24]:[17]]),0) -> 113.33333 | J98: 111 | K98: 113 | L98: 116 | AF98: GIROUX | AG98: 102 | AH98: BEAUCHEMIN | AP98: 22-23 | AQ98: HENAULT | AR98: D | AS98: POWER | AT98: 35 | AU98: YES | AX98: COMTOIS | AZ98: 1 | BA98: 11 | BB98: 11
B99: =B98+1 -> 97 | C99: F | D99: SKINNER | E99: =COUNT(Tableau2[[#This Row],[24]:[17]]) -> 7 | F99: 1 | H99: =SUM(Tableau2[[#This Row],[24]:[17]]) -> 340 | I99: =IFERROR(AVERAGE(Tableau2[[#This Row],[24]:[17]]),0) -> 48.571429 | J99: 46 | K99: 82 | M99: 14 | N99: 23 | O99: 63 | P99: 49 | Q99: 63 | AF99: KUCHEROV | AG99: 100 | AH99: BEAUCHEMIN | AP99: 20-21 | AQ99: BEAUCHEMIN | AR99: D | AS99: RIELLY | AT99: 35 | AU99: YES | AX99: BERTUZZI | AZ99: 1 | BA99: 7 | BB99: 7
B100: =B99+1 -> 98 | C100: D | D100: MAKAR | E100: =COUNT(Tableau2[[#This Row],[24]:[17]]) -> 5 | G100: 2 | H100: =SUM(Tableau2[[#This Row],[24]:[17]]) -> 336 | I100: =IFERROR(AVERAGE(Tableau2[[#This Row],[24]:[17]]),0) -> 67.2 | J100: 90 | K100: 66 | L100: 86 | M100: 44 | N100: 50 | AF100: MALKIN | AG100: 98 | AH100: FORCIER | AP100: 17-18 | AQ100: DIEGO | AR100: F | AS100: SAAD | AT100: 35 | AU100: YES | AX100: FABBRI | AZ100: 1 | BA100: 6 | BB100: 6
B101: =B100+1 -> 99 | C101: F | D101: TOFFOLI | E101: =COUNT(Tableau2[[#This Row],[24]:[17]]) -> 7 | H101: =SUM(Tableau2[[#This Row],[24]:[17]]) -> 336 | I101: =IFERROR(AVERAGE(Tableau2[[#This Row],[24]:[17]]),0) -> 48 | J101: 55 | K101: 73 | L101: 49 | M101: 44 | O101: 34 | P101: 47 | Q101: 34 | AF101: MACKINNON | AG101: 97 | AH101: FORCIER | AP101: 20-21 | AQ101: MIOUSSE | AR101: G | AS101: SAMSONOV | AT101: 35 | AU101: YES | AX101: SHIPACHYOV | AZ101: 1 | BA101: 1 | BB101: 1
...

Sheet TRIV
B2: Rookies | I2: Best Non Drafted Team | S2: AGE AVG | T2: AVG | U2: 24 | V2: 23 | W2: 22 | X2: 21 | Y2: 20 | Z2: 19 | AA2: 18 | AB2: 17 | AE2: Build of a Champ | AL2: 2024 | AM2: POS | AN2: DRAFT | AO2: PG | AP2: PTS | AR2: ROOKIE OF THE YEAR
B3: 2024 | C3: POS | D3: DRAFT | E3: PG | F3: PTS | I3: 2024 | J3: PG | K3: PTS | L3: 2023 | M3: PG | N3: PTS | O3: 2022 | P3: PG | Q3: PTS | S3: CHABOT | T3: =AVERAGE(U3:AB3) -> 25.216118 | U3: 27 | V3: 25.578947 | W3: 25.4 | X3: 24.4 | Y3: 25.05 | Z3: 23.4 | AA3: 25.2 | AB3: 25.7 | AE3: Player | AF3: PTS | AG3: Acquired | AH3: Year | AI3: PICK | AL3: BEDARD | AM3: F | AN3: HENAULT | AO3: 68 | AP3: 61 | AR3: YEAR | AS3: PLAYER | AT3: POS | AU3: DRAFT | AV3: PG | AW3: PTS
B4: BEDARD | C4: F | D4: HENAULT | E4: 68 | F4: 61 | I4: NYQUIST | J4: 81 | K4: 75 | L4: BENN | M4: 82 | N4: 78 | O4: KREIDER | P4: 81 | Q4: 77 | S4: BEAUCHEMIN | T4: =AVERAGE(U4:AB4) -> 25.686118 | U4: 25.21 | V4: 24.578947 | W4: 24 | X4: 25.2 | Y4: 26.4 | Z4: 25.2 | AA4: 26.5 | AB4: 28.4 | AE4: TKACHUK M. | AF4: 80 | AG4: DRAFT | AH4: 2023 | AI4: 7 | AL4: HUGHES L | AM4: D | AN4: CONSTANTIN | AO4: 82 | AP4: 47 | AR4: 2024 | AS4: BEDARD | AT4: F | AU4: HENAULT | AV4: 68 | AW4: 61
B5: HUGHES L | C5: D | D5: CONSTANTIN | E5: 82 | F5: 47 | I5: O'REILLY | J5: 82 | K5: 69 | L5: KUZMENKO | M5: 81 | N5: 74 | O5: BRATT | P5: 76 | Q5: 73 | S5: DIEGO | T5: =AVERAGE(U5:AB5) -> 25.925132 | U5: 26.58 | V5: 24.421053 | W5: 25.4 | X5: 23.7 | Y5: 23.9 | Z5: 26.9 | AA5: 27.2 | AB5: 29.3 | AE5: MATTHEWS | AF5: 98 | AG5: DRAFT | AH5: 2022 | AI5: 3 | AL5: COOLEY | AM5: F | AN5: DESROSIERS | AO5: 82 | AP5: 44 | AR5: 2023 | AS5: BENIERS | AT5: F | AU5: MIOUSSE | AV5: 80 | AW5: 57
B6: COOLEY | C6: F | D6: DESROSIERS | E6: 82 | F6: 44 | I6: JARVIS | J6: 81 | K6: 67 | L6: MCCAN | M6: 79 | N6: 70 | O6: THOMPSON | P6: 78 | Q6: 68 | S6: HENAULT | T6: =AVERAGE(U6:AB6) -> 26.047566 | U6: 24.47 | V6: 25.210526 | W6: 26.8 | X6: 26.3 | Y6: 27.2 | Z6: 27.7 | AA6: 25 | AB6: 25.7 | AE6: GUENTZEL | AF6: 68 | AG6: DRAFT | AH6: 2017 | AI6: 20 | AL6: KNIES | AM6: F | AN6: BEAUCHEMIN | AO6: 80 | AP6: 35 | AR6: =AR5-1 -> 2022 | AS6: ZEGRAS | AT6: F | AU6: PICARD | AV6: 75 | AW6: 61
B7: KNIES | C7: F | D7: BEAUCHEMIN | E7: 80 | F7: 35 | I7: GRANLUND M. | J7: 69 | K7: 60 | L7: COZENS | M7: 81 | N7: 68 | O7: TERRY | P7: 75 | Q7: 67 | S7: ROBB | T7: =AVERAGE(U7:AB7) -> 26.388737 | U7: 26.47 | V7: 25.473684 | W7: 27.5 | X7: 26.6 | Y7: 25.9 | Z7: - | AA7: - | AB7: - | AE7: AHO | AF7: 85 | AG7: DRAFT | AH7: 2017 | AI7: 29 | AL7: CARLSSON | AM7: F | AN7: DESROSIERS | AO7: 55 | AP7: 29 | AR7: =AR6-1 -> 2021 | AS7: KAPRIZOV | AT7: F | AU7: PICARD | AV7: 55 | AW7: 51
B8: CARLSSON | C8: F | D8: DESROSIERS | E8: 55 | F8: 29 | I8: COYLE | J8: 82 | K8: 60 | L8: COUTURE | M8: 82 | N8: 67 | O8: HARTMAN | P8: 82 | Q8: 65 | S8: ROB/DAV | T8: =AVERAGE(U8:AB8) -> 26.640614 | U8: 26.47 | V8: 25.473684 | W8: 27.5 | X8: 26.6 | Y8: 25.9 | Z8: 27.9 | AA8: - | AB8: - | AE8: KEMPE | AF8: 66 | AG8: DRAFT | AH8: 2022 | AI8: 99 | AL8: FANTILLI | AM8: F | AN8: DESROSIERS | AO8: 49 | AP8: 27 | AR8: =AR7-1 -> 2020 | AS8: HUGHES Q. | AT8: D | AU8: FORCIER | AV8: 68 | AW8: 53
B9: FANTILLI | C9: F | D9: DESROSIERS | E9: 49 | F9: 27 | I9: VATRANO | J9: 82 | K9: 60 | L9: STROME D. | M9: 81 | N9: 65 | O9: GRANLUND | P9: 80 | Q9: 64 | S9: MIOUSSE | T9: =AVERAGE(U9:AB9) -> 27.392237 | U9: 28.58 | V9: 27.157895 | W9: 27.3 | X9: 28 | Y9: 27.1 | Z9: 25.7 | AA9: 26.5 | AB9: 28.8 | AE9: BENIERS | AF9: 33 | AG9: DRAFT | AH9: 2022 | AI9: 39 | AL9: LEVI | AM9: G | AN9: BEAUCHEMIN | AO9: 23 | AP9: 22 | AR9: =AR8-1 -> 2019 | AS9: PETTERSSON | AT9: F | AU9: BLIER | AV9: 71 | AW9: 66
B10: LEVI | C10: G | D10: BEAUCHEMIN | E10: 23 | F10: 22 | I10: SHARANGOVICH | J10: 82 | K10: 59 | L10: KILLORN | M10: 82 | N10: 65 | O10: SKINNER | P10: 80 | Q10: 63 | S10: DESROSIERS | T10: =AVERAGE(U10:AB10) -> 27.475395 | U10: 22.74 | V10: 29.263158 | W10: 30 | X10: 27.4 | Y10: 28.4 | Z10: 29 | AA10: 26.4 | AB10: 26.6 | AE10: BJORKSTRAND | AF10: 52 | AG10: DRAFT | AH10: 2022 | AI10: 87 | AL10: ZELLWEGER | AM10: D | AN10: DESROSIERS | AO10: 26 | AP10: 9 | AR10: =AR9-1 -> 2018 | AS10: HISCHIER | AT10: F | AU10: DESROSIERS | AV10: 82 | AW10: 52
